DSDL9/final/src/tcam_entry.v
`timescale 1ns/1ps
`default_nettype none

// One DATA_WIDTH-bit ternary memory entry.
// A 1 in stored_x_mask makes the corresponding stored bit a X.
module tcam_entry #(
    parameter integer DATA_WIDTH = 16
) (
    input  wire                  clk,
    input  wire                  reset,
    input  wire                  write_enable,
    input  wire [DATA_WIDTH-1:0] write_data,
    input  wire [DATA_WIDTH-1:0] write_x_mask,
    input  wire [DATA_WIDTH-1:0] search_data,
    output wire                  match
);
    reg [DATA_WIDTH-1:0] stored_data;       // Caputered data from write_data
    reg [DATA_WIDTH-1:0] stored_x_mask;     // Captured mask
    reg                  valid;             // Single bit valid, some tests show invalid cases

    wire [DATA_WIDTH-1:0] mismatched_bits;  // Bits that didn't match

    always @(posedge clk) begin
        if (reset) begin
            valid <= 1'b0;
        end else if (write_enable) begin
            stored_data <= write_data;
            stored_x_mask <= write_x_mask;
            valid <= 1'b1;
        end
    end

    // Masked positions are removed before checking for unequal bits.
    assign mismatched_bits = (search_data ^ stored_data) & ~stored_x_mask;
    assign match = valid && (mismatched_bits == {DATA_WIDTH{1'b0}});
endmodule

`default_nettype wire

DSDL9/final/quartus/tcam_no_loop.v
`timescale 1ns/1ps
`default_nettype none

// Parallel-write TCAM with an instance array and no for loop.
// The packed data/mask buses are split across entries; search_data is shared.
module tcam_no_loop #(
    parameter integer DATA_WIDTH = 4,
    parameter integer DEPTH = 4
) (
    input  wire                         clk,
    input  wire                         reset,
    input  wire [DEPTH-1:0]             write_enable,
    input  wire [DEPTH*DATA_WIDTH-1:0]  write_data,
    input  wire [DEPTH*DATA_WIDTH-1:0]  write_x_mask,
    input  wire [DATA_WIDTH-1:0]        search_data,
    output wire [DEPTH-1:0]             match_lines
);
    generate
        if (DATA_WIDTH < 1 || DEPTH < 1) begin : invalid_parameters
            initial $fatal(1, "TCAM requires DATA_WIDTH >= 1 and DEPTH >= 1");
        end else begin : valid_parameters
            tcam_entry #(.DATA_WIDTH(DATA_WIDTH)) entries [DEPTH-1:0] (
                .clk(clk),
                .reset(reset),
                .write_enable(write_enable),
                .write_data(write_data),
                .write_x_mask(write_x_mask),
                .search_data(search_data),
                .match(match_lines)
            );
        end
    endgenerate
endmodule

`default_nettype wire

DSDL9/final/quartus/tcam.v
`timescale 1ns/1ps
`default_nettype none

// Each enabled row stores its own data and X mask on the same rising edge. Meaning multiple registers with defined
// Data width on a single store.
// Row i uses write_data[i*DATA_WIDTH +: DATA_WIDTH] with the same mask slice.
module tcam #(
    parameter integer DATA_WIDTH = 4,
    parameter integer DEPTH = 4
) (
    input  wire                         clk,
    input  wire                         reset,
    input  wire [DEPTH-1:0]             write_enable,
    input  wire [DEPTH*DATA_WIDTH-1:0]  write_data,     // Data of all registers
    input  wire [DEPTH*DATA_WIDTH-1:0]  write_x_mask,   // X values for all registers
    input  wire [DATA_WIDTH-1:0]        search_data,    // Data we comparing with
    output wire [DEPTH-1:0]             match_lines     // Registers matched
);
    genvar row;

    generate
        if (DATA_WIDTH < 1 || DEPTH < 1) begin : invalid_parameters
            initial $fatal(1, "TCAM requires DATA_WIDTH >= 1 and DEPTH >= 1");
        end else begin : valid_parameters
            for (row = 0; row < DEPTH; row = row + 1) begin : entries
                tcam_entry #(.DATA_WIDTH(DATA_WIDTH)) entry (
                    .clk(clk),
                    .reset(reset),
                    .write_enable(write_enable[row]),
                    .write_data(write_data[row*DATA_WIDTH +: DATA_WIDTH]),
                    .write_x_mask(write_x_mask[row*DATA_WIDTH +: DATA_WIDTH]),
                    .search_data(search_data),
                    .match(match_lines[row])
                );
            end
        end
    endgenerate
endmodule

`default_nettype wire

DSDL9/tb_tcam_4x3.v
`timescale 1ns/1ps
`default_nettype none

// 4 x 3 exact and independent wildcard masks
module tb_tcam_4x3;
    localparam integer DATA_WIDTH = 3;
    localparam integer DEPTH = 4;
    reg clk = 1'b0;
    reg reset = 1'b1;
    reg [DEPTH-1:0] write_enable = 0;
    reg [DEPTH*DATA_WIDTH-1:0] write_data = 0;
    reg [DEPTH*DATA_WIDTH-1:0] write_x_mask = 0;
    reg [DATA_WIDTH-1:0] search_data = 0;
    wire [DEPTH-1:0] match_loop;
    wire [DEPTH-1:0] match_no_loop;

    tcam #(.DATA_WIDTH(DATA_WIDTH), .DEPTH(DEPTH)) loop (
        .clk(clk), .reset(reset), .write_enable(write_enable),
        .write_data(write_data), .write_x_mask(write_x_mask),
        .search_data(search_data), .match_lines(match_loop)
    );
    tcam_no_loop #(.DATA_WIDTH(DATA_WIDTH), .DEPTH(DEPTH)) no_loop (
        .clk(clk), .reset(reset), .write_enable(write_enable),
        .write_data(write_data), .write_x_mask(write_x_mask),
        .search_data(search_data), .match_lines(match_no_loop)
    );

    always #5 clk = ~clk;

    task check_search;
        input [DATA_WIDTH-1:0] data;
        input [DEPTH-1:0] expected;
        begin
            search_data = data;
            #1;
            if (match_loop !== expected || match_no_loop !== expected)
                $fatal(1, "Search %h: expected %h, loop %h, no-loop %h",
                       data, expected, match_loop, match_no_loop);
            #9; // Keep each result visible in GTKWave.
        end
    endtask

    initial begin
        $dumpfile("build/tb_tcam_4x3.vcd");
        $dumpvars(0, tb_tcam_4x3);
        @(posedge clk);
        #1 reset = 1'b0;

        @(negedge clk);
        // Rows 3..0 contain 111, 10X, X10, 001.
        write_data = {3'b111, 3'b100, 3'b010, 3'b001};
        write_x_mask = {3'b000, 3'b001, 3'b100, 3'b000};
        write_enable = 4'b1111;
        @(posedge clk);
        #1 write_enable = 4'b0000;

        // Exhaust every possible 3-bit search key.
        check_search(3'b000, 4'b0000);
        check_search(3'b001, 4'b0001);
        check_search(3'b010, 4'b0010);
        check_search(3'b011, 4'b0000);
        check_search(3'b100, 4'b0100);
        check_search(3'b101, 4'b0100);
        check_search(3'b110, 4'b0010);
        check_search(3'b111, 4'b1000);

        $display("PASS: 4 x 3 exact and independent wildcard masks (both implementations)");
        $finish;
    end
endmodule

`default_nettype wire

DSDL9/final/build/tb_tcam_4x3.vcd
$date
	Sat Sep 12 09:50:56 2026
$end
$version
	Icarus Verilog
$end
$timescale
	1ps
$end
$scope module tb_tcam_4x3 $end
$var wire 4 ! match_no_loop [3:0] $end
$var wire 4 " match_loop [3:0] $end
$var parameter 32 # DATA_WIDTH $end
$var parameter 32 $ DEPTH $end
$var reg 1 % clk $end
$var reg 1 & reset $end
$var reg 3 ' search_data [2:0] $end
$var reg 12 ( write_data [11:0] $end
$var reg 4 ) write_enable [3:0] $end
$var reg 12 * write_x_mask [11:0] $end
$scope module loop $end
$var wire 1 % clk $end
$var wire 1 & reset $end
$var wire 3 + search_data [2:0] $end
$var wire 12 , write_data [11:0] $end
$var wire 4 - write_enable [3:0] $end
$var wire 12 . write_x_mask [11:0] $end
$var wire 4 / match_lines [3:0] $end
$var parameter 32 0 DATA_WIDTH $end
$var parameter 32 1 DEPTH $end
$scope begin valid_parameters $end
$scope begin entries[0] $end
$var parameter 2 2 row $end
$scope module entry $end
$var wire 1 % clk $end
$var wire 1 3 match $end
$var wire 3 4 mismatched_bits [2:0] $end
$var wire 1 & reset $end
$var wire 3 5 search_data [2:0] $end
$var wire 3 6 write_data [2:0] $end
$var wire 1 7 write_enable $end
$var wire 3 8 write_x_mask [2:0] $end
$var parameter 32 9 DATA_WIDTH $end
$var reg 3 : stored_data [2:0] $end
$var reg 3 ; stored_x_mask [2:0] $end
$var reg 1 < valid $end
$upscope $end
$upscope $end
$scope begin entries[1] $end
$var parameter 2 = row $end
$scope module entry $end
$var wire 1 % clk $end
$var wire 1 > match $end
$var wire 3 ? mismatched_bits [2:0] $end
$var wire 1 & reset $end
$var wire 3 @ search_data [2:0] $end
$var wire 3 A write_data [2:0] $end
$var wire 1 B write_enable $end
$var wire 3 C write_x_mask [2:0] $end
$var parameter 32 D DATA_WIDTH $end
$var reg 3 E stored_data [2:0] $end
$var reg 3 F stored_x_mask [2:0] $end
$var reg 1 G valid $end
$upscope $end
$upscope $end
$scope begin entries[2] $end
$var parameter 3 H row $end
$scope module entry $end
$var wire 1 % clk $end
$var wire 1 I match $end
$var wire 3 J mismatched_bits [2:0] $end
$var wire 1 & reset $end
$var wire 3 K search_data [2:0] $end
$var wire 3 L write_data [2:0] $end
$var wire 1 M write_enable $end
$var wire 3 N write_x_mask [2:0] $end
$var parameter 32 O DATA_WIDTH $end
$var reg 3 P stored_data [2:0] $end
$var reg 3 Q stored_x_mask [2:0] $end
$var reg 1 R valid $end
$upscope $end
$upscope $end
$scope begin entries[3] $end
$var parameter 3 S row $end
$scope module entry $end
$var wire 1 % clk $end
$var wire 1 T match $end
$var wire 3 U mismatched_bits [2:0] $end
$var wire 1 & reset $end
$var wire 3 V search_data [2:0] $end
$var wire 3 W write_data [2:0] $end
$var wire 1 X write_enable $end
$var wire 3 Y write_x_mask [2:0] $end
$var parameter 32 Z DATA_WIDTH $end
$var reg 3 [ stored_data [2:0] $end
$var reg 3 \ stored_x_mask [2:0] $end
$var reg 1 ] valid $end
$upscope $end
$upscope $end
$upscope $end
$upscope $end
$scope module no_loop $end
$var wire 1 % clk $end
$var wire 1 & reset $end
$var wire 3 ^ search_data [2:0] $end
$var wire 12 _ write_data [11:0] $end
$var wire 4 ` write_enable [3:0] $end
$var wire 12 a write_x_mask [11:0] $end
$var wire 4 b match_lines [3:0] $end
$var parameter 32 c DATA_WIDTH $end
$var parameter 32 d DEPTH $end
$scope begin valid_parameters $end
$scope module entries[0] $end
$var wire 1 % clk $end
$var wire 1 e match $end
$var wire 3 f mismatched_bits [2:0] $end
$var wire 1 & reset $end
$var wire 3 g search_data [2:0] $end
$var wire 3 h write_data [2:0] $end
$var wire 1 i write_enable $end
$var wire 3 j write_x_mask [2:0] $end
$var parameter 32 k DATA_WIDTH $end
$var reg 3 l stored_data [2:0] $end
$var reg 3 m stored_x_mask [2:0] $end
$var reg 1 n valid $end
$upscope $end
$scope module entries[1] $end
$var wire 1 % clk $end
$var wire 1 o match $end
$var wire 3 p mismatched_bits [2:0] $end
$var wire 1 & reset $end
$var wire 3 q search_data [2:0] $end
$var wire 3 r write_data [2:0] $end
$var wire 1 s write_enable $end
$var wire 3 t write_x_mask [2:0] $end
$var parameter 32 u DATA_WIDTH $end
$var reg 3 v stored_data [2:0] $end
$var reg 3 w stored_x_mask [2:0] $end
$var reg 1 x valid $end
$upscope $end
$scope module entries[2] $end
$var wire 1 % clk $end
$var wire 1 y match $end
$var wire 3 z mismatched_bits [2:0] $end
$var wire 1 & reset $end
$var wire 3 { search_data [2:0] $end
$var wire 3 | write_data [2:0] $end
$var wire 1 } write_enable $end
$var wire 3 ~ write_x_mask [2:0] $end
$var parameter 32 !" DATA_WIDTH $end
$var reg 3 "" stored_data [2:0] $end
$var reg 3 #" stored_x_mask [2:0] $end
$var reg 1 $" valid $end
$upscope $end
$scope module entries[3] $end
$var wire 1 % clk $end
$var wire 1 %" match $end
$var wire 3 &" mismatched_bits [2:0] $end
$var wire 1 & reset $end
$var wire 3 '" search_data [2:0] $end
$var wire 3 (" write_data [2:0] $end
$var wire 1 )" write_enable $end
$var wire 3 *" write_x_mask [2:0] $end
$var parameter 32 +" DATA_WIDTH $end
$var reg 3 ," stored_data [2:0] $end
$var reg 3 -" stored_x_mask [2:0] $end
$var reg 1 ." valid $end
$upscope $end
$upscope $end
$upscope $end
$scope task check_search $end
$var reg 3 /" data [2:0] $end
$var reg 4 0" expected [3:0] $end
$upscope $end
$upscope $end
$enddefinitions $end
$comment Show the parameter values. $end
$dumpall
b11 +"
b11 !"
b11 u
b11 k
b100 d
b11 c
b11 Z
b11 S
b11 O
b10 H
b11 D
b1 =
b11 9
b0 2
b100 1
b11 0
b100 $
b11 #
$end
#0
$dumpvars
bx 0"
bx /"
x."
bx -"
bx ,"
b0 *"
0)"
b0 ("
b0 '"
bx &"
x%"
x$"
bx #"
bx ""
b0 ~
0}
b0 |
b0 {
bx z
xy
xx
bx w
bx v
b0 t
0s
b0 r
b0 q
bx p
xo
xn
bx m
bx l
b0 j
0i
b0 h
b0 g
bx f
xe
bx b
b0 a
b0 `
b0 _
b0 ^
x]
bx \
bx [
b0 Y
0X
b0 W
b0 V
bx U
xT
xR
bx Q
bx P
b0 N
0M
b0 L
b0 K
bx J
xI
xG
bx F
bx E
b0 C
0B
b0 A
b0 @
bx ?
x>
x<
bx ;
bx :
b0 8
07
b0 6
b0 5
bx 4
x3
bx /
b0 .
b0 -
b0 ,
b0 +
b0 *
b0 )
b0 (
b0 '
1&
0%
bx "
bx !
$end
#5000
03
0>
0I
b0 "
b0 /
0T
0e
0o
0y
b0 !
b0 b
0%"
0<
0G
0R
0]
0n
0x
0$"
0."
1%
#6000
0&
#10000
17
1B
1M
1X
1i
1s
1}
1)"
b100 C
b1 N
b100 t
b1 ~
b1 6
b10 A
b100 L
b111 W
b1 h
b10 r
b100 |
b111 ("
b1111 )
b1111 -
b1111 `
b1100000 *
b1100000 .
b1100000 a
b111100010001 (
b111100010001 ,
b111100010001 _
0%
#15000
b111 &"
b100 z
b10 p
b1 f
b111 U
b100 J
b10 ?
b1 4
0%"
0y
0o
b0 !
b0 b
0e
0T
0I
0>
b0 "
b0 /
03
1."
b0 -"
b111 ,"
1$"
b1 #"
b100 ""
1x
b100 w
b10 v
1n
b0 m
b1 l
1]
b0 \
b111 [
1R
b1 Q
b100 P
1G
b100 F
b10 E
1<
b0 ;
b1 :
1%
#16000
07
0B
0M
0X
0i
0s
0}
0)"
b0 0"
b0 /"
b0 )
b0 -
b0 `
#20000
0%
#25000
1%
#26000
b1 "
b1 /
13
b1 !
b1 b
1e
b0 4
b11 ?
b110 U
b0 f
b11 p
b110 &"
b1 '
b1 +
b1 5
b1 @
b1 K
b1 V
b1 ^
b1 g
b1 q
b1 {
b1 '"
b1 0"
b1 /"
#30000
0%
#35000
1%
#36000
03
b10 "
b10 /
1>
0e
b10 !
b10 b
1o
b11 4
b0 ?
b110 J
b101 U
b11 f
b0 p
b110 z
b101 &"
b10 '
b10 +
b10 5
b10 @
b10 K
b10 V
b10 ^
b10 g
b10 q
b10 {
b10 '"
b10 0"
b10 /"
#40000
0%
#45000
1%
#46000
b0 "
b0 /
0>
b0 !
b0 b
0o
b10 4
b1 ?
b100 U
b10 f
b1 p
b100 &"
b11 '
b11 +
b11 5
b11 @
b11 K
b11 V
b11 ^
b11 g
b11 q
b11 {
b11 '"
b0 0"
b11 /"
#50000
0%
#55000
1%
#56000
b100 "
b100 /
1I
b100 !
b100 b
1y
b101 4
b10 ?
b0 J
b11 U
b101 f
b10 p
b0 z
b11 &"
b100 '
b100 +
b100 5
b100 @
b100 K
b100 V
b100 ^
b100 g
b100 q
b100 {
b100 '"
b100 0"
b100 /"
#60000
0%
#65000
1%
#66000
b100 4
b11 ?
b10 U
b100 f
b11 p
b10 &"
b101 '
b101 +
b101 5
b101 @
b101 K
b101 V
b101 ^
b101 g
b101 q
b101 {
b101 '"
b101 /"
#70000
0%
#75000
1%
#76000
1>
b10 "
b10 /
0I
1o
b10 !
b10 b
0y
b111 4
b0 ?
b10 J
b1 U
b111 f
b0 p
b10 z
b1 &"
b110 '
b110 +
b110 5
b110 @
b110 K
b110 V
b110 ^
b110 g
b110 q
b110 {
b110 '"
b10 0"
b110 /"
#80000
0%
#85000
1%
#86000
0>
b1000 "
b1000 /
1T
0o
b1000 !
b1000 b
1%"
b110 4
b1 ?
b0 U
b110 f
b1 p
b0 &"
b111 '
b111 +
b111 5
b111 @
b111 K
b111 V
b111 ^
b111 g
b111 q
b111 {
b111 '"
b1000 0"
b111 /"
