DSDL9/final/src/tcam_entry.v
`timescale 1ns/1ps
`default_nettype none

// One DATA_WIDTH-bit ternary memory entry.
// A 1 in stored_x_mask makes the corresponding stored bit a X.
module tcam_entry #(
    parameter integer DATA_WIDTH = 16
) (
    input  wire                  clk,
    input  wire                  reset,
    input  wire                  write_enable,
    input  wire [DATA_WIDTH-1:0] write_data,
    input  wire [DATA_WIDTH-1:0] write_x_mask,
    input  wire [DATA_WIDTH-1:0] search_data,
    output wire                  match
);
    reg [DATA_WIDTH-1:0] stored_data;       // Caputered data from write_data
    reg [DATA_WIDTH-1:0] stored_x_mask;     // Captured mask
    reg                  valid;             // Single bit valid, some tests show invalid cases

    wire [DATA_WIDTH-1:0] mismatched_bits;  // Bits that didn't match

    always @(posedge clk) begin
        if (reset) begin
            valid <= 1'b0;
        end else if (write_enable) begin
            stored_data <= write_data;
            stored_x_mask <= write_x_mask;
            valid <= 1'b1;
        end
    end

    // Masked positions are removed before checking for unequal bits.
    assign mismatched_bits = (search_data ^ stored_data) & ~stored_x_mask;
    assign match = valid && (mismatched_bits == {DATA_WIDTH{1'b0}});
endmodule

`default_nettype wire

DSDL9/final/quartus/tcam_no_loop.v
`timescale 1ns/1ps
`default_nettype none

// Parallel-write TCAM with an instance array and no for loop.
// The packed data/mask buses are split across entries; search_data is shared.
module tcam_no_loop #(
    parameter integer DATA_WIDTH = 4,
    parameter integer DEPTH = 4
) (
    input  wire                         clk,
    input  wire                         reset,
    input  wire [DEPTH-1:0]             write_enable,
    input  wire [DEPTH*DATA_WIDTH-1:0]  write_data,
    input  wire [DEPTH*DATA_WIDTH-1:0]  write_x_mask,
    input  wire [DATA_WIDTH-1:0]        search_data,
    output wire [DEPTH-1:0]             match_lines
);
    generate
        if (DATA_WIDTH < 1 || DEPTH < 1) begin : invalid_parameters
            initial $fatal(1, "TCAM requires DATA_WIDTH >= 1 and DEPTH >= 1");
        end else begin : valid_parameters
            tcam_entry #(.DATA_WIDTH(DATA_WIDTH)) entries [DEPTH-1:0] (
                .clk(clk),
                .reset(reset),
                .write_enable(write_enable),
                .write_data(write_data),
                .write_x_mask(write_x_mask),
                .search_data(search_data),
                .match(match_lines)
            );
        end
    endgenerate
endmodule

`default_nettype wire

DSDL9/final/quartus/tcam.v
`timescale 1ns/1ps
`default_nettype none

// Each enabled row stores its own data and X mask on the same rising edge. Meaning multiple registers with defined
// Data width on a single store.
// Row i uses write_data[i*DATA_WIDTH +: DATA_WIDTH] with the same mask slice.
module tcam #(
    parameter integer DATA_WIDTH = 4,
    parameter integer DEPTH = 4
) (
    input  wire                         clk,
    input  wire                         reset,
    input  wire [DEPTH-1:0]             write_enable,
    input  wire [DEPTH*DATA_WIDTH-1:0]  write_data,     // Data of all registers
    input  wire [DEPTH*DATA_WIDTH-1:0]  write_x_mask,   // X values for all registers
    input  wire [DATA_WIDTH-1:0]        search_data,    // Data we comparing with
    output wire [DEPTH-1:0]             match_lines     // Registers matched
);
    genvar row;

    generate
        if (DATA_WIDTH < 1 || DEPTH < 1) begin : invalid_parameters
            initial $fatal(1, "TCAM requires DATA_WIDTH >= 1 and DEPTH >= 1");
        end else begin : valid_parameters
            for (row = 0; row < DEPTH; row = row + 1) begin : entries
                tcam_entry #(.DATA_WIDTH(DATA_WIDTH)) entry (
                    .clk(clk),
                    .reset(reset),
                    .write_enable(write_enable[row]),
                    .write_data(write_data[row*DATA_WIDTH +: DATA_WIDTH]),
                    .write_x_mask(write_x_mask[row*DATA_WIDTH +: DATA_WIDTH]),
                    .search_data(search_data),
                    .match(match_lines[row])
                );
            end
        end
    endgenerate
endmodule

`default_nettype wire

DSDL9/tb_tcam_1x1.v
`timescale 1ns/1ps
`default_nettype none

// 1 x 1 minimum size and synchronous reset priority
module tb_tcam_1x1;
    localparam integer DATA_WIDTH = 1;
    localparam integer DEPTH = 1;
    reg clk = 1'b0;
    reg reset = 1'b1;
    reg [DEPTH-1:0] write_enable = 0;
    reg [DEPTH*DATA_WIDTH-1:0] write_data = 0;
    reg [DEPTH*DATA_WIDTH-1:0] write_x_mask = 0;
    reg [DATA_WIDTH-1:0] search_data = 0;
    wire [DEPTH-1:0] match_loop;
    wire [DEPTH-1:0] match_no_loop;

    tcam #(.DATA_WIDTH(DATA_WIDTH), .DEPTH(DEPTH)) loop (
        .clk(clk), .reset(reset), .write_enable(write_enable),
        .write_data(write_data), .write_x_mask(write_x_mask),
        .search_data(search_data), .match_lines(match_loop)
    );
    tcam_no_loop #(.DATA_WIDTH(DATA_WIDTH), .DEPTH(DEPTH)) no_loop (
        .clk(clk), .reset(reset), .write_enable(write_enable),
        .write_data(write_data), .write_x_mask(write_x_mask),
        .search_data(search_data), .match_lines(match_no_loop)
    );

    always #5 clk = ~clk;

    task check_search;
        input [DATA_WIDTH-1:0] data;
        input [DEPTH-1:0] expected;
        begin
            search_data = data;
            #1;
            if (match_loop !== expected || match_no_loop !== expected)
                $fatal(1, "Search %h: expected %h, loop %h, no-loop %h",
                       data, expected, match_loop, match_no_loop);
            #9; // Keep each result visible in GTKWave.
        end
    endtask

    initial begin
        $dumpfile("build/tb_tcam_1x1.vcd");
        $dumpvars(0, tb_tcam_1x1);
        @(posedge clk);
        #1 reset = 1'b0;

        check_search(1'b0, 1'b0);
        check_search(1'b1, 1'b0);
        @(negedge clk);
        write_data = 1'b1;
        write_enable = 1'b1;
        @(posedge clk);
        #1 write_enable = 1'b0;
        check_search(1'b1, 1'b1);
        check_search(1'b0, 1'b0);

        @(negedge clk);
        write_data = 1'b0;
        write_x_mask = 1'b1;
        write_enable = 1'b1;
        @(posedge clk);
        #1 write_enable = 1'b0;
        check_search(1'b0, 1'b1);
        check_search(1'b1, 1'b1);

        @(negedge clk);
        reset = 1'b1;
        write_enable = 1'b1;
        #1;
        if (match_loop !== 1'b1 || match_no_loop !== 1'b1)
            $fatal(1, "Reset acted before the rising clock edge");
        @(posedge clk);
        #1;
        reset = 1'b0;
        write_enable = 1'b0;
        check_search(1'b0, 1'b0);
        check_search(1'b1, 1'b0);

        $display("PASS: 1 x 1 minimum size and synchronous reset priority (both implementations)");
        $finish;
    end
endmodule

`default_nettype wire

DSDL9/final/build/tb_tcam_1x1.vcd
$date
	Sat Sep 12 09:50:56 2026
$end
$version
	Icarus Verilog
$end
$timescale
	1ps
$end
$scope module tb_tcam_1x1 $end
$var wire 1 ! match_no_loop $end
$var wire 1 " match_loop $end
$var parameter 32 # DATA_WIDTH $end
$var parameter 32 $ DEPTH $end
$var reg 1 % clk $end
$var reg 1 & reset $end
$var reg 1 ' search_data $end
$var reg 1 ( write_data $end
$var reg 1 ) write_enable $end
$var reg 1 * write_x_mask $end
$scope module loop $end
$var wire 1 % clk $end
$var wire 1 & reset $end
$var wire 1 ' search_data $end
$var wire 1 ( write_data $end
$var wire 1 ) write_enable $end
$var wire 1 * write_x_mask $end
$var wire 1 " match_lines $end
$var parameter 32 + DATA_WIDTH $end
$var parameter 32 , DEPTH $end
$scope begin valid_parameters $end
$scope begin entries[0] $end
$var parameter 2 - row $end
$scope module entry $end
$var wire 1 % clk $end
$var wire 1 " match $end
$var wire 1 . mismatched_bits $end
$var wire 1 & reset $end
$var wire 1 ' search_data $end
$var wire 1 ( write_data $end
$var wire 1 ) write_enable $end
$var wire 1 * write_x_mask $end
$var parameter 32 / DATA_WIDTH $end
$var reg 1 0 stored_data $end
$var reg 1 1 stored_x_mask $end
$var reg 1 2 valid $end
$upscope $end
$upscope $end
$upscope $end
$upscope $end
$scope module no_loop $end
$var wire 1 % clk $end
$var wire 1 & reset $end
$var wire 1 ' search_data $end
$var wire 1 ( write_data $end
$var wire 1 ) write_enable $end
$var wire 1 * write_x_mask $end
$var wire 1 ! match_lines $end
$var parameter 32 3 DATA_WIDTH $end
$var parameter 32 4 DEPTH $end
$scope begin valid_parameters $end
$scope module entries[0] $end
$var wire 1 % clk $end
$var wire 1 ! match $end
$var wire 1 5 mismatched_bits $end
$var wire 1 & reset $end
$var wire 1 ' search_data $end
$var wire 1 ( write_data $end
$var wire 1 ) write_enable $end
$var wire 1 * write_x_mask $end
$var parameter 32 6 DATA_WIDTH $end
$var reg 1 7 stored_data $end
$var reg 1 8 stored_x_mask $end
$var reg 1 9 valid $end
$upscope $end
$upscope $end
$upscope $end
$scope task check_search $end
$var reg 1 : data $end
$var reg 1 ; expected $end
$upscope $end
$upscope $end
$enddefinitions $end
$comment Show the parameter values. $end
$dumpall
b1 6
b1 4
b1 3
b1 /
b0 -
b1 ,
b1 +
b1 $
b1 #
$end
#0
$dumpvars
x;
x:
x9
x8
x7
x5
x2
x1
x0
x.
0*
0)
0(
0'
1&
0%
x"
x!
$end
#5000
0"
0!
02
09
1%
#6000
0;
0:
0&
#10000
0%
#15000
1%
#16000
1'
1:
#20000
0%
#25000
1%
#30000
1)
1(
0%
#35000
05
0.
1!
1"
19
08
17
12
01
10
1%
#36000
1;
0)
#40000
0%
#45000
1%
#46000
0"
0!
1.
15
0'
0;
0:
#50000
0%
#55000
1%
#60000
1)
1*
0(
0%
#65000
1"
1!
0.
05
11
00
18
07
1%
#66000
1;
0)
#70000
0%
#75000
1%
#76000
1'
1:
#80000
0%
#85000
1%
#90000
1)
1&
0%
#95000
0!
0"
09
02
1%
#96000
0'
0;
0:
0)
0&
#100000
0%
#105000
1%
#106000
1'
1:
