DSDL9/final/src/tcam_entry.v
`timescale 1ns/1ps
`default_nettype none

// One DATA_WIDTH-bit ternary memory entry.
// A 1 in stored_x_mask makes the corresponding stored bit a X.
module tcam_entry #(
    parameter integer DATA_WIDTH = 16
) (
    input  wire                  clk,
    input  wire                  reset,
    input  wire                  write_enable,
    input  wire [DATA_WIDTH-1:0] write_data,
    input  wire [DATA_WIDTH-1:0] write_x_mask,
    input  wire [DATA_WIDTH-1:0] search_data,
    output wire                  match
);
    reg [DATA_WIDTH-1:0] stored_data;       // Caputered data from write_data
    reg [DATA_WIDTH-1:0] stored_x_mask;     // Captured mask
    reg                  valid;             // Single bit valid, some tests show invalid cases

    wire [DATA_WIDTH-1:0] mismatched_bits;  // Bits that didn't match

    always @(posedge clk) begin
        if (reset) begin
            valid <= 1'b0;
        end else if (write_enable) begin
            stored_data <= write_data;
            stored_x_mask <= write_x_mask;
            valid <= 1'b1;
        end
    end

    // Masked positions are removed before checking for unequal bits.
    assign mismatched_bits = (search_data ^ stored_data) & ~stored_x_mask;
    assign match = valid && (mismatched_bits == {DATA_WIDTH{1'b0}});
endmodule

`default_nettype wire

DSDL9/final/quartus/tcam.v
`timescale 1ns/1ps
`default_nettype none

// Each enabled row stores its own data and X mask on the same rising edge. Meaning multiple registers with defined
// Data width on a single store.
// Row i uses write_data[i*DATA_WIDTH +: DATA_WIDTH] with the same mask slice.
module tcam #(
    parameter integer DATA_WIDTH = 4,
    parameter integer DEPTH = 4
) (
    input  wire                         clk,
    input  wire                         reset,
    input  wire [DEPTH-1:0]             write_enable,
    input  wire [DEPTH*DATA_WIDTH-1:0]  write_data,     // Data of all registers
    input  wire [DEPTH*DATA_WIDTH-1:0]  write_x_mask,   // X values for all registers
    input  wire [DATA_WIDTH-1:0]        search_data,    // Data we comparing with
    output wire [DEPTH-1:0]             match_lines     // Registers matched
);
    genvar row;

    generate
        if (DATA_WIDTH < 1 || DEPTH < 1) begin : invalid_parameters
            initial $fatal(1, "TCAM requires DATA_WIDTH >= 1 and DEPTH >= 1");
        end else begin : valid_parameters
            for (row = 0; row < DEPTH; row = row + 1) begin : entries
                tcam_entry #(.DATA_WIDTH(DATA_WIDTH)) entry (
                    .clk(clk),
                    .reset(reset),
                    .write_enable(write_enable[row]),
                    .write_data(write_data[row*DATA_WIDTH +: DATA_WIDTH]),
                    .write_x_mask(write_x_mask[row*DATA_WIDTH +: DATA_WIDTH]),
                    .search_data(search_data),
                    .match(match_lines[row])
                );
            end
        end
    endgenerate
endmodule

`default_nettype wire

DSDL9/final/quartus/tcam_upgraded.v
`timescale 1ns/1ps
`default_nettype none

// Addressed-write TCAM: one row is written per clock; all rows are searched.
// At the default 16 x 16 size, the external interface uses 71 pins.
module tcam_upgraded #(
    parameter integer DATA_WIDTH = 16,
    parameter integer DEPTH = 16
) (
    input  wire                         clk,
    input  wire                         reset,
    input  wire                         write_enable,
    input  wire [((DEPTH > 1) ? $clog2(DEPTH) : 1)-1:0] write_address,
    input  wire [DATA_WIDTH-1:0]        write_data,
    input  wire [DATA_WIDTH-1:0]        write_x_mask,
    input  wire [DATA_WIDTH-1:0]        search_data,
    output wire [DEPTH-1:0]             match_lines
);
    generate
        if (DATA_WIDTH < 1 || DEPTH < 1) begin : invalid_parameters
            initial $fatal(1, "TCAM requires DATA_WIDTH >= 1 and DEPTH >= 1");
        end else begin : valid_parameters
            wire [DEPTH-1:0] row_write_enable;
            wire [DEPTH*DATA_WIDTH-1:0] all_write_data;
            wire [DEPTH*DATA_WIDTH-1:0] all_write_x_mask;

            // Move the enable bit to the addressed row; unused addresses write none.
            assign row_write_enable = {{(DEPTH-1){1'b0}}, write_enable}
                                    << write_address;
            // All rows receive the same inputs, but only the enabled row stores them.
            assign all_write_data = {DEPTH{write_data}};
            assign all_write_x_mask = {DEPTH{write_x_mask}};

            tcam #(
                .DATA_WIDTH(DATA_WIDTH),
                .DEPTH(DEPTH)
            ) core (
                .clk(clk),
                .reset(reset),
                .write_enable(row_write_enable),
                .write_data(all_write_data),
                .write_x_mask(all_write_x_mask),
                .search_data(search_data),
                .match_lines(match_lines)
            );
        end
    endgenerate
endmodule

`default_nettype wire

DSDL9/final/tb/tb_tcam_upgraded.v
`timescale 1ns/1ps
`default_nettype none

// 16 x 16 addressed writes: row selection, wildcard matching, and write hold.
module tb_tcam_upgraded;
    reg clk = 1'b0;
    reg reset = 1'b1;
    reg write_enable = 1'b0;
    reg [3:0] write_address = 4'd0;
    reg [15:0] write_data = 16'h0000;
    reg [15:0] write_x_mask = 16'h0000;
    reg [15:0] search_data = 16'h0000;
    wire [15:0] match_lines;
    integer row;

    tcam_upgraded #(.DATA_WIDTH(16), .DEPTH(16)) dut (
        .clk(clk),
        .reset(reset),
        .write_enable(write_enable),
        .write_address(write_address),
        .write_data(write_data),
        .write_x_mask(write_x_mask),
        .search_data(search_data),
        .match_lines(match_lines)
    );

    always #5 clk = ~clk;

    task write_row;
        input [3:0] address;
        input [15:0] data;
        input [15:0] x_mask;
        begin
            @(negedge clk);
            write_address = address;
            write_data = data;
            write_x_mask = x_mask;
            write_enable = 1'b1;
            @(posedge clk);
            #1 write_enable = 1'b0;
        end
    endtask

    task expect_match;
        input [15:0] key;
        input [15:0] expected;
        begin
            search_data = key;
            #1;
            if (match_lines !== expected)
                $fatal(1, "key=%h expected=%h actual=%h", key, expected, match_lines);
        end
    endtask

    initial begin
        $dumpfile("build/tb_tcam_upgraded.vcd");
        $dumpvars(0, tb_tcam_upgraded);

        @(posedge clk);
        #1 reset = 1'b0;

        // Program all sixteen physical rows through the four-bit address port.
        for (row = 0; row < 16; row = row + 1)
            write_row(row[3:0], 16'h1000 + row, 16'h0000);

        // Literal results catch incorrect decoding without repeating its logic.
        expect_match(16'h1000, 16'h0001);
        expect_match(16'h1001, 16'h0002);
        expect_match(16'h1002, 16'h0004);
        expect_match(16'h1003, 16'h0008);
        expect_match(16'h1004, 16'h0010);
        expect_match(16'h1005, 16'h0020);
        expect_match(16'h1006, 16'h0040);
        expect_match(16'h1007, 16'h0080);
        expect_match(16'h1008, 16'h0100);
        expect_match(16'h1009, 16'h0200);
        expect_match(16'h100A, 16'h0400);
        expect_match(16'h100B, 16'h0800);
        expect_match(16'h100C, 16'h1000);
        expect_match(16'h100D, 16'h2000);
        expect_match(16'h100E, 16'h4000);
        expect_match(16'h100F, 16'h8000);

        // Rewrite row 7 with four wildcard bits and verify both match and miss.
        write_row(4'd7, 16'hA500, 16'h00F0);
        expect_match(16'hA5A0, 16'h0080);
        expect_match(16'hA4A0, 16'h0000);

        // Changing the inputs with write_enable low must not overwrite row 7.
        @(negedge clk);
        write_address = 4'd7;
        write_data = 16'hFFFF;
        write_x_mask = 16'hFFFF;
        @(posedge clk);
        #1;
        expect_match(16'hA5A0, 16'h0080);
        expect_match(16'hFFFF, 16'h0000);

        // Reset must invalidate all sixteen rows.
        reset = 1'b1;
        @(posedge clk);
        #1 reset = 1'b0;
        expect_match(16'h1000, 16'h0000);
        expect_match(16'hA5A0, 16'h0000);

        $display("PASS: tcam_upgraded 16 x 16 addressed writes, masks, hold, and reset");
        $finish;
    end
endmodule

`default_nettype wire

DSDL9/final/build/tb_tcam_upgraded.vcd
$date
	Mon Sep 14 15:03:05 2026
$end
$version
	Icarus Verilog
$end
$timescale
	1ps
$end
$scope module tb_tcam_upgraded $end
$var wire 16 ! match_lines [15:0] $end
$var reg 1 " clk $end
$var reg 1 # reset $end
$var reg 16 $ search_data [15:0] $end
$var reg 4 % write_address [3:0] $end
$var reg 16 & write_data [15:0] $end
$var reg 1 ' write_enable $end
$var reg 16 ( write_x_mask [15:0] $end
$var integer 32 ) row [31:0] $end
$scope module dut $end
$var wire 1 " clk $end
$var wire 1 # reset $end
$var wire 16 * search_data [15:0] $end
$var wire 4 + write_address [3:0] $end
$var wire 16 , write_data [15:0] $end
$var wire 1 ' write_enable $end
$var wire 16 - write_x_mask [15:0] $end
$var wire 16 . match_lines [15:0] $end
$var parameter 32 / DATA_WIDTH $end
$var parameter 32 0 DEPTH $end
$scope begin valid_parameters $end
$var wire 16 1 row_write_enable [15:0] $end
$var wire 256 2 all_write_x_mask [255:0] $end
$var wire 256 3 all_write_data [255:0] $end
$scope module core $end
$var wire 1 " clk $end
$var wire 1 # reset $end
$var wire 16 4 search_data [15:0] $end
$var wire 256 5 write_data [255:0] $end
$var wire 16 6 write_enable [15:0] $end
$var wire 256 7 write_x_mask [255:0] $end
$var wire 16 8 match_lines [15:0] $end
$var parameter 32 9 DATA_WIDTH $end
$var parameter 32 : DEPTH $end
$scope begin valid_parameters $end
$scope begin entries[0] $end
$var parameter 2 ; row $end
$scope module entry $end
$var wire 1 " clk $end
$var wire 1 < match $end
$var wire 16 = mismatched_bits [15:0] $end
$var wire 1 # reset $end
$var wire 16 > search_data [15:0] $end
$var wire 16 ? write_data [15:0] $end
$var wire 1 @ write_enable $end
$var wire 16 A write_x_mask [15:0] $end
$var parameter 32 B DATA_WIDTH $end
$var reg 16 C stored_data [15:0] $end
$var reg 16 D stored_x_mask [15:0] $end
$var reg 1 E valid $end
$upscope $end
$upscope $end
$scope begin entries[1] $end
$var parameter 2 F row $end
$scope module entry $end
$var wire 1 " clk $end
$var wire 1 G match $end
$var wire 16 H mismatched_bits [15:0] $end
$var wire 1 # reset $end
$var wire 16 I search_data [15:0] $end
$var wire 16 J write_data [15:0] $end
$var wire 1 K write_enable $end
$var wire 16 L write_x_mask [15:0] $end
$var parameter 32 M DATA_WIDTH $end
$var reg 16 N stored_data [15:0] $end
$var reg 16 O stored_x_mask [15:0] $end
$var reg 1 P valid $end
$upscope $end
$upscope $end
$scope begin entries[2] $end
$var parameter 3 Q row $end
$scope module entry $end
$var wire 1 " clk $end
$var wire 1 R match $end
$var wire 16 S mismatched_bits [15:0] $end
$var wire 1 # reset $end
$var wire 16 T search_data [15:0] $end
$var wire 16 U write_data [15:0] $end
$var wire 1 V write_enable $end
$var wire 16 W write_x_mask [15:0] $end
$var parameter 32 X DATA_WIDTH $end
$var reg 16 Y stored_data [15:0] $end
$var reg 16 Z stored_x_mask [15:0] $end
$var reg 1 [ valid $end
$upscope $end
$upscope $end
$scope begin entries[3] $end
$var parameter 3 \ row $end
$scope module entry $end
$var wire 1 " clk $end
$var wire 1 ] match $end
$var wire 16 ^ mismatched_bits [15:0] $end
$var wire 1 # reset $end
$var wire 16 _ search_data [15:0] $end
$var wire 16 ` write_data [15:0] $end
$var wire 1 a write_enable $end
$var wire 16 b write_x_mask [15:0] $end
$var parameter 32 c DATA_WIDTH $end
$var reg 16 d stored_data [15:0] $end
$var reg 16 e stored_x_mask [15:0] $end
$var reg 1 f valid $end
$upscope $end
$upscope $end
$scope begin entries[4] $end
$var parameter 4 g row $end
$scope module entry $end
$var wire 1 " clk $end
$var wire 1 h match $end
$var wire 16 i mismatched_bits [15:0] $end
$var wire 1 # reset $end
$var wire 16 j search_data [15:0] $end
$var wire 16 k write_data [15:0] $end
$var wire 1 l write_enable $end
$var wire 16 m write_x_mask [15:0] $end
$var parameter 32 n DATA_WIDTH $end
$var reg 16 o stored_data [15:0] $end
$var reg 16 p stored_x_mask [15:0] $end
$var reg 1 q valid $end
$upscope $end
$upscope $end
$scope begin entries[5] $end
$var parameter 4 r row $end
$scope module entry $end
$var wire 1 " clk $end
$var wire 1 s match $end
$var wire 16 t mismatched_bits [15:0] $end
$var wire 1 # reset $end
$var wire 16 u search_data [15:0] $end
$var wire 16 v write_data [15:0] $end
$var wire 1 w write_enable $end
$var wire 16 x write_x_mask [15:0] $end
$var parameter 32 y DATA_WIDTH $end
$var reg 16 z stored_data [15:0] $end
$var reg 16 { stored_x_mask [15:0] $end
$var reg 1 | valid $end
$upscope $end
$upscope $end
$scope begin entries[6] $end
$var parameter 4 } row $end
$scope module entry $end
$var wire 1 " clk $end
$var wire 1 ~ match $end
$var wire 16 !" mismatched_bits [15:0] $end
$var wire 1 # reset $end
$var wire 16 "" search_data [15:0] $end
$var wire 16 #" write_data [15:0] $end
$var wire 1 $" write_enable $end
$var wire 16 %" write_x_mask [15:0] $end
$var parameter 32 &" DATA_WIDTH $end
$var reg 16 '" stored_data [15:0] $end
$var reg 16 (" stored_x_mask [15:0] $end
$var reg 1 )" valid $end
$upscope $end
$upscope $end
$scope begin entries[7] $end
$var parameter 4 *" row $end
$scope module entry $end
$var wire 1 " clk $end
$var wire 1 +" match $end
$var wire 16 ," mismatched_bits [15:0] $end
$var wire 1 # reset $end
$var wire 16 -" search_data [15:0] $end
$var wire 16 ." write_data [15:0] $end
$var wire 1 /" write_enable $end
$var wire 16 0" write_x_mask [15:0] $end
$var parameter 32 1" DATA_WIDTH $end
$var reg 16 2" stored_data [15:0] $end
$var reg 16 3" stored_x_mask [15:0] $end
$var reg 1 4" valid $end
$upscope $end
$upscope $end
$scope begin entries[8] $end
$var parameter 5 5" row $end
$scope module entry $end
$var wire 1 " clk $end
$var wire 1 6" match $end
$var wire 16 7" mismatched_bits [15:0] $end
$var wire 1 # reset $end
$var wire 16 8" search_data [15:0] $end
$var wire 16 9" write_data [15:0] $end
$var wire 1 :" write_enable $end
$var wire 16 ;" write_x_mask [15:0] $end
$var parameter 32 <" DATA_WIDTH $end
$var reg 16 =" stored_data [15:0] $end
$var reg 16 >" stored_x_mask [15:0] $end
$var reg 1 ?" valid $end
$upscope $end
$upscope $end
$scope begin entries[9] $end
$var parameter 5 @" row $end
$scope module entry $end
$var wire 1 " clk $end
$var wire 1 A" match $end
$var wire 16 B" mismatched_bits [15:0] $end
$var wire 1 # reset $end
$var wire 16 C" search_data [15:0] $end
$var wire 16 D" write_data [15:0] $end
$var wire 1 E" write_enable $end
$var wire 16 F" write_x_mask [15:0] $end
$var parameter 32 G" DATA_WIDTH $end
$var reg 16 H" stored_data [15:0] $end
$var reg 16 I" stored_x_mask [15:0] $end
$var reg 1 J" valid $end
$upscope $end
$upscope $end
$scope begin entries[10] $end
$var parameter 5 K" row $end
$scope module entry $end
$var wire 1 " clk $end
$var wire 1 L" match $end
$var wire 16 M" mismatched_bits [15:0] $end
$var wire 1 # reset $end
$var wire 16 N" search_data [15:0] $end
$var wire 16 O" write_data [15:0] $end
$var wire 1 P" write_enable $end
$var wire 16 Q" write_x_mask [15:0] $end
$var parameter 32 R" DATA_WIDTH $end
$var reg 16 S" stored_data [15:0] $end
$var reg 16 T" stored_x_mask [15:0] $end
$var reg 1 U" valid $end
$upscope $end
$upscope $end
$scope begin entries[11] $end
$var parameter 5 V" row $end
$scope module entry $end
$var wire 1 " clk $end
$var wire 1 W" match $end
$var wire 16 X" mismatched_bits [15:0] $end
$var wire 1 # reset $end
$var wire 16 Y" search_data [15:0] $end
$var wire 16 Z" write_data [15:0] $end
$var wire 1 [" write_enable $end
$var wire 16 \" write_x_mask [15:0] $end
$var parameter 32 ]" DATA_WIDTH $end
$var reg 16 ^" stored_data [15:0] $end
$var reg 16 _" stored_x_mask [15:0] $end
$var reg 1 `" valid $end
$upscope $end
$upscope $end
$scope begin entries[12] $end
$var parameter 5 a" row $end
$scope module entry $end
$var wire 1 " clk $end
$var wire 1 b" match $end
$var wire 16 c" mismatched_bits [15:0] $end
$var wire 1 # reset $end
$var wire 16 d" search_data [15:0] $end
$var wire 16 e" write_data [15:0] $end
$var wire 1 f" write_enable $end
$var wire 16 g" write_x_mask [15:0] $end
$var parameter 32 h" DATA_WIDTH $end
$var reg 16 i" stored_data [15:0] $end
$var reg 16 j" stored_x_mask [15:0] $end
$var reg 1 k" valid $end
$upscope $end
$upscope $end
$scope begin entries[13] $end
$var parameter 5 l" row $end
$scope module entry $end
$var wire 1 " clk $end
$var wire 1 m" match $end
$var wire 16 n" mismatched_bits [15:0] $end
$var wire 1 # reset $end
$var wire 16 o" search_data [15:0] $end
$var wire 16 p" write_data [15:0] $end
$var wire 1 q" write_enable $end
$var wire 16 r" write_x_mask [15:0] $end
$var parameter 32 s" DATA_WIDTH $end
$var reg 16 t" stored_data [15:0] $end
$var reg 16 u" stored_x_mask [15:0] $end
$var reg 1 v" valid $end
$upscope $end
$upscope $end
$scope begin entries[14] $end
$var parameter 5 w" row $end
$scope module entry $end
$var wire 1 " clk $end
$var wire 1 x" match $end
$var wire 16 y" mismatched_bits [15:0] $end
$var wire 1 # reset $end
$var wire 16 z" search_data [15:0] $end
$var wire 16 {" write_data [15:0] $end
$var wire 1 |" write_enable $end
$var wire 16 }" write_x_mask [15:0] $end
$var parameter 32 ~" DATA_WIDTH $end
$var reg 16 !# stored_data [15:0] $end
$var reg 16 "# stored_x_mask [15:0] $end
$var reg 1 ## valid $end
$upscope $end
$upscope $end
$scope begin entries[15] $end
$var parameter 5 $# row $end
$scope module entry $end
$var wire 1 " clk $end
$var wire 1 %# match $end
$var wire 16 &# mismatched_bits [15:0] $end
$var wire 1 # reset $end
$var wire 16 '# search_data [15:0] $end
$var wire 16 (# write_data [15:0] $end
$var wire 1 )# write_enable $end
$var wire 16 *# write_x_mask [15:0] $end
$var parameter 32 +# DATA_WIDTH $end
$var reg 16 ,# stored_data [15:0] $end
$var reg 16 -# stored_x_mask [15:0] $end
$var reg 1 .# valid $end
$upscope $end
$upscope $end
$upscope $end
$upscope $end
$upscope $end
$upscope $end
$scope task expect_match $end
$var reg 16 /# expected [15:0] $end
$var reg 16 0# key [15:0] $end
$upscope $end
$scope task write_row $end
$var reg 4 1# address [3:0] $end
$var reg 16 2# data [15:0] $end
$var reg 16 3# x_mask [15:0] $end
$upscope $end
$upscope $end
$enddefinitions $end
$comment Show the parameter values. $end
$dumpall
b10000 +#
b1111 $#
b10000 ~"
b1110 w"
b10000 s"
b1101 l"
b10000 h"
b1100 a"
b10000 ]"
b1011 V"
b10000 R"
b1010 K"
b10000 G"
b1001 @"
b10000 <"
b1000 5"
b10000 1"
b111 *"
b10000 &"
b110 }
b10000 y
b101 r
b10000 n
b100 g
b10000 c
b11 \
b10000 X
b10 Q
b10000 M
b1 F
b10000 B
b0 ;
b10000 :
b10000 9
b10000 0
b10000 /
$end
#0
$dumpvars
bx 3#
bx 2#
bx 1#
bx 0#
bx /#
x.#
bx -#
bx ,#
b0 *#
0)#
b0 (#
b0 '#
bx &#
x%#
x##
bx "#
bx !#
b0 }"
0|"
b0 {"
b0 z"
bx y"
xx"
xv"
bx u"
bx t"
b0 r"
0q"
b0 p"
b0 o"
bx n"
xm"
xk"
bx j"
bx i"
b0 g"
0f"
b0 e"
b0 d"
bx c"
xb"
x`"
bx _"
bx ^"
b0 \"
0["
b0 Z"
b0 Y"
bx X"
xW"
xU"
bx T"
bx S"
b0 Q"
0P"
b0 O"
b0 N"
bx M"
xL"
xJ"
bx I"
bx H"
b0 F"
0E"
b0 D"
b0 C"
bx B"
xA"
x?"
bx >"
bx ="
b0 ;"
0:"
b0 9"
b0 8"
bx 7"
x6"
x4"
bx 3"
bx 2"
b0 0"
0/"
b0 ."
b0 -"
bx ,"
x+"
x)"
bx ("
bx '"
b0 %"
0$"
b0 #"
b0 ""
bx !"
x~
x|
bx {
bx z
b0 x
0w
b0 v
b0 u
bx t
xs
xq
bx p
bx o
b0 m
0l
b0 k
b0 j
bx i
xh
xf
bx e
bx d
b0 b
0a
b0 `
b0 _
bx ^
x]
x[
bx Z
bx Y
b0 W
0V
b0 U
b0 T
bx S
xR
xP
bx O
bx N
b0 L
0K
b0 J
b0 I
bx H
xG
xE
bx D
bx C
b0 A
0@
b0 ?
b0 >
bx =
x<
bx 8
b0 7
b0 6
b0 5
b0 4
b0 3
b0 2
b0 1
bx .
b0 -
b0 ,
b0 +
b0 *
bx )
b0 (
0'
b0 &
b0 %
b0 $
1#
0"
bx !
$end
#5000
0<
0G
0R
0]
0h
0s
0~
0+"
06"
0A"
0L"
0W"
0b"
0m"
0x"
b0 !
b0 .
b0 8
0%#
0E
0P
0[
0f
0q
0|
0)"
04"
0?"
0J"
0U"
0`"
0k"
0v"
0##
0.#
1"
#6000
b0 3#
b1000000000000 2#
b0 1#
b0 )
0#
#10000
1@
b1000000000000 ?
b1000000000000 J
b1000000000000 U
b1000000000000 `
b1000000000000 k
b1000000000000 v
b1000000000000 #"
b1000000000000 ."
b1000000000000 9"
b1000000000000 D"
b1000000000000 O"
b1000000000000 Z"
b1000000000000 e"
b1000000000000 p"
b1000000000000 {"
b1000000000000 (#
b1 1
b1 6
1'
b1000000000000000100000000000000010000000000000001000000000000000100000000000000010000000000000001000000000000000100000000000000010000000000000001000000000000000100000000000000010000000000000001000000000000000100000000000000010000000000000001000000000000 3
b1000000000000000100000000000000010000000000000001000000000000000100000000000000010000000000000001000000000000000100000000000000010000000000000001000000000000000100000000000000010000000000000001000000000000000100000000000000010000000000000001000000000000 5
b1000000000000 &
b1000000000000 ,
0"
#15000
b1000000000000 =
b0 !
b0 .
b0 8
0<
1E
b0 D
b1000000000000 C
1"
#16000
0@
b1000000000001 2#
b1 1#
b1 )
b0 1
b0 6
0'
#20000
1K
b1000000000001 ?
b1000000000001 J
b1000000000001 U
b1000000000001 `
b1000000000001 k
b1000000000001 v
b1000000000001 #"
b1000000000001 ."
b1000000000001 9"
b1000000000001 D"
b1000000000001 O"
b1000000000001 Z"
b1000000000001 e"
b1000000000001 p"
b1000000000001 {"
b1000000000001 (#
b10 1
b10 6
1'
b1000000000001000100000000000100010000000000010001000000000001000100000000000100010000000000010001000000000001000100000000000100010000000000010001000000000001000100000000000100010000000000010001000000000001000100000000000100010000000000010001000000000001 3
b1000000000001000100000000000100010000000000010001000000000001000100000000000100010000000000010001000000000001000100000000000100010000000000010001000000000001000100000000000100010000000000010001000000000001000100000000000100010000000000010001000000000001 5
b1000000000001 &
b1000000000001 ,
b1 %
b1 +
0"
#25000
b1000000000001 H
b0 !
b0 .
b0 8
0G
1P
b0 O
b1000000000001 N
1"
#26000
0K
b1000000000010 2#
b10 1#
b10 )
b0 1
b0 6
0'
#30000
1V
b1000000000010 ?
b1000000000010 J
b1000000000010 U
b1000000000010 `
b1000000000010 k
b1000000000010 v
b1000000000010 #"
b1000000000010 ."
b1000000000010 9"
b1000000000010 D"
b1000000000010 O"
b1000000000010 Z"
b1000000000010 e"
b1000000000010 p"
b1000000000010 {"
b1000000000010 (#
b100 1
b100 6
1'
b1000000000010000100000000001000010000000000100001000000000010000100000000001000010000000000100001000000000010000100000000001000010000000000100001000000000010000100000000001000010000000000100001000000000010000100000000001000010000000000100001000000000010 3
b1000000000010000100000000001000010000000000100001000000000010000100000000001000010000000000100001000000000010000100000000001000010000000000100001000000000010000100000000001000010000000000100001000000000010000100000000001000010000000000100001000000000010 5
b1000000000010 &
b1000000000010 ,
b10 %
b10 +
0"
#35000
b1000000000010 S
b0 !
b0 .
b0 8
0R
1[
b0 Z
b1000000000010 Y
1"
#36000
0V
b1000000000011 2#
b11 1#
b11 )
b0 1
b0 6
0'
#40000
1a
b1000000000011 ?
b1000000000011 J
b1000000000011 U
b1000000000011 `
b1000000000011 k
b1000000000011 v
b1000000000011 #"
b1000000000011 ."
b1000000000011 9"
b1000000000011 D"
b1000000000011 O"
b1000000000011 Z"
b1000000000011 e"
b1000000000011 p"
b1000000000011 {"
b1000000000011 (#
b1000 1
b1000 6
1'
b1000000000011000100000000001100010000000000110001000000000011000100000000001100010000000000110001000000000011000100000000001100010000000000110001000000000011000100000000001100010000000000110001000000000011000100000000001100010000000000110001000000000011 3
b1000000000011000100000000001100010000000000110001000000000011000100000000001100010000000000110001000000000011000100000000001100010000000000110001000000000011000100000000001100010000000000110001000000000011000100000000001100010000000000110001000000000011 5
b1000000000011 &
b1000000000011 ,
b11 %
b11 +
0"
#45000
b1000000000011 ^
b0 !
b0 .
b0 8
0]
1f
b0 e
b1000000000011 d
1"
#46000
0a
b1000000000100 2#
b100 1#
b100 )
b0 1
b0 6
0'
#50000
1l
b1000000000100 ?
b1000000000100 J
b1000000000100 U
b1000000000100 `
b1000000000100 k
b1000000000100 v
b1000000000100 #"
b1000000000100 ."
b1000000000100 9"
b1000000000100 D"
b1000000000100 O"
b1000000000100 Z"
b1000000000100 e"
b1000000000100 p"
b1000000000100 {"
b1000000000100 (#
b10000 1
b10000 6
1'
b1000000000100000100000000010000010000000001000001000000000100000100000000010000010000000001000001000000000100000100000000010000010000000001000001000000000100000100000000010000010000000001000001000000000100000100000000010000010000000001000001000000000100 3
b1000000000100000100000000010000010000000001000001000000000100000100000000010000010000000001000001000000000100000100000000010000010000000001000001000000000100000100000000010000010000000001000001000000000100000100000000010000010000000001000001000000000100 5
b1000000000100 &
b1000000000100 ,
b100 %
b100 +
0"
#55000
b1000000000100 i
b0 !
b0 .
b0 8
0h
1q
b0 p
b1000000000100 o
1"
#56000
0l
b1000000000101 2#
b101 1#
b101 )
b0 1
b0 6
0'
#60000
1w
b1000000000101 ?
b1000000000101 J
b1000000000101 U
b1000000000101 `
b1000000000101 k
b1000000000101 v
b1000000000101 #"
b1000000000101 ."
b1000000000101 9"
b1000000000101 D"
b1000000000101 O"
b1000000000101 Z"
b1000000000101 e"
b1000000000101 p"
b1000000000101 {"
b1000000000101 (#
b100000 1
b100000 6
1'
b1000000000101000100000000010100010000000001010001000000000101000100000000010100010000000001010001000000000101000100000000010100010000000001010001000000000101000100000000010100010000000001010001000000000101000100000000010100010000000001010001000000000101 3
b1000000000101000100000000010100010000000001010001000000000101000100000000010100010000000001010001000000000101000100000000010100010000000001010001000000000101000100000000010100010000000001010001000000000101000100000000010100010000000001010001000000000101 5
b1000000000101 &
b1000000000101 ,
b101 %
b101 +
0"
#65000
b1000000000101 t
b0 !
b0 .
b0 8
0s
1|
b0 {
b1000000000101 z
1"
#66000
0w
b1000000000110 2#
b110 1#
b110 )
b0 1
b0 6
0'
#70000
1$"
b1000000000110 ?
b1000000000110 J
b1000000000110 U
b1000000000110 `
b1000000000110 k
b1000000000110 v
b1000000000110 #"
b1000000000110 ."
b1000000000110 9"
b1000000000110 D"
b1000000000110 O"
b1000000000110 Z"
b1000000000110 e"
b1000000000110 p"
b1000000000110 {"
b1000000000110 (#
b1000000 1
b1000000 6
1'
b1000000000110000100000000011000010000000001100001000000000110000100000000011000010000000001100001000000000110000100000000011000010000000001100001000000000110000100000000011000010000000001100001000000000110000100000000011000010000000001100001000000000110 3
b1000000000110000100000000011000010000000001100001000000000110000100000000011000010000000001100001000000000110000100000000011000010000000001100001000000000110000100000000011000010000000001100001000000000110000100000000011000010000000001100001000000000110 5
b1000000000110 &
b1000000000110 ,
b110 %
b110 +
0"
#75000
b1000000000110 !"
b0 !
b0 .
b0 8
0~
1)"
b0 ("
b1000000000110 '"
1"
#76000
0$"
b1000000000111 2#
b111 1#
b111 )
b0 1
b0 6
0'
#80000
1/"
b1000000000111 ?
b1000000000111 J
b1000000000111 U
b1000000000111 `
b1000000000111 k
b1000000000111 v
b1000000000111 #"
b1000000000111 ."
b1000000000111 9"
b1000000000111 D"
b1000000000111 O"
b1000000000111 Z"
b1000000000111 e"
b1000000000111 p"
b1000000000111 {"
b1000000000111 (#
b10000000 1
b10000000 6
1'
b1000000000111000100000000011100010000000001110001000000000111000100000000011100010000000001110001000000000111000100000000011100010000000001110001000000000111000100000000011100010000000001110001000000000111000100000000011100010000000001110001000000000111 3
b1000000000111000100000000011100010000000001110001000000000111000100000000011100010000000001110001000000000111000100000000011100010000000001110001000000000111000100000000011100010000000001110001000000000111000100000000011100010000000001110001000000000111 5
b1000000000111 &
b1000000000111 ,
b111 %
b111 +
0"
#85000
b1000000000111 ,"
b0 !
b0 .
b0 8
0+"
14"
b0 3"
b1000000000111 2"
1"
#86000
0/"
b1000000001000 2#
b1000 1#
b1000 )
b0 1
b0 6
0'
#90000
1:"
b1000000001000 ?
b1000000001000 J
b1000000001000 U
b1000000001000 `
b1000000001000 k
b1000000001000 v
b1000000001000 #"
b1000000001000 ."
b1000000001000 9"
b1000000001000 D"
b1000000001000 O"
b1000000001000 Z"
b1000000001000 e"
b1000000001000 p"
b1000000001000 {"
b1000000001000 (#
b100000000 1
b100000000 6
1'
b1000000001000000100000000100000010000000010000001000000001000000100000000100000010000000010000001000000001000000100000000100000010000000010000001000000001000000100000000100000010000000010000001000000001000000100000000100000010000000010000001000000001000 3
b1000000001000000100000000100000010000000010000001000000001000000100000000100000010000000010000001000000001000000100000000100000010000000010000001000000001000000100000000100000010000000010000001000000001000000100000000100000010000000010000001000000001000 5
b1000000001000 &
b1000000001000 ,
b1000 %
b1000 +
0"
#95000
b1000000001000 7"
b0 !
b0 .
b0 8
06"
1?"
b0 >"
b1000000001000 ="
1"
#96000
0:"
b1000000001001 2#
b1001 1#
b1001 )
b0 1
b0 6
0'
#100000
1E"
b1000000001001 ?
b1000000001001 J
b1000000001001 U
b1000000001001 `
b1000000001001 k
b1000000001001 v
b1000000001001 #"
b1000000001001 ."
b1000000001001 9"
b1000000001001 D"
b1000000001001 O"
b1000000001001 Z"
b1000000001001 e"
b1000000001001 p"
b1000000001001 {"
b1000000001001 (#
b1000000000 1
b1000000000 6
1'
b1000000001001000100000000100100010000000010010001000000001001000100000000100100010000000010010001000000001001000100000000100100010000000010010001000000001001000100000000100100010000000010010001000000001001000100000000100100010000000010010001000000001001 3
b1000000001001000100000000100100010000000010010001000000001001000100000000100100010000000010010001000000001001000100000000100100010000000010010001000000001001000100000000100100010000000010010001000000001001000100000000100100010000000010010001000000001001 5
b1000000001001 &
b1000000001001 ,
b1001 %
b1001 +
0"
#105000
b1000000001001 B"
b0 !
b0 .
b0 8
0A"
1J"
b0 I"
b1000000001001 H"
1"
#106000
0E"
b1000000001010 2#
b1010 1#
b1010 )
b0 1
b0 6
0'
