DSDL5/Final/rtl/barrel_ashr.v
// Variable-distance combinational arithmetic-right shifter.
module barrel_ashr (din, amt, dout);
    parameter W = 18;
    localparam AmountW = $clog2(W);

    input wire [W-1:0] din;
    input wire [AmountW-1:0] amt;
    output reg [W-1:0] dout;

    integer k;

    always @* begin
        dout = din;
        for (k = 0; k < AmountW; k = k + 1)
            if (amt[k]) dout = $signed(dout) >>> (1 << k);
    end

endmodule

DSDL5/Final/rtl/skip_encode.v
// Returns the distance to the nearest upcoming Booth boundary.
module skip_encode (Map, Dist);

    parameter MapW = 9;
    localparam DistW = $clog2(MapW);
    localparam MaxSkip = MapW - 1;

    input wire [MapW-1:0] Map;
    output reg [DistW-1:0] Dist;

    integer k;

    always @* begin
        Dist = MaxSkip;
        // Descending scan lets the nearest (lowest) set bit win.
        for (k = MaxSkip; k >= 1; k = k - 1)
            if (Map[k]) Dist = k;
    end

endmodule

DSDL5/Final/rtl/booth_datapath.v
// Booth datapath: {A, Q, Q_1} is shifted as one 2N+2-bit register.
// A has a guard bit so negating the most-negative N-bit value cannot overflow.
// A precomputed boundary map enables multi-bit skips between Booth operations.
// N must be at least 2.

module booth_datapath (Clk, RstN, Load, Step, Multiplicand, Multiplier,
                       Product, LastStep);

    parameter N = 8;

    localparam DistW = $clog2(N+1);
    localparam ShiftAmountW = $clog2(2*N+2);

    input wire Clk;
    input wire RstN;
    input wire Load;
    input wire Step;
    input wire [N-1:0] Multiplicand;
    input wire [N-1:0] Multiplier;
    output wire [2*N-1:0] Product;
    // High while the current Step consumes every remaining multiplier bit.
    output wire LastStep;

    reg [N:0] A;
    reg [N-1:0] Q;
    reg Q_1;
    reg [N-1:0] M;
    reg [DistW-1:0] Remaining;
    reg [N-1:0] Bmap;

    // Booth pair 01 adds, 10 subtracts, and 00/11 only shift.
    wire DoAdd = (~Q[0]) & Q_1;
    wire DoSub = Q[0] & ~Q_1;

    // Sign extension preserves negative M values in the wider accumulator.
    wire [N:0] MExt = {M[N-1], M};

    wire [N:0] AOp = DoSub ? (A - MExt) : DoAdd ? (A + MExt) : A;

    // A set bit marks a Booth transition: Q[i] XOR Q[i-1], with Q[-1]=0.
    // The map shifts with Q so bit zero always describes the current position.
    wire [N-1:0] BmapInit = Multiplier ^ {Multiplier[N-2:0], 1'b0};

    // The leading zero lets the encoder return N when no boundary remains.
    wire [DistW-1:0] Raw;

    skip_encode #(.MapW(N+1)) u_encode (
        .Map({1'b0, Bmap}),
        .Dist(Raw)
    );

    // Cap the skip at the number of unprocessed multiplier bits.
    wire [DistW-1:0] Dist = (Raw < Remaining) ? Raw : Remaining;

    assign LastStep = (Dist == Remaining);

    wire [N:0] BmapShifted;

    barrel_ashr #(.W(N+1)) u_map_shift (
        .din({1'b0, Bmap}),
        .amt(Dist),
        .dout(BmapShifted)
    );

    wire [2*N+1:0] Shifted;

    wire [ShiftAmountW-1:0] DistWide = Dist;

    barrel_ashr #(.W(2*N+2)) u_shift (
        .din({AOp, Q, Q_1}),
        .amt(DistWide),
        .dout(Shifted)
    );

    always @(posedge Clk or negedge RstN) begin
        if (!RstN) begin
            A <= {(N+1){1'b0}};
            Q <= {N{1'b0}};
            Q_1 <= 1'b0;
            M <= {N{1'b0}};
            Remaining <= {DistW{1'b0}};
            Bmap <= {N{1'b0}};
        end
        else if (Load) begin
            A <= {(N+1){1'b0}};
            Q <= Multiplier;
            Q_1 <= 1'b0;
            M <= Multiplicand;
            Remaining <= N;
            Bmap <= BmapInit;
        end
        else if (Step) begin
            {A, Q, Q_1} <= Shifted;
            Remaining <= Remaining - Dist;
            Bmap <= BmapShifted[N-1:0];
        end
    end

    // Drop A's guard bit after all N multiplier bits have been consumed.
    assign Product = {A[N-1:0], Q};

endmodule

DSDL5/Final/quartus/booth_control.v
// Controller for the Start/Load/Step/Done handshake.
module booth_control (Clk, RstN, Start, LastStep, Load, Step, Done);

    input wire Clk;
    input wire RstN; // asynchronous active-low reset
    input wire Start;
    input wire LastStep;
    output wire Load;
    output wire Step;
    output wire Done; // one-cycle result-valid pulse

    localparam IDLE = 2'd0, LOAD = 2'd1, CALC = 2'd2, REPORT = 2'd3;

    reg [1:0] State;

    always @(posedge Clk or negedge RstN) begin
        if (!RstN) State <= IDLE;
        else case (State)
            IDLE: State <= Start ? LOAD : IDLE;
            LOAD: State <= CALC;
            CALC: State <= LastStep ? REPORT : CALC;
            REPORT: State <= IDLE;
        endcase
    end

    assign Load = (State == LOAD);
    assign Step = (State == CALC);
    assign Done = (State == REPORT);

endmodule

DSDL5/Final/quartus/booth_multiplier.v
// Signed N x N Booth multiplier with variable-distance shifts.
// Pulse Start for one cycle while operands are stable. Done pulses when Product
// is valid; busy Start pulses are ignored and Product holds until the next run.

module booth_multiplier (Clk, RstN, Start, Multiplicand, Multiplier,
                         Product, Done);

    parameter N = 8;

    input wire Clk;
    input wire RstN;
    input wire Start;
    input wire [N-1:0] Multiplicand;
    input wire [N-1:0] Multiplier;
    output wire [2*N-1:0] Product;
    output wire Done;

    wire Load;
    wire Step;
    wire LastStep;

    booth_control u_control (
        .Clk(Clk),
        .RstN(RstN),
        .Start(Start),
        .LastStep(LastStep),
        .Load(Load),
        .Step(Step),
        .Done(Done)
    );

    booth_datapath #(.N(N)) u_datapath (
        .Clk(Clk),
        .RstN(RstN),
        .Load(Load),
        .Step(Step),
        .Multiplicand(Multiplicand),
        .Multiplier(Multiplier),
        .Product(Product),
        .LastStep(LastStep)
    );

endmodule

DSDL5/Final/rtl/booth_multiplier_tb.v
// Self-checking directed and exhaustive testbench for the N=8 multiplier.
// Waveforms cover directed cases only; all 65,536 pairs are still checked.

`timescale 1ns / 1ps

module booth_multiplier_tb;

    parameter N = 8;
    parameter CYCLE = 10; // 100 MHz

    reg Clk;
    reg RstN;
    reg Start;
    reg [N-1:0] Multiplicand;
    reg [N-1:0] Multiplier;
    wire [2*N-1:0] Product;
    wire Done;

    reg [2*N-1:0] Got; // product captured at Done
    integer RunSteps; // CALC cycles of the current run
    integer SumSteps; // over the whole exhaustive phase
    integer MaxSteps;
    integer MinSteps;

    reg signed [2*N-1:0] Expected;
    reg [31:0] Errors;
    reg [31:0] Runs;
    integer i, j;

    booth_multiplier #(.N(N)) dut (
        .Clk(Clk),
        .RstN(RstN),
        .Start(Start),
        .Multiplicand(Multiplicand),
        .Multiplier(Multiplier),
        .Product(Product),
        .Done(Done)
    );

    initial Clk = 1'b0;
    always #(CYCLE/2) Clk = ~Clk;

    // Count datapath calculation cycles, excluding load/report overhead.
    always @(posedge Clk)
        if (dut.Step) RunSteps = RunSteps + 1;

    // Run one multiplication and compare it with Verilog's signed multiply.
    task do_mul;
        input reg [N-1:0] a;
        input reg [N-1:0] b;
        begin
            @(negedge Clk);
            Multiplicand = a;
            Multiplier = b;
            Start = 1'b1;
            RunSteps = 0;

            @(negedge Clk);
            Start = 1'b0;

            while (!Done) @(negedge Clk);
            Got = Product;

            Expected = $signed(a) * $signed(b);
            Runs = Runs + 1;

            if (Got !== Expected) begin
                Errors = Errors + 1;
                $display("FAIL: %0d * %0d -> %0d (%h), expected %0d (%h)",
                         $signed(a), $signed(b), $signed(Got), Got,
                         Expected, Expected);
            end

            SumSteps = SumSteps + RunSteps;
            if (RunSteps > MaxSteps) MaxSteps = RunSteps;
            if (RunSteps < MinSteps) MinSteps = RunSteps;
        end
    endtask

    // Print directed cases for use in the report.
    task show_mul;
        input reg [N-1:0] a;
        input reg [N-1:0] b;
        input reg [8*44-1:0] note;
        begin
            do_mul(a, b);
            $display("  %5d * %5d = %6d   steps: %0d   %0s",
                     $signed(a), $signed(b), $signed(Got), RunSteps, note);
        end
    endtask

    initial begin
        Errors = 0;
        Runs = 0;
        SumSteps = 0;
        MaxSteps = 0;
        MinSteps = 1000;
        RunSteps = 0;

        $dumpfile("booth_multiplier_tb.vcd");
        $dumpvars(0, booth_multiplier_tb);

        Start = 1'b0;
        Multiplicand = {N{1'b0}};
        Multiplier = {N{1'b0}};

        RstN = 1'b0;
        repeat (2) @(negedge Clk);
        RstN = 1'b1;
        @(negedge Clk);

        // Directed corner cases.
        $display("");
        $display("--- directed cases ---");

        show_mul(8'd0, 8'd0, "zero");
        show_mul(8'd0, -8'd128, "zero x min");
        show_mul(8'd1, 8'd1, "one");
        show_mul(-8'd1, -8'd1, "-1 x -1");
        show_mul(8'd3, 8'd5, "small positive");
        show_mul(-8'd3, 8'd5, "negative x positive");
        show_mul(8'd3, -8'd5, "positive x negative");
        show_mul(-8'd3, -8'd5, "negative x negative");
        show_mul(8'd3, 8'd7, "run of ones in Q");
        show_mul(-8'd128, 8'd2, "min x 2: overflows an N-bit accumulator");
        show_mul(-8'd128, -8'd128, "min x min: largest product");
        show_mul(8'd127, 8'd127, "max x max");
        show_mul(-8'd128, 8'd127, "min x max");
        show_mul(8'h55, 8'hAA, "alternating bits: worst case");
        show_mul(8'd5, -8'd1, "all ones multiplier: best case");

        if (Errors == 0) $display("  directed cases clean");

        // Exhaustive verification.
        $dumpoff; // 65536 runs would make the VCD useless
        $display("");
        $display("--- exhaustive: all %0d signed operand pairs ---", 256*256);

        Runs = 0;
        SumSteps = 0;
        MaxSteps = 0;
        MinSteps = 1000;

        for (i = 0; i < 256; i = i + 1)
            for (j = 0; j < 256; j = j + 1)
                do_mul(i[N-1:0], j[N-1:0]);

        $display("  %0d products checked against Verilog signed multiply", Runs);
        $display("");
        $display("--- cycle cost per multiply (CALC steps only) ---");
        $display("  plain shift-and-add / 1-bit Booth: %0d steps always", N);
        $display("  this design: min %0d, max %0d, average %0.2f  (%0.1f%% of it)",
                 MinSteps, MaxSteps, SumSteps * 1.0 / Runs,
                 SumSteps * 100.0 / (Runs * N));

        $display("");
        if (Errors == 0)
            $display("========== PASS: booth_multiplier clean ==========");
        else
            $display("========== FAIL: %0d error(s) ==========", Errors);
        $finish;
    end

endmodule

DSDL5/Final/sim/booth_multiplier_tb.vcd
$date
	Sun Aug 16 04:19:29 2026
$end
$version
	Icarus Verilog
$end
$timescale
	1ps
$end
$scope module booth_multiplier_tb $end
$var wire 16 ! Product [15:0] $end
$var wire 1 " Done $end
$var parameter 32 # CYCLE $end
$var parameter 32 $ N $end
$var reg 1 % Clk $end
$var reg 32 & Errors [31:0] $end
$var reg 16 ' Expected [15:0] $end
$var reg 16 ( Got [15:0] $end
$var reg 8 ) Multiplicand [7:0] $end
$var reg 8 * Multiplier [7:0] $end
$var reg 1 + RstN $end
$var reg 32 , Runs [31:0] $end
$var reg 1 - Start $end
$var integer 32 . MaxSteps [31:0] $end
$var integer 32 / MinSteps [31:0] $end
$var integer 32 0 RunSteps [31:0] $end
$var integer 32 1 SumSteps [31:0] $end
$var integer 32 2 i [31:0] $end
$var integer 32 3 j [31:0] $end
$scope module dut $end
$var wire 1 % Clk $end
$var wire 8 4 Multiplicand [7:0] $end
$var wire 8 5 Multiplier [7:0] $end
$var wire 1 + RstN $end
$var wire 1 - Start $end
$var wire 1 6 Step $end
$var wire 16 7 Product [15:0] $end
$var wire 1 8 Load $end
$var wire 1 9 LastStep $end
$var wire 1 " Done $end
$var parameter 32 : N $end
$scope module u_control $end
$var wire 1 % Clk $end
$var wire 1 + RstN $end
$var wire 1 - Start $end
$var wire 1 6 Step $end
$var wire 1 8 Load $end
$var wire 1 9 LastStep $end
$var wire 1 " Done $end
$var parameter 2 ; CALC $end
$var parameter 2 < IDLE $end
$var parameter 2 = LOAD $end
$var parameter 2 > REPORT $end
$var reg 2 ? State [1:0] $end
$upscope $end
$scope module u_datapath $end
$var wire 8 @ BmapInit [7:0] $end
$var wire 1 % Clk $end
$var wire 1 A DoAdd $end
$var wire 1 B DoSub $end
$var wire 1 8 Load $end
$var wire 8 C Multiplicand [7:0] $end
$var wire 8 D Multiplier [7:0] $end
$var wire 1 + RstN $end
$var wire 1 6 Step $end
$var wire 18 E Shifted [17:0] $end
$var wire 4 F Raw [3:0] $end
$var wire 16 G Product [15:0] $end
$var wire 9 H MExt [8:0] $end
$var wire 1 9 LastStep $end
$var wire 5 I DistWide [4:0] $end
$var wire 4 J Dist [3:0] $end
$var wire 9 K BmapShifted [8:0] $end
$var wire 9 L AOp [8:0] $end
$var parameter 32 M DistW $end
$var parameter 32 N N $end
$var parameter 32 O ShiftAmountW $end
$var reg 9 P A [8:0] $end
$var reg 8 Q Bmap [7:0] $end
$var reg 8 R M [7:0] $end
$var reg 8 S Q [7:0] $end
$var reg 1 T Q_1 $end
$var reg 4 U Remaining [3:0] $end
$scope module u_encode $end
$var wire 9 V Map [8:0] $end
$var parameter 32 W DistW $end
$var parameter 33 X MapW $end
$var parameter 34 Y MaxSkip $end
$var reg 4 Z Dist [3:0] $end
$var integer 32 [ k [31:0] $end
$upscope $end
$scope module u_map_shift $end
$var wire 4 \ amt [3:0] $end
$var wire 9 ] din [8:0] $end
$var parameter 32 ^ AmountW $end
$var parameter 33 _ W $end
$var reg 9 ` dout [8:0] $end
$var integer 32 a k [31:0] $end
$upscope $end
$scope module u_shift $end
$var wire 5 b amt [4:0] $end
$var wire 18 c din [17:0] $end
$var parameter 32 d AmountW $end
$var parameter 65 e W $end
$var reg 18 f dout [17:0] $end
$var integer 32 g k [31:0] $end
$upscope $end
$upscope $end
$upscope $end
$scope task do_mul $end
$var reg 8 h a [7:0] $end
$var reg 8 i b [7:0] $end
$upscope $end
$scope task show_mul $end
$var reg 8 j a [7:0] $end
$var reg 8 k b [7:0] $end
$var reg 352 l note [351:0] $end
$upscope $end
$upscope $end
$enddefinitions $end
$comment Show the parameter values. $end
$dumpall
b10010 e
b101 d
b1001 _
b100 ^
b1000 Y
b1001 X
b100 W
b101 O
b1000 N
b100 M
b11 >
b1 =
b0 <
b10 ;
b1000 :
b1000 $
b1010 #
$end
#0
$dumpvars
bx l
bx k
bx j
bx i
bx h
b101 g
b0 f
b0 c
b0 b
b100 a
b0 `
b0 ]
b0 \
b0 [
b1000 Z
b0 V
b0 U
0T
b0 S
b0 R
b0 Q
b0 P
b0 L
b0 K
b0 J
b0 I
b0 H
b0 G
b1000 F
b0 E
b0 D
b0 C
0B
0A
b0 @
b0 ?
19
08
b0 7
06
b0 5
b0 4
bx 3
bx 2
b0 1
b0 0
b1111101000 /
b0 .
0-
b0 ,
0+
b0 *
b0 )
bx (
bx '
b0 &
0%
0"
b0 !
$end
#5000
1%
#10000
0%
#15000
1%
#20000
1+
0%
#25000
1%
#30000
b0 i
b0 h
b1111010011001010111001001101111 l
b0 k
b0 j
0%
#35000
1%
#40000
1-
0%
#45000
18
b1 ?
1%
#50000
0-
0%
#55000
b101 g
b100 a
b1000 I
b1000 b
b1000 J
b1000 \
08
16
b10 ?
19
b1000 U
1%
#60000
0%
#65000
b101 g
b100 a
b0 I
b0 b
b0 J
b0 \
19
b0 U
06
1"
b11 ?
b1 0
1%
#70000
b10000000 i
b1111010011001010111001001101111001000000111100000100000011011010110100101101110 l
b10000000 k
b1 /
b1 .
b1 1
b1 ,
b0 '
b0 (
0%
#75000
0"
b0 ?
1%
#80000
b10000000 @
b0 0
1-
b10000000 *
b10000000 5
b10000000 D
0%
#85000
18
b1 ?
1%
#90000
0-
0%
#95000
b111 F
b111 Z
b0 [
b100 a
b1 K
b1 `
b111 I
b111 b
b111 J
b111 \
b101 g
b10 E
b10 f
08
16
b10 ?
b10000000 V
b10000000 ]
b10000000 Q
09
b1000 U
b100000000 c
b10000000 !
b10000000 7
b10000000 G
b10000000 S
1%
#100000
0%
#105000
1B
b0 [
b1000 F
b1000 Z
b0 K
b0 `
b100 a
19
b1 I
b1 b
b1 J
b1 \
b1 E
b1 f
b101 g
b1 V
b1 ]
b1 Q
b1 U
b10 c
b1 !
b1 7
b1 G
b1 S
b1 0
1%
#110000
0%
#115000
1A
0B
b0 [
b100 a
b0 I
b0 b
b0 J
b0 \
b1 E
b1 f
b101 g
06
1"
b11 ?
b0 V
b0 ]
b0 Q
19
b0 U
b0 !
b0 7
b0 G
b0 S
b1 c
1T
b10 0
1%
#120000
b1 i
b1 h
b11011110110111001100101 l
b1 k
b1 j
b10 .
b11 1
b10 ,
0%
#125000
0"
b0 ?
1%
#130000
b11 @
b0 0
1-
b1 *
b1 5
b1 D
b1 )
b1 4
b1 C
0%
#135000
18
b1 ?
1%
#140000
0-
0%
#145000
b111111111 L
1B
b1 F
b1 Z
b0 [
b100 a
b1 K
b1 `
b1 I
b1 b
b1 J
b1 \
0A
b101 g
b111111111100000001 E
b111111111100000001 f
b11 V
b11 ]
b11 Q
09
b1000 U
b1 H
b1 R
0T
b111111111000000010 c
b1 !
b1 7
b1 G
b1 S
08
16
b10 ?
1%
#150000
0%
#155000
1A
19
b111 I
b111 b
b111 J
b111 \
0B
b0 [
b1000 F
b1000 Z
b0 K
b0 `
b100 a
b0 L
b10 E
b10 f
b101 g
b1 V
b1 ]
b1 Q
b111 U
b111111111 P
b1111111110000000 !
b1111111110000000 7
b1111111110000000 G
b10000000 S
b100000001 c
1T
b1 0
1%
#160000
0%
#165000
b111111111 L
1B
b0 [
b100 a
b0 I
b0 b
b0 J
b0 \
b111111111000000010 E
b111111111000000010 f
b101 g
0A
b0 V
b0 ]
b0 Q
19
b0 U
b0 P
b1 !
b1 7
b1 G
b1 S
b111111111000000010 c
0T
06
1"
b11 ?
b10 0
1%
#170000
b11111111 i
b11111111 h
b101101001100010010000001111000001000000010110100110001 l
b11111111 k
b11111111 j
b101 1
b11 ,
b1 '
b1 (
0%
#175000
0"
b0 ?
1%
#180000
b1 @
b0 0
1-
b11111111 *
b11111111 5
b11111111 D
b11111111 )
b11111111 4
b11111111 C
0%
#185000
18
b1 ?
1%
#190000
0-
0%
#195000
b0 [
b100 a
b0 K
b0 `
b1000 I
b1000 b
b1000 J
b1000 \
b1 L
b101 g
b11 E
b11 f
08
16
b10 ?
b1 V
b1 ]
b1 Q
19
b1000 U
b111111111 H
b11111111 R
b1111111110 c
b11111111 !
b11111111 7
b11111111 G
b11111111 S
1%
#200000
0%
#205000
b0 L
0B
b0 [
b100 a
b0 I
b0 b
b0 J
b0 \
b101 g
b11 E
b11 f
b0 V
b0 ]
b0 Q
19
b0 U
b1 !
b1 7
b1 G
b1 S
b11 c
1T
06
1"
b11 ?
b1 0
1%
#210000
b101 i
b11 h
b111001101101101011000010110110001101100001000000111000001101111011100110110100101110100011010010111011001100101 l
b101 k
b11 j
b110 1
b100 ,
0%
#215000
0"
b0 ?
1%
#220000
b1111 @
b0 0
1-
b101 *
b101 5
b101 D
b11 )
b11 4
b11 C
0%
#225000
18
b1 ?
1%
#230000
0-
0%
#235000
b111111101 L
1B
b1 F
b1 Z
b0 [
b100 a
b111 K
b111 `
b1 I
b1 b
b1 J
b1 \
b101 g
b111111110100000101 E
b111111110100000101 f
08
16
b10 ?
b1111 V
b1111 ]
b1111 Q
09
b1000 U
b11 H
b11 R
0T
b111111101000001010 c
b101 !
b101 7
b101 G
b101 S
1%
#240000
0%
#245000
1A
0B
b0 [
b1 F
b1 Z
b11 K
b11 `
b100 a
b1 L
b101 g
b110000010 E
b110000010 f
b111 V
b111 ]
b111 Q
b111 U
b111111110 P
b1111111010000010 !
b1111111010000010 7
b1111111010000010 G
b10000010 S
b1100000101 c
1T
b1 0
1%
#250000
0%
#255000
b111111101 L
1B
b0 [
b1 F
b1 Z
b1 K
b1 `
b100 a
b101 g
b111111110111000001 E
b111111110111000001 f
0A
b11 V
b11 ]
b11 Q
b110 U
b0 P
b11000001 !
b11000001 7
b11000001 G
b11000001 S
b111111101110000010 c
0T
b10 0
1%
#260000
0%
#265000
1A
19
b101 I
b101 b
b101 J
b101 \
0B
b0 [
b1000 F
b1000 Z
b0 K
b0 `
b100 a
b1 L
b101 g
b11110 E
b11110 f
b1 V
b1 ]
b1 Q
b101 U
b111111110 P
b1111111011100000 !
b1111111011100000 7
b1111111011100000 G
b11100000 S
b1111000001 c
1T
b11 0
1%
#270000
0%
#275000
b111111101 L
1B
b0 [
b100 a
b0 I
b0 b
b0 J
b0 \
b101 g
b111111101000011110 E
b111111101000011110 f
0A
06
1"
b11 ?
b0 V
b0 ]
b0 Q
19
b0 U
b0 P
b1111 !
b1111 7
b1111 G
b1111 S
b111111101000011110 c
0T
b100 0
1%
#280000
b11111101 h
b1101110011001010110011101100001011101000110100101110110011001010010000001111000001000000111000001101111011100110110100101110100011010010111011001100101 l
b11111101 j
b100 .
b1010 1
b101 ,
b1111 '
b1111 (
0%
#285000
0"
b0 ?
1%
#290000
b0 0
1-
b11111101 )
b11111101 4
b11111101 C
0%
#295000
18
b1 ?
1%
#300000
0-
0%
#305000
b1 F
b1 Z
b0 [
b100 a
b111 K
b111 `
b1 I
b1 b
b1 J
b1 \
b11 L
b101 g
b1100000101 E
b1100000101 f
b1111 V
b1111 ]
b1111 Q
09
b1000 U
b111111101 H
b11111101 R
b11000001010 c
b101 !
b101 7
b101 G
b101 S
08
16
b10 ?
1%
#310000
0%
#315000
1A
0B
b0 [
b1 F
b1 Z
b11 K
b11 `
b100 a
b111111110 L
b101 g
b111111111010000010 E
b111111111010000010 f
b111 V
b111 ]
b111 Q
b111 U
b1 P
b110000010 !
b110000010 7
b110000010 G
b10000010 S
b111111110100000101 c
1T
b1 0
1%
#320000
0%
#325000
b10 L
1B
b0 [
b1 F
b1 Z
b1 K
b1 `
b100 a
b101 g
b1001000001 E
b1001000001 f
0A
b11 V
b11 ]
b11 Q
b110 U
b111111111 P
b1111111101000001 !
b1111111101000001 7
b1111111101000001 G
b1000001 S
b10010000010 c
0T
b10 0
1%
#330000
0%
#335000
1A
19
b101 I
b101 b
b101 J
b101 \
0B
b0 [
b1000 F
b1000 Z
b0 K
b0 `
b100 a
b111111110 L
b101 g
b111111111111100010 E
b111111111111100010 f
b1 V
b1 ]
b1 Q
b101 U
b1 P
b100100000 !
b100100000 7
b100100000 G
b100000 S
b111111110001000001 c
1T
b11 0
1%
#340000
0%
#345000
b10 L
1B
b0 [
b100 a
b0 I
b0 b
b0 J
b0 \
b101 g
b10111100010 E
b10111100010 f
0A
b0 V
b0 ]
b0 Q
19
b0 U
b111111111 P
b1111111111110001 !
b1111111111110001 7
b1111111111110001 G
b11110001 S
b10111100010 c
0T
06
1"
b11 ?
b100 0
1%
#350000
b11111011 i
b11 h
b1110000011011110111001101101001011101000110100101110110011001010010000001111000001000000110111001100101011001110110000101110100011010010111011001100101 l
b11111011 k
b11 j
b1110 1
b110 ,
b1111111111110001 '
b1111111111110001 (
0%
#355000
0"
b0 ?
1%
#360000
b1101 @
b0 0
1-
b11111011 *
b11111011 5
b11111011 D
b11 )
b11 4
b11 C
0%
#365000
18
b1 ?
1%
#370000
0-
0%
#375000
b10 F
b10 Z
b0 [
b100 a
b11 K
b11 `
b10 I
b10 b
b10 J
b10 \
b101 g
b111111111011111101 E
b111111111011111101 f
b111111101 L
08
16
b10 ?
b1101 V
b1101 ]
b1101 Q
09
b1000 U
b11 H
b11 R
b111111101111110110 c
b11111011 !
b11111011 7
b11111011 G
b11111011 S
b0 P
1%
#380000
0%
#385000
1A
b1 I
b1 b
b1 J
b1 \
0B
b0 [
b1 F
b1 Z
b1 K
b1 `
b100 a
b10 L
b101 g
b1001111110 E
b1001111110 f
b11 V
b11 ]
b11 Q
b110 U
b111111111 P
b1111111101111110 !
b1111111101111110 7
b1111111101111110 G
b1111110 S
b10011111101 c
1T
b1 0
1%
#390000
0%
#395000
19
b101 I
b101 b
b101 J
b101 \
b111111110 L
1B
b0 [
b1000 F
b1000 Z
b0 K
b0 `
b100 a
b101 g
b111111111111100011 E
b111111111111100011 f
0A
b1 V
b1 ]
b1 Q
b101 U
b1 P
b100111111 !
b100111111 7
b100111111 G
b111111 S
b111111110001111110 c
0T
b10 0
1%
#400000
0%
#405000
0B
b0 [
b100 a
b0 I
b0 b
b0 J
b0 \
b111111111 L
b101 g
b111111111111100011 E
b111111111111100011 f
b0 V
b0 ]
b0 Q
19
b0 U
b111111111 P
b1111111111110001 !
b1111111111110001 7
b1111111111110001 G
b11110001 S
b111111111111100011 c
1T
06
1"
b11 ?
b11 0
1%
#410000
b11111101 h
b1101110011001010110011101100001011101000110100101110110011001010010000001111000001000000110111001100101011001110110000101110100011010010111011001100101 l
b11111101 j
b10001 1
b111 ,
0%
#415000
0"
b0 ?
1%
#420000
b0 0
1-
b11111101 )
b11111101 4
b11111101 C
0%
#425000
18
b1 ?
1%
#430000
0-
0%
#435000
1B
b11 L
b10 F
b10 Z
b0 [
b100 a
b11 K
b11 `
b10 I
b10 b
b10 J
b10 \
b101 g
b111111101 E
b111111101 f
08
16
b10 ?
b1101 V
b1101 ]
b1101 Q
09
b1000 U
b111111101 H
b11111101 R
0T
b11111110110 c
b11111011 !
b11111011 7
b11111011 G
b11111011 S
b0 P
1%
#440000
0%
#445000
1A
b111111101 L
b1 I
b1 b
b1 J
b1 \
0B
b0 [
b1 F
b1 Z
b1 K
b1 `
b100 a
b101 g
b111111110111111110 E
b111111110111111110 f
b11 V
b11 ]
b11 Q
b110 U
b11111110 !
b11111110 7
b11111110 G
b11111110 S
b111111101111111101 c
1T
b1 0
1%
#450000
0%
#455000
19
b101 I
b101 b
b101 J
b101 \
b1 L
1B
b0 [
b1000 F
b1000 Z
b0 K
b0 `
b100 a
b101 g
b11111 E
b11111 f
0A
b1 V
b1 ]
b1 Q
b101 U
b111111110 P
b1111111011111111 !
b1111111011111111 7
b1111111011111111 G
b11111111 S
b1111111110 c
0T
b10 0
1%
#460000
0%
#465000
0B
b0 [
b100 a
b0 I
b0 b
b0 J
b0 \
b0 L
b101 g
b11111 E
b11111 f
b0 V
b0 ]
b0 Q
19
b0 U
b0 P
b1111 !
b1111 7
b1111 G
b1111 S
b11111 c
1T
06
1"
b11 ?
b11 0
1%
#470000
b111 i
b11 h
b1110010011101010110111000100000011011110110011000100000011011110110111001100101011100110010000001101001011011100010000001010001 l
b111 k
b11 j
b10100 1
b1000 ,
b1111 '
b1111 (
0%
#475000
0"
b0 ?
1%
#480000
b1001 @
b0 0
1-
b111 *
b111 5
b111 D
b11 )
b11 4
b11 C
0%
#485000
18
b1 ?
1%
#490000
0-
0%
#495000
b111111101 L
1B
b11 F
b11 Z
b0 [
b100 a
b1 K
b1 `
b11 I
b11 b
b11 J
b11 \
b101 g
b111111111101000001 E
b111111111101000001 f
08
16
b10 ?
b1001 V
b1001 ]
b1001 Q
09
b1000 U
b11 H
b11 R
0T
b111111101000001110 c
b111 !
b111 7
b111 G
b111 S
1%
#500000
0%
#505000
1A
19
b101 I
b101 b
b101 J
b101 \
0B
b0 [
b1000 F
b1000 Z
b0 K
b0 `
b100 a
b10 L
b101 g
b101010 E
b101010 f
b1 V
b1 ]
b1 Q
b101 U
b111111111 P
b1111111110100000 !
b1111111110100000 7
b1111111110100000 G
b10100000 S
b10101000001 c
1T
b1 0
1%
#510000
0%
#515000
b111111101 L
1B
b0 [
b100 a
b0 I
b0 b
b0 J
b0 \
b101 g
b111111101000101010 E
b111111101000101010 f
0A
06
1"
b11 ?
b0 V
b0 ]
b0 Q
19
b0 U
b0 P
b10101 !
b10101 7
b10101 G
b10101 S
b111111101000101010 c
0T
b10 0
1%
#520000
b10 i
b10000000 h
b11011010110100101101110001000000111100000100000001100100011101000100000011011110111011001100101011100100110011001101100011011110111011101110011001000000110000101101110001000000100111000101101011000100110100101110100001000000110000101100011011000110111010101101101011101010110110001100001011101000110111101110010 l
b10 k
b10000000 j
b10110 1
b1001 ,
b10101 '
b10101 (
0%
#525000
0"
b0 ?
1%
#530000
b110 @
b0 0
1-
b10 *
b10 5
b10 D
b10000000 )
b10000000 4
b10000000 C
0%
#535000
18
b1 ?
1%
#540000
0-
0%
#545000
0B
b1 F
b1 Z
b0 [
b100 a
b11 K
b11 `
b1 I
b1 b
b1 J
b1 \
b0 L
b101 g
b10 E
b10 f
b110 V
b110 ]
b110 Q
09
b1000 U
b110000000 H
b10000000 R
b100 c
b10 !
b10 7
b10 G
b10 S
08
16
b10 ?
1%
#550000
0%
#555000
b10000000 L
1B
b0 [
b1 F
b1 Z
b1 K
b1 `
b100 a
b1000000000000001 E
b1000000000000001 f
b101 g
b11 V
b11 ]
b11 Q
b111 U
b10000000000000010 c
b1 !
b1 7
b1 G
b1 S
b1 0
1%
#560000
0%
#565000
1A
19
b110 I
b110 b
b110 J
b110 \
0B
b0 [
b1000 F
b1000 Z
b0 K
b0 `
b100 a
b111000000 L
b101 g
b111111111000000000 E
b111111111000000000 f
b1 V
b1 ]
b1 Q
b110 U
b1000000 P
b100000000000000 !
b100000000000000 7
b100000000000000 G
b0 S
b111000000000000001 c
1T
b10 0
1%
#570000
0%
#575000
b111111111 L
b0 [
b100 a
b0 I
b0 b
b0 J
b0 \
b1111111100000000 !
b1111111100000000 7
b1111111100000000 G
b101 g
b111111111000000000 E
b111111111000000000 f
0A
06
1"
b11 ?
b0 V
b0 ]
b0 Q
19
b0 U
b111111111 P
b111111111000000000 c
0T
b11 0
1%
#580000
b10000000 i
b110110101101001011011100010000001111000001000000110110101101001011011100011101000100000011011000110000101110010011001110110010101110011011101000010000001110000011100100110111101100100011101010110001101110100 l
b10000000 k
b11001 1
b1010 ,
b1111111100000000 '
b1111111100000000 (
0%
#585000
0"
b0 ?
1%
#590000
b10000000 @
b0 0
1-
b10000000 *
b10000000 5
b10000000 D
0%
#595000
18
b1 ?
1%
#600000
0-
0%
#605000
b0 L
b111 F
b111 Z
b0 [
b100 a
b1 K
b1 `
b111 I
b111 b
b111 J
b111 \
b101 g
b10 E
b10 f
b10000000 V
b10000000 ]
b10000000 Q
09
b1000 U
b100000000 c
b10000000 !
b10000000 7
b10000000 G
b10000000 S
b0 P
08
16
b10 ?
1%
#610000
0%
