DSDL5/Final/rtl/barrel_ashr.v
// Variable-distance combinational arithmetic-right shifter.
module barrel_ashr (din, amt, dout);
    parameter W = 18;
    localparam AmountW = $clog2(W);

    input wire [W-1:0] din;
    input wire [AmountW-1:0] amt;
    output reg [W-1:0] dout;

    integer k;

    always @* begin
        dout = din;
        for (k = 0; k < AmountW; k = k + 1)
            if (amt[k]) dout = $signed(dout) >>> (1 << k);
    end

endmodule

DSDL5/Final/rtl/skip_encode.v
// Returns the distance to the nearest upcoming Booth boundary.
module skip_encode (Map, Dist);

    parameter MapW = 9;
    localparam DistW = $clog2(MapW);
    localparam MaxSkip = MapW - 1;

    input wire [MapW-1:0] Map;
    output reg [DistW-1:0] Dist;

    integer k;

    always @* begin
        Dist = MaxSkip;
        // Descending scan lets the nearest (lowest) set bit win.
        for (k = MaxSkip; k >= 1; k = k - 1)
            if (Map[k]) Dist = k;
    end

endmodule

DSDL5/Final/rtl/booth_datapath.v
// Booth datapath: {A, Q, Q_1} is shifted as one 2N+2-bit register.
// A has a guard bit so negating the most-negative N-bit value cannot overflow.
// A precomputed boundary map enables multi-bit skips between Booth operations.
// N must be at least 2.

module booth_datapath (Clk, RstN, Load, Step, Multiplicand, Multiplier,
                       Product, LastStep);

    parameter N = 8;

    localparam DistW = $clog2(N+1);
    localparam ShiftAmountW = $clog2(2*N+2);

    input wire Clk;
    input wire RstN;
    input wire Load;
    input wire Step;
    input wire [N-1:0] Multiplicand;
    input wire [N-1:0] Multiplier;
    output wire [2*N-1:0] Product;
    // High while the current Step consumes every remaining multiplier bit.
    output wire LastStep;

    reg [N:0] A;
    reg [N-1:0] Q;
    reg Q_1;
    reg [N-1:0] M;
    reg [DistW-1:0] Remaining;
    reg [N-1:0] Bmap;

    // Booth pair 01 adds, 10 subtracts, and 00/11 only shift.
    wire DoAdd = (~Q[0]) & Q_1;
    wire DoSub = Q[0] & ~Q_1;

    // Sign extension preserves negative M values in the wider accumulator.
    wire [N:0] MExt = {M[N-1], M};

    wire [N:0] AOp = DoSub ? (A - MExt) : DoAdd ? (A + MExt) : A;

    // A set bit marks a Booth transition: Q[i] XOR Q[i-1], with Q[-1]=0.
    // The map shifts with Q so bit zero always describes the current position.
    wire [N-1:0] BmapInit = Multiplier ^ {Multiplier[N-2:0], 1'b0};

    // The leading zero lets the encoder return N when no boundary remains.
    wire [DistW-1:0] Raw;

    skip_encode #(.MapW(N+1)) u_encode (
        .Map({1'b0, Bmap}),
        .Dist(Raw)
    );

    // Cap the skip at the number of unprocessed multiplier bits.
    wire [DistW-1:0] Dist = (Raw < Remaining) ? Raw : Remaining;

    assign LastStep = (Dist == Remaining);

    wire [N:0] BmapShifted;

    barrel_ashr #(.W(N+1)) u_map_shift (
        .din({1'b0, Bmap}),
        .amt(Dist),
        .dout(BmapShifted)
    );

    wire [2*N+1:0] Shifted;

    wire [ShiftAmountW-1:0] DistWide = Dist;

    barrel_ashr #(.W(2*N+2)) u_shift (
        .din({AOp, Q, Q_1}),
        .amt(DistWide),
        .dout(Shifted)
    );

    always @(posedge Clk or negedge RstN) begin
        if (!RstN) begin
            A <= {(N+1){1'b0}};
            Q <= {N{1'b0}};
            Q_1 <= 1'b0;
            M <= {N{1'b0}};
            Remaining <= {DistW{1'b0}};
            Bmap <= {N{1'b0}};
        end
        else if (Load) begin
            A <= {(N+1){1'b0}};
            Q <= Multiplier;
            Q_1 <= 1'b0;
            M <= Multiplicand;
            Remaining <= N;
            Bmap <= BmapInit;
        end
        else if (Step) begin
            {A, Q, Q_1} <= Shifted;
            Remaining <= Remaining - Dist;
            Bmap <= BmapShifted[N-1:0];
        end
    end

    // Drop A's guard bit after all N multiplier bits have been consumed.
    assign Product = {A[N-1:0], Q};

endmodule

DSDL5/Final/quartus/booth_control.v
// Controller for the Start/Load/Step/Done handshake.
module booth_control (Clk, RstN, Start, LastStep, Load, Step, Done);

    input wire Clk;
    input wire RstN; // asynchronous active-low reset
    input wire Start;
    input wire LastStep;
    output wire Load;
    output wire Step;
    output wire Done; // one-cycle result-valid pulse

    localparam IDLE = 2'd0, LOAD = 2'd1, CALC = 2'd2, REPORT = 2'd3;

    reg [1:0] State;

    always @(posedge Clk or negedge RstN) begin
        if (!RstN) State <= IDLE;
        else case (State)
            IDLE: State <= Start ? LOAD : IDLE;
            LOAD: State <= CALC;
            CALC: State <= LastStep ? REPORT : CALC;
            REPORT: State <= IDLE;
        endcase
    end

    assign Load = (State == LOAD);
    assign Step = (State == CALC);
    assign Done = (State == REPORT);

endmodule

DSDL5/Final/quartus/booth_multiplier.v
// Signed N x N Booth multiplier with variable-distance shifts.
// Pulse Start for one cycle while operands are stable. Done pulses when Product
// is valid; busy Start pulses are ignored and Product holds until the next run.

module booth_multiplier (Clk, RstN, Start, Multiplicand, Multiplier,
                         Product, Done);

    parameter N = 8;

    input wire Clk;
    input wire RstN;
    input wire Start;
    input wire [N-1:0] Multiplicand;
    input wire [N-1:0] Multiplier;
    output wire [2*N-1:0] Product;
    output wire Done;

    wire Load;
    wire Step;
    wire LastStep;

    booth_control u_control (
        .Clk(Clk),
        .RstN(RstN),
        .Start(Start),
        .LastStep(LastStep),
        .Load(Load),
        .Step(Step),
        .Done(Done)
    );

    booth_datapath #(.N(N)) u_datapath (
        .Clk(Clk),
        .RstN(RstN),
        .Load(Load),
        .Step(Step),
        .Multiplicand(Multiplicand),
        .Multiplier(Multiplier),
        .Product(Product),
        .LastStep(LastStep)
    );

endmodule

DSDL5/Final/rtl/booth_multiplier_3x7_tb.v
`timescale 1ns / 1ps

module booth_multiplier_3x7_tb;

    reg Clk;
    reg RstN;
    reg Start;
    reg [7:0] Multiplicand;
    reg [7:0] Multiplier;
    wire [15:0] Product;
    wire Done;

    booth_multiplier dut (
        .Clk(Clk),
        .RstN(RstN),
        .Start(Start),
        .Multiplicand(Multiplicand),
        .Multiplier(Multiplier),
        .Product(Product),
        .Done(Done)
    );

    initial Clk = 1'b0;
    always #5 Clk = ~Clk;

    initial begin
        $dumpfile("booth_multiplier_3x7_tb.vcd");
        $dumpvars(0, booth_multiplier_3x7_tb);

        RstN = 1'b0;
        Start = 1'b0;
        Multiplicand = 8'd0;
        Multiplier = 8'd0;

        repeat (2) @(negedge Clk);
        RstN = 1'b1;

        @(negedge Clk);
        Multiplicand = 8'd3;
        Multiplier = 8'd7;
        Start = 1'b1;

        @(negedge Clk);
        Start = 1'b0;

        wait (Done);
        #1;

        if (Product === 16'd21)
            $display("PASS: 3 * 7 = %0d", Product);
        else
            $fatal(1, "FAIL: 3 * 7 = %0d, expected 21", Product);

        @(negedge Clk);
        $finish;
    end

endmodule

DSDL5/Final/sim/booth_multiplier_3x7_tb.vcd
$date
	Sun Aug 16 06:34:23 2026
$end
$version
	Icarus Verilog
$end
$timescale
	1ps
$end
$scope module booth_multiplier_3x7_tb $end
$var wire 16 ! Product [15:0] $end
$var wire 1 " Done $end
$var reg 1 # Clk $end
$var reg 8 $ Multiplicand [7:0] $end
$var reg 8 % Multiplier [7:0] $end
$var reg 1 & RstN $end
$var reg 1 ' Start $end
$scope module dut $end
$var wire 1 # Clk $end
$var wire 8 ( Multiplicand [7:0] $end
$var wire 8 ) Multiplier [7:0] $end
$var wire 1 & RstN $end
$var wire 1 ' Start $end
$var wire 1 * Step $end
$var wire 16 + Product [15:0] $end
$var wire 1 , Load $end
$var wire 1 - LastStep $end
$var wire 1 " Done $end
$var parameter 32 . N $end
$scope module u_control $end
$var wire 1 # Clk $end
$var wire 1 & RstN $end
$var wire 1 ' Start $end
$var wire 1 * Step $end
$var wire 1 , Load $end
$var wire 1 - LastStep $end
$var wire 1 " Done $end
$var parameter 2 / CALC $end
$var parameter 2 0 IDLE $end
$var parameter 2 1 LOAD $end
$var parameter 2 2 REPORT $end
$var reg 2 3 State [1:0] $end
$upscope $end
$scope module u_datapath $end
$var wire 8 4 BmapInit [7:0] $end
$var wire 1 # Clk $end
$var wire 1 5 DoAdd $end
$var wire 1 6 DoSub $end
$var wire 1 , Load $end
$var wire 8 7 Multiplicand [7:0] $end
$var wire 8 8 Multiplier [7:0] $end
$var wire 1 & RstN $end
$var wire 1 * Step $end
$var wire 18 9 Shifted [17:0] $end
$var wire 4 : Raw [3:0] $end
$var wire 16 ; Product [15:0] $end
$var wire 9 < MExt [8:0] $end
$var wire 1 - LastStep $end
$var wire 5 = DistWide [4:0] $end
$var wire 4 > Dist [3:0] $end
$var wire 9 ? BmapShifted [8:0] $end
$var wire 9 @ AOp [8:0] $end
$var parameter 32 A DistW $end
$var parameter 32 B N $end
$var parameter 32 C ShiftAmountW $end
$var reg 9 D A [8:0] $end
$var reg 8 E Bmap [7:0] $end
$var reg 8 F M [7:0] $end
$var reg 8 G Q [7:0] $end
$var reg 1 H Q_1 $end
$var reg 4 I Remaining [3:0] $end
$scope module u_encode $end
$var wire 9 J Map [8:0] $end
$var parameter 32 K DistW $end
$var parameter 33 L MapW $end
$var parameter 34 M MaxSkip $end
$var reg 4 N Dist [3:0] $end
$var integer 32 O k [31:0] $end
$upscope $end
$scope module u_map_shift $end
$var wire 4 P amt [3:0] $end
$var wire 9 Q din [8:0] $end
$var parameter 32 R AmountW $end
$var parameter 33 S W $end
$var reg 9 T dout [8:0] $end
$var integer 32 U k [31:0] $end
$upscope $end
$scope module u_shift $end
$var wire 5 V amt [4:0] $end
$var wire 18 W din [17:0] $end
$var parameter 32 X AmountW $end
$var parameter 65 Y W $end
$var reg 18 Z dout [17:0] $end
$var integer 32 [ k [31:0] $end
$upscope $end
$upscope $end
$upscope $end
$upscope $end
$enddefinitions $end
$comment Show the parameter values. $end
$dumpall
b10010 Y
b101 X
b1001 S
b100 R
b1000 M
b1001 L
b100 K
b101 C
b1000 B
b100 A
b11 2
b1 1
b0 0
b10 /
b1000 .
$end
#0
$dumpvars
b101 [
b0 Z
b0 W
b0 V
b100 U
b0 T
b0 Q
b0 P
b0 O
b1000 N
b0 J
b0 I
0H
b0 G
b0 F
b0 E
b0 D
b0 @
b0 ?
b0 >
b0 =
b0 <
b0 ;
b1000 :
b0 9
b0 8
b0 7
06
05
b0 4
b0 3
1-
0,
b0 +
0*
b0 )
b0 (
0'
0&
b0 %
b0 $
0#
0"
b0 !
$end
#5000
1#
#10000
0#
#15000
1#
#20000
1&
0#
#25000
1#
#30000
b1001 4
1'
b111 %
b111 )
b111 8
b11 $
b11 (
b11 7
0#
#35000
1,
b1 3
1#
#40000
0'
0#
#45000
b111111101 @
16
b11 :
b11 N
b0 O
b100 U
b1 ?
b1 T
b11 =
b11 V
b11 >
b11 P
b101 [
b111111111101000001 9
b111111111101000001 Z
b1001 J
b1001 Q
b1001 E
0-
b1000 I
b11 <
b11 F
b111111101000001110 W
b111 !
b111 +
b111 ;
b111 G
0,
1*
b10 3
1#
#50000
0#
#55000
15
1-
b101 =
b101 V
b101 >
b101 P
06
b0 O
b1000 :
b1000 N
b0 ?
b0 T
b100 U
b10 @
b101 [
b101010 9
b101010 Z
b1 J
b1 Q
b1 E
b101 I
b111111111 D
b1111111110100000 !
b1111111110100000 +
b1111111110100000 ;
b10100000 G
b10101000001 W
1H
1#
#60000
0#
#65000
b111111101 @
16
b0 O
b100 U
b0 =
b0 V
b0 >
b0 P
b101 [
b111111101000101010 9
b111111101000101010 Z
05
b0 J
b0 Q
b0 E
1-
b0 I
b0 D
b10101 !
b10101 +
b10101 ;
b10101 G
b111111101000101010 W
0H
0*
1"
b11 3
1#
