DSDL7/Final/rtl/UARTReceiver.v
`timescale 1ns/1ps

// Seven-bit UART receiver for the assignment-specific parity-before-data frame.
// rx is synchronized, the start bit is confirmed at midpoint, and each later
// symbol is sampled once per BIT_TICKS clocks at the same phase.
module UARTReceiver #(
    parameter integer BIT_TICKS = 434
) (
    input  wire       clk,
    input  wire       rstN,
    input  wire       rx,
    output reg  [6:0] rec_data,
    output reg        rec_new_data,
    output reg        correct_data
);

    function integer counter_width;
        input integer value;
        integer width;
        begin
            value = value - 1;
            width = 0;
            while (value > 0) begin
                value = value >> 1;
                width = width + 1;
            end
            counter_width = width < 1 ? 1 : width;
        end
    endfunction

    localparam integer TICK_WIDTH = counter_width(BIT_TICKS);
    localparam [TICK_WIDTH-1:0] LAST_TICK = BIT_TICKS - 1;
    localparam [TICK_WIDTH-1:0] HALF_TICK = (BIT_TICKS / 2) - 1;

    localparam [2:0] IDLE   = 3'd0;
    localparam [2:0] START  = 3'd1;
    localparam [2:0] PARITY = 3'd2;
    localparam [2:0] DATA   = 3'd3;
    localparam [2:0] STOP   = 3'd4;

    reg rx_meta;
    reg rx_sync;
    reg [2:0] state;
    reg [TICK_WIDTH-1:0] tick_count;
    reg [2:0] bit_index;
    reg [6:0] data_latch;
    reg parity_latch;

    // Two flip-flops isolate the FSM from an asynchronous serial input.
    always @(posedge clk or negedge rstN) begin
        if (!rstN) begin
            rx_meta <= 1'b1;
            rx_sync <= 1'b1;
        end else begin
            rx_meta <= rx;
            rx_sync <= rx_meta;
        end
    end

    always @(posedge clk or negedge rstN) begin
        if (!rstN) begin
            state          <= IDLE;
            tick_count     <= {TICK_WIDTH{1'b0}};
            bit_index      <= 3'd0;
            data_latch     <= 7'd0;
            parity_latch   <= 1'b0;
            rec_data       <= 7'd0;
            rec_new_data   <= 1'b0;
            correct_data   <= 1'b0;
        end else begin
            // Completion and validity are aligned one-clock notifications.
            rec_new_data <= 1'b0;
            correct_data <= 1'b0;

            case (state)
                IDLE: begin
                    tick_count <= {TICK_WIDTH{1'b0}};
                    bit_index <= 3'd0;
                    if (!rx_sync)
                        state <= START;
                end

                START: begin
                    if (tick_count == HALF_TICK) begin
                        tick_count <= {TICK_WIDTH{1'b0}};
                        state <= rx_sync ? IDLE : PARITY;
                    end else begin
                        tick_count <= tick_count + 1'b1;
                    end
                end

                PARITY: begin
                    if (tick_count == LAST_TICK) begin
                        tick_count <= {TICK_WIDTH{1'b0}};
                        bit_index <= 3'd0;
                        parity_latch <= rx_sync;
                        state <= DATA;
                    end else begin
                        tick_count <= tick_count + 1'b1;
                    end
                end

                DATA: begin
                    if (tick_count == LAST_TICK) begin
                        tick_count <= {TICK_WIDTH{1'b0}};
                        data_latch[bit_index] <= rx_sync;
                        if (bit_index == 3'd6) begin
                            state <= STOP;
                        end else begin
                            bit_index <= bit_index + 1'b1;
                        end
                    end else begin
                        tick_count <= tick_count + 1'b1;
                    end
                end

                STOP: begin
                    if (tick_count == LAST_TICK) begin
                        tick_count <= {TICK_WIDTH{1'b0}};
                        rec_new_data <= 1'b1;
                        if (rx_sync && ((^data_latch) == parity_latch)) begin
                            rec_data <= data_latch;
                            correct_data <= 1'b1;
                        end
                        state <= IDLE;
                    end else begin
                        tick_count <= tick_count + 1'b1;
                    end
                end

                default: begin
                    state <= IDLE;
                    tick_count <= {TICK_WIDTH{1'b0}};
                    bit_index <= 3'd0;
                end
            endcase
        end
    end

endmodule

DSDL7/final/rtl/tb_uart_parity_error.v
`timescale 1ns/1ps

module tb_uart_parity_error;

    localparam integer BIT_TICKS = 10;
    localparam integer TIMEOUT_CYCLES = 20 * BIT_TICKS;
    localparam [6:0] SEED_DATA = 7'b1011001;
    localparam [6:0] BAD_DATA = 7'b0101101;

    reg clk;
    reg rstN;
    reg rx;
    wire [6:0] rec_data;
    wire rec_new_data;
    wire correct_data;

    UARTReceiver #(.BIT_TICKS(BIT_TICKS)) dut (
        .clk(clk),
        .rstN(rstN),
        .rx(rx),
        .rec_data(rec_data),
        .rec_new_data(rec_new_data),
        .correct_data(correct_data)
    );

    initial clk = 1'b0;
    always #5 clk = ~clk;

    task hold_rx;
        input value;
        integer cycle;
        begin
            rx = value;
            for (cycle = 0; cycle < BIT_TICKS; cycle = cycle + 1)
                @(negedge clk);
        end
    endtask

    task drive_frame;
        input [6:0] data;
        input parity_bit;
        input stop_bit;
        integer bit_index;
        begin
            @(negedge clk);
            hold_rx(1'b0);
            hold_rx(parity_bit);
            for (bit_index = 0; bit_index < 7; bit_index = bit_index + 1)
                hold_rx(data[bit_index]);
            rx = stop_bit;
        end
    endtask

    task wait_completion;
        integer cycles;
        begin
            cycles = 0;
            while (rec_new_data !== 1'b1 && cycles < TIMEOUT_CYCLES) begin
                @(negedge clk);
                cycles = cycles + 1;
            end
            if (rec_new_data !== 1'b1)
                $fatal(1, "FAIL: receiver completion timeout");
        end
    endtask

    initial begin
        $dumpfile("/tmp/tb_uart_parity_error.vcd");
        $dumpvars(0, tb_uart_parity_error);
        rstN = 1'b1;
        rx = 1'b1;
        #1 rstN = 1'b0;
        repeat (2) @(negedge clk);
        rstN = 1'b1;
        repeat (2) @(negedge clk);

        drive_frame(SEED_DATA, ^SEED_DATA, 1'b1);
        wait_completion;
        if (correct_data !== 1'b1 || rec_data !== SEED_DATA)
            $fatal(1, "FAIL: valid seed frame was not accepted");
        @(negedge clk);

        drive_frame(BAD_DATA, ~(^BAD_DATA), 1'b1);
        wait_completion;
        if (correct_data !== 1'b0)
            $fatal(1, "FAIL: corrupted parity was accepted");
        if (rec_data !== SEED_DATA)
            $fatal(1, "FAIL: invalid frame changed rec_data to %b", rec_data);
        @(negedge clk);
        if (rec_new_data !== 1'b0)
            $fatal(1, "FAIL: rec_new_data exceeded one cycle");

        $display("PASS: parity errors are rejected");
        $finish;
    end

endmodule

DSDL7/final/sim/tb_uart_parity_error.vcd
$date
	Mon Aug 24 09:43:54 2026
$end
$version
	Icarus Verilog
$end
$timescale
	1ps
$end
$scope module tb_uart_parity_error $end
$var wire 1 ! rec_new_data $end
$var wire 7 " rec_data [6:0] $end
$var wire 1 # correct_data $end
$var parameter 7 $ BAD_DATA $end
$var parameter 32 % BIT_TICKS $end
$var parameter 7 & SEED_DATA $end
$var parameter 32 ' TIMEOUT_CYCLES $end
$var reg 1 ( clk $end
$var reg 1 ) rstN $end
$var reg 1 * rx $end
$scope module dut $end
$var wire 1 ( clk $end
$var wire 1 ) rstN $end
$var wire 1 * rx $end
$var parameter 32 + BIT_TICKS $end
$var parameter 3 , DATA $end
$var parameter 4 - HALF_TICK $end
$var parameter 3 . IDLE $end
$var parameter 4 / LAST_TICK $end
$var parameter 3 0 PARITY $end
$var parameter 3 1 START $end
$var parameter 3 2 STOP $end
$var parameter 32 3 TICK_WIDTH $end
$var reg 3 4 bit_index [2:0] $end
$var reg 1 # correct_data $end
$var reg 7 5 data_latch [6:0] $end
$var reg 1 6 parity_latch $end
$var reg 7 7 rec_data [6:0] $end
$var reg 1 ! rec_new_data $end
$var reg 1 8 rx_meta $end
$var reg 1 9 rx_sync $end
$var reg 3 : state [2:0] $end
$var reg 4 ; tick_count [3:0] $end
$scope function counter_width $end
$var integer 32 < value [31:0] $end
$var integer 32 = width [31:0] $end
$upscope $end
$upscope $end
$scope task drive_frame $end
$var reg 7 > data [6:0] $end
$var reg 1 ? parity_bit $end
$var reg 1 @ stop_bit $end
$var integer 32 A bit_index [31:0] $end
$upscope $end
$scope task hold_rx $end
$var reg 1 B value $end
$var integer 32 C cycle [31:0] $end
$upscope $end
$scope task wait_completion $end
$var integer 32 D cycles [31:0] $end
$upscope $end
$upscope $end
$enddefinitions $end
$comment Show the parameter values. $end
$dumpall
b100 3
b100 2
b1 1
b10 0
b1001 /
b0 .
b100 -
b11 ,
b1010 +
b11001000 '
b1011001 &
b1010 %
b101101 $
$end
#0
$dumpvars
bx D
bx C
xB
bx A
x@
x?
bx >
bx =
bx <
bx ;
bx :
x9
x8
bx 7
x6
bx 5
bx 4
1*
1)
0(
x#
bx "
x!
$end
#1000
19
18
0#
0!
b0 "
b0 7
06
b0 5
b0 4
b0 ;
b0 :
0)
#5000
1(
#10000
0(
#15000
1(
#20000
1)
0(
#25000
1(
#30000
0(
#35000
1(
#40000
1@
0?
b1011001 >
0(
#45000
1(
#50000
b0 C
0*
0B
0(
#55000
08
1(
#60000
b1 C
0(
#65000
09
1(
#70000
b10 C
0(
#75000
b1 :
1(
#80000
b11 C
0(
#85000
b1 ;
1(
#90000
b100 C
0(
#95000
b10 ;
1(
#100000
b101 C
0(
#105000
b11 ;
1(
#110000
b110 C
0(
#115000
b100 ;
1(
#120000
b111 C
0(
#125000
b10 :
b0 ;
1(
#130000
b1000 C
0(
#135000
b1 ;
1(
#140000
b1001 C
0(
#145000
b10 ;
1(
#150000
b0 C
0(
#155000
b11 ;
1(
#160000
b1 C
0(
#165000
b100 ;
1(
#170000
b10 C
0(
#175000
b101 ;
1(
#180000
b11 C
0(
#185000
b110 ;
1(
#190000
b100 C
0(
#195000
b111 ;
1(
#200000
b101 C
0(
#205000
b1000 ;
1(
#210000
b110 C
0(
#215000
b1001 ;
1(
#220000
b111 C
0(
#225000
b11 :
b0 ;
1(
#230000
b1000 C
0(
#235000
b1 ;
1(
#240000
b1001 C
0(
#245000
b10 ;
1(
#250000
1*
1B
b0 A
b0 C
0(
#255000
18
b11 ;
1(
#260000
b1 C
0(
#265000
b100 ;
19
1(
#270000
b10 C
0(
#275000
b101 ;
1(
#280000
b11 C
0(
#285000
b110 ;
1(
#290000
b100 C
0(
#295000
b111 ;
1(
#300000
b101 C
0(
#305000
b1000 ;
1(
#310000
b110 C
0(
#315000
b1001 ;
1(
#320000
b111 C
0(
#325000
b1 4
b1 5
b0 ;
1(
#330000
b1000 C
0(
#335000
b1 ;
1(
#340000
b1001 C
0(
#345000
b10 ;
1(
#350000
0*
0B
b1 A
b0 C
0(
#355000
08
b11 ;
1(
#360000
b1 C
0(
#365000
b100 ;
09
1(
#370000
b10 C
0(
#375000
b101 ;
1(
#380000
b11 C
0(
#385000
b110 ;
1(
#390000
b100 C
0(
#395000
b111 ;
1(
#400000
b101 C
0(
#405000
b1000 ;
1(
#410000
b110 C
0(
#415000
b1001 ;
1(
#420000
b111 C
0(
#425000
b10 4
b0 ;
1(
#430000
b1000 C
0(
#435000
b1 ;
1(
#440000
b1001 C
0(
#445000
b10 ;
1(
#450000
b10 A
b0 C
0(
#455000
b11 ;
1(
#460000
b1 C
0(
#465000
b100 ;
1(
#470000
b10 C
0(
#475000
b101 ;
1(
#480000
b11 C
0(
#485000
b110 ;
1(
#490000
b100 C
0(
#495000
b111 ;
1(
#500000
b101 C
0(
#505000
b1000 ;
1(
#510000
b110 C
0(
#515000
b1001 ;
1(
#520000
b111 C
0(
#525000
b11 4
b0 ;
1(
#530000
b1000 C
0(
#535000
b1 ;
1(
#540000
b1001 C
0(
#545000
b10 ;
1(
#550000
1*
1B
b11 A
b0 C
0(
#555000
18
b11 ;
1(
#560000
b1 C
0(
#565000
b100 ;
19
1(
#570000
b10 C
0(
#575000
b101 ;
1(
#580000
b11 C
0(
#585000
b110 ;
1(
#590000
b100 C
0(
#595000
b111 ;
1(
#600000
b101 C
0(
#605000
b1000 ;
1(
#610000
b110 C
0(
#615000
b1001 ;
1(
#620000
b111 C
0(
#625000
b100 4
b1001 5
b0 ;
1(
#630000
b1000 C
0(
#635000
b1 ;
1(
#640000
b1001 C
0(
#645000
b10 ;
1(
#650000
b100 A
b0 C
0(
#655000
b11 ;
1(
#660000
b1 C
0(
#665000
b100 ;
1(
#670000
b10 C
0(
#675000
b101 ;
1(
#680000
b11 C
0(
#685000
b110 ;
1(
#690000
b100 C
0(
#695000
b111 ;
1(
#700000
b101 C
0(
#705000
b1000 ;
1(
#710000
b110 C
0(
#715000
b1001 ;
1(
#720000
b111 C
0(
#725000
b101 4
b11001 5
b0 ;
1(
#730000
b1000 C
0(
#735000
b1 ;
1(
#740000
b1001 C
0(
#745000
b10 ;
1(
#750000
0*
0B
b101 A
b0 C
0(
#755000
08
b11 ;
1(
#760000
b1 C
0(
#765000
b100 ;
09
1(
#770000
b10 C
0(
#775000
b101 ;
1(
#780000
b11 C
0(
#785000
b110 ;
1(
#790000
b100 C
0(
#795000
b111 ;
1(
#800000
b101 C
0(
#805000
b1000 ;
1(
#810000
b110 C
0(
#815000
b1001 ;
1(
#820000
b111 C
0(
#825000
b110 4
b0 ;
1(
#830000
b1000 C
0(
#835000
b1 ;
1(
#840000
b1001 C
0(
#845000
b10 ;
1(
#850000
1*
1B
b110 A
b0 C
0(
#855000
18
b11 ;
1(
#860000
b1 C
0(
#865000
b100 ;
19
1(
#870000
b10 C
0(
#875000
b101 ;
1(
#880000
b11 C
0(
#885000
b110 ;
1(
#890000
b100 C
0(
#895000
b111 ;
1(
#900000
b101 C
0(
#905000
b1000 ;
1(
#910000
b110 C
0(
#915000
b1001 ;
1(
#920000
b111 C
0(
#925000
b100 :
b1011001 5
b0 ;
1(
#930000
b1000 C
0(
#935000
b1 ;
1(
#940000
b1001 C
0(
#945000
b10 ;
1(
#950000
b0 D
b111 A
b1010 C
0(
#955000
b11 ;
1(
#960000
b1 D
0(
#965000
b100 ;
1(
#970000
b10 D
0(
#975000
b101 ;
1(
#980000
b11 D
0(
#985000
b110 ;
1(
#990000
b100 D
0(
#995000
b111 ;
1(
#1000000
b101 D
0(
#1005000
b1000 ;
1(
#1010000
b110 D
0(
#1015000
b1001 ;
1(
#1020000
b111 D
0(
#1025000
b0 :
1#
b1011001 "
b1011001 7
1!
b0 ;
1(
#1030000
b1000 D
0(
#1035000
b0 4
0#
0!
1(
#1040000
1?
b101101 >
0(
#1045000
1(
#1050000
b0 C
0*
0B
0(
#1055000
08
1(
#1060000
b1 C
0(
#1065000
09
1(
#1070000
b10 C
0(
#1075000
b1 :
1(
#1080000
b11 C
0(
#1085000
b1 ;
1(
#1090000
b100 C
0(
#1095000
b10 ;
1(
#1100000
b101 C
0(
#1105000
b11 ;
1(
#1110000
b110 C
0(
#1115000
b100 ;
1(
#1120000
b111 C
0(
#1125000
b10 :
b0 ;
1(
#1130000
b1000 C
0(
#1135000
b1 ;
1(
#1140000
b1001 C
0(
#1145000
b10 ;
1(
#1150000
1*
1B
b0 C
0(
#1155000
18
b11 ;
1(
#1160000
b1 C
0(
#1165000
b100 ;
19
1(
#1170000
b10 C
0(
#1175000
b101 ;
1(
#1180000
b11 C
0(
#1185000
b110 ;
1(
#1190000
b100 C
0(
#1195000
b111 ;
1(
#1200000
b101 C
0(
#1205000
b1000 ;
1(
#1210000
b110 C
0(
#1215000
b1001 ;
1(
#1220000
b111 C
0(
#1225000
b11 :
16
b0 ;
1(
#1230000
b1000 C
0(
#1235000
b1 ;
1(
#1240000
b1001 C
0(
#1245000
b10 ;
1(
#1250000
b0 A
b0 C
0(
#1255000
b11 ;
1(
#1260000
b1 C
0(
#1265000
b100 ;
1(
#1270000
b10 C
0(
#1275000
b101 ;
1(
#1280000
b11 C
0(
#1285000
b110 ;
1(
#1290000
b100 C
0(
#1295000
b111 ;
1(
#1300000
b101 C
0(
#1305000
b1000 ;
1(
#1310000
b110 C
0(
#1315000
b1001 ;
1(
#1320000
b111 C
0(
#1325000
b1 4
b0 ;
1(
#1330000
b1000 C
0(
#1335000
b1 ;
1(
#1340000
b1001 C
0(
#1345000
b10 ;
1(
#1350000
0*
0B
b1 A
b0 C
0(
#1355000
08
b11 ;
1(
#1360000
b1 C
0(
#1365000
b100 ;
09
1(
#1370000
b10 C
0(
#1375000
b101 ;
1(
#1380000
b11 C
0(
#1385000
b110 ;
1(
#1390000
b100 C
0(
#1395000
b111 ;
1(
#1400000
b101 C
0(
#1405000
b1000 ;
1(
#1410000
b110 C
0(
#1415000
b1001 ;
1(
#1420000
b111 C
0(
#1425000
b10 4
b0 ;
1(
#1430000
b1000 C
0(
#1435000
b1 ;
1(
#1440000
b1001 C
0(
#1445000
b10 ;
1(
#1450000
1*
1B
b10 A
b0 C
0(
#1455000
18
b11 ;
1(
#1460000
b1 C
0(
#1465000
b100 ;
19
1(
#1470000
b10 C
0(
#1475000
b101 ;
1(
#1480000
b11 C
0(
#1485000
b110 ;
1(
#1490000
b100 C
0(
#1495000
b111 ;
1(
#1500000
b101 C
0(
#1505000
b1000 ;
1(
#1510000
b110 C
0(
#1515000
b1001 ;
1(
#1520000
b111 C
0(
#1525000
b11 4
b1011101 5
b0 ;
1(
#1530000
b1000 C
0(
#1535000
b1 ;
1(
#1540000
b1001 C
0(
#1545000
b10 ;
1(
#1550000
b11 A
b0 C
0(
#1555000
b11 ;
1(
#1560000
b1 C
0(
#1565000
b100 ;
1(
#1570000
b10 C
0(
#1575000
b101 ;
1(
#1580000
b11 C
0(
#1585000
b110 ;
1(
#1590000
b100 C
0(
#1595000
b111 ;
1(
#1600000
b101 C
0(
#1605000
b1000 ;
1(
#1610000
b110 C
0(
#1615000
b1001 ;
1(
#1620000
b111 C
0(
#1625000
b100 4
b0 ;
1(
#1630000
b1000 C
0(
#1635000
b1 ;
1(
#1640000
b1001 C
0(
#1645000
b10 ;
1(
#1650000
0*
0B
b100 A
b0 C
0(
#1655000
08
b11 ;
1(
#1660000
b1 C
0(
#1665000
b100 ;
09
1(
#1670000
b10 C
0(
#1675000
b101 ;
1(
#1680000
b11 C
0(
#1685000
b110 ;
1(
#1690000
b100 C
0(
#1695000
b111 ;
1(
#1700000
b101 C
0(
#1705000
b1000 ;
1(
#1710000
b110 C
0(
#1715000
b1001 ;
1(
#1720000
b111 C
0(
#1725000
b101 4
b1001101 5
b0 ;
1(
#1730000
b1000 C
0(
#1735000
b1 ;
1(
#1740000
b1001 C
0(
#1745000
b10 ;
1(
#1750000
1*
1B
b101 A
b0 C
0(
#1755000
18
b11 ;
1(
#1760000
b1 C
0(
#1765000
b100 ;
19
1(
#1770000
b10 C
0(
#1775000
b101 ;
1(
#1780000
b11 C
0(
#1785000
b110 ;
1(
#1790000
b100 C
0(
#1795000
b111 ;
1(
#1800000
b101 C
0(
#1805000
b1000 ;
1(
#1810000
b110 C
0(
#1815000
b1001 ;
1(
#1820000
b111 C
0(
#1825000
b110 4
b1101101 5
b0 ;
1(
#1830000
b1000 C
0(
#1835000
b1 ;
1(
#1840000
b1001 C
0(
#1845000
b10 ;
1(
#1850000
0*
0B
b110 A
b0 C
0(
#1855000
08
b11 ;
1(
#1860000
b1 C
0(
#1865000
b100 ;
09
1(
#1870000
b10 C
0(
#1875000
b101 ;
1(
#1880000
b11 C
0(
#1885000
b110 ;
1(
#1890000
b100 C
0(
#1895000
b111 ;
1(
#1900000
b101 C
0(
#1905000
b1000 ;
1(
#1910000
b110 C
0(
#1915000
b1001 ;
1(
#1920000
b111 C
0(
#1925000
b100 :
b101101 5
b0 ;
1(
#1930000
b1000 C
0(
#1935000
b1 ;
1(
#1940000
b1001 C
0(
#1945000
b10 ;
1(
#1950000
b0 D
1*
b111 A
b1010 C
0(
#1955000
18
b11 ;
1(
#1960000
b1 D
0(
#1965000
b100 ;
19
1(
#1970000
b10 D
0(
#1975000
b101 ;
1(
#1980000
b11 D
0(
#1985000
b110 ;
1(
#1990000
b100 D
0(
#1995000
b111 ;
1(
#2000000
b101 D
0(
#2005000
b1000 ;
1(
#2010000
b110 D
0(
#2015000
b1001 ;
1(
#2020000
b111 D
0(
#2025000
b0 :
1!
b0 ;
1(
#2030000
b1000 D
0(
#2035000
b0 4
0!
1(
