DSDL7/Final/rtl/UARTReceiver.v
`timescale 1ns/1ps

// Seven-bit UART receiver for the assignment-specific parity-before-data frame.
// rx is synchronized, the start bit is confirmed at midpoint, and each later
// symbol is sampled once per BIT_TICKS clocks at the same phase.
module UARTReceiver #(
    parameter integer BIT_TICKS = 434
) (
    input  wire       clk,
    input  wire       rstN,
    input  wire       rx,
    output reg  [6:0] rec_data,
    output reg        rec_new_data,
    output reg        correct_data
);

    function integer counter_width;
        input integer value;
        integer width;
        begin
            value = value - 1;
            width = 0;
            while (value > 0) begin
                value = value >> 1;
                width = width + 1;
            end
            counter_width = width < 1 ? 1 : width;
        end
    endfunction

    localparam integer TICK_WIDTH = counter_width(BIT_TICKS);
    localparam [TICK_WIDTH-1:0] LAST_TICK = BIT_TICKS - 1;
    localparam [TICK_WIDTH-1:0] HALF_TICK = (BIT_TICKS / 2) - 1;

    localparam [2:0] IDLE   = 3'd0;
    localparam [2:0] START  = 3'd1;
    localparam [2:0] PARITY = 3'd2;
    localparam [2:0] DATA   = 3'd3;
    localparam [2:0] STOP   = 3'd4;

    reg rx_meta;
    reg rx_sync;
    reg [2:0] state;
    reg [TICK_WIDTH-1:0] tick_count;
    reg [2:0] bit_index;
    reg [6:0] data_latch;
    reg parity_latch;

    // Two flip-flops isolate the FSM from an asynchronous serial input.
    always @(posedge clk or negedge rstN) begin
        if (!rstN) begin
            rx_meta <= 1'b1;
            rx_sync <= 1'b1;
        end else begin
            rx_meta <= rx;
            rx_sync <= rx_meta;
        end
    end

    always @(posedge clk or negedge rstN) begin
        if (!rstN) begin
            state          <= IDLE;
            tick_count     <= {TICK_WIDTH{1'b0}};
            bit_index      <= 3'd0;
            data_latch     <= 7'd0;
            parity_latch   <= 1'b0;
            rec_data       <= 7'd0;
            rec_new_data   <= 1'b0;
            correct_data   <= 1'b0;
        end else begin
            // Completion and validity are aligned one-clock notifications.
            rec_new_data <= 1'b0;
            correct_data <= 1'b0;

            case (state)
                IDLE: begin
                    tick_count <= {TICK_WIDTH{1'b0}};
                    bit_index <= 3'd0;
                    if (!rx_sync)
                        state <= START;
                end

                START: begin
                    if (tick_count == HALF_TICK) begin
                        tick_count <= {TICK_WIDTH{1'b0}};
                        state <= rx_sync ? IDLE : PARITY;
                    end else begin
                        tick_count <= tick_count + 1'b1;
                    end
                end

                PARITY: begin
                    if (tick_count == LAST_TICK) begin
                        tick_count <= {TICK_WIDTH{1'b0}};
                        bit_index <= 3'd0;
                        parity_latch <= rx_sync;
                        state <= DATA;
                    end else begin
                        tick_count <= tick_count + 1'b1;
                    end
                end

                DATA: begin
                    if (tick_count == LAST_TICK) begin
                        tick_count <= {TICK_WIDTH{1'b0}};
                        data_latch[bit_index] <= rx_sync;
                        if (bit_index == 3'd6) begin
                            state <= STOP;
                        end else begin
                            bit_index <= bit_index + 1'b1;
                        end
                    end else begin
                        tick_count <= tick_count + 1'b1;
                    end
                end

                STOP: begin
                    if (tick_count == LAST_TICK) begin
                        tick_count <= {TICK_WIDTH{1'b0}};
                        rec_new_data <= 1'b1;
                        if (rx_sync && ((^data_latch) == parity_latch)) begin
                            rec_data <= data_latch;
                            correct_data <= 1'b1;
                        end
                        state <= IDLE;
                    end else begin
                        tick_count <= tick_count + 1'b1;
                    end
                end

                default: begin
                    state <= IDLE;
                    tick_count <= {TICK_WIDTH{1'b0}};
                    bit_index <= 3'd0;
                end
            endcase
        end
    end

endmodule

DSDL7/final/quartus/UARTSender.v
`timescale 1ns/1ps

// Seven-bit UART sender for the assignment-specific parity-before-data frame.
// new_data is accepted only while idle; the active frame uses a latched copy.
module UARTSender #(
    parameter integer BIT_TICKS = 434
) (
    input  wire       clk,
    input  wire       rstN,
    input  wire       new_data,
    input  wire [6:0] send_data,
    output wire       tx,
    output wire       busy
);

    function integer counter_width;
        input integer value;
        integer width;
        begin
            value = value - 1;
            width = 0;
            while (value > 0) begin
                value = value >> 1;
                width = width + 1;
            end
            counter_width = width < 1 ? 1 : width;
        end
    endfunction

    localparam integer TICK_WIDTH = counter_width(BIT_TICKS);
    localparam [TICK_WIDTH-1:0] LAST_TICK = BIT_TICKS - 1;

    localparam [2:0] IDLE   = 3'd0;
    localparam [2:0] START  = 3'd1;
    localparam [2:0] PARITY = 3'd2;
    localparam [2:0] DATA   = 3'd3;
    localparam [2:0] STOP   = 3'd4;

    reg [2:0] state;
    reg [TICK_WIDTH-1:0] tick_count;
    reg [2:0] bit_index;
    reg [6:0] data_latch;
    reg parity_latch;

    assign busy = state != IDLE;
    assign tx = state == START  ? 1'b0 :
                state == PARITY ? parity_latch :
                state == DATA   ? data_latch[bit_index] : 1'b1;

    always @(posedge clk or negedge rstN) begin
        if (!rstN) begin
            state        <= IDLE;
            tick_count   <= {TICK_WIDTH{1'b0}};
            bit_index    <= 3'd0;
            data_latch   <= 7'd0;
            parity_latch <= 1'b0;
        end else begin
            case (state)
                IDLE: begin
                    tick_count <= {TICK_WIDTH{1'b0}};
                    bit_index  <= 3'd0;
                    if (new_data) begin
                        data_latch   <= send_data;
                        parity_latch <= ^send_data;
                        state        <= START;
                    end
                end

                START: begin
                    if (tick_count == LAST_TICK) begin
                        tick_count <= {TICK_WIDTH{1'b0}};
                        state <= PARITY;
                    end else begin
                        tick_count <= tick_count + 1'b1;
                    end
                end

                PARITY: begin
                    if (tick_count == LAST_TICK) begin
                        tick_count <= {TICK_WIDTH{1'b0}};
                        bit_index <= 3'd0;
                        state <= DATA;
                    end else begin
                        tick_count <= tick_count + 1'b1;
                    end
                end

                DATA: begin
                    if (tick_count == LAST_TICK) begin
                        tick_count <= {TICK_WIDTH{1'b0}};
                        if (bit_index == 3'd6) begin
                            state <= STOP;
                        end else begin
                            bit_index <= bit_index + 1'b1;
                        end
                    end else begin
                        tick_count <= tick_count + 1'b1;
                    end
                end

                STOP: begin
                    if (tick_count == LAST_TICK) begin
                        tick_count <= {TICK_WIDTH{1'b0}};
                        state <= IDLE;
                    end else begin
                        tick_count <= tick_count + 1'b1;
                    end
                end

                default: begin
                    state <= IDLE;
                    tick_count <= {TICK_WIDTH{1'b0}};
                    bit_index <= 3'd0;
                end
            endcase
        end
    end

endmodule

DSDL7/final/rtl/UARTTop.v
`timescale 1ns/1ps

// Direct internal loopback: the sender's serial output is the receiver input.
module UARTTop #(
    parameter integer BIT_TICKS = 434
) (
    input  wire       clk,
    input  wire       rstN,
    input  wire       new_data,
    input  wire [6:0] send_data,
    output wire       tx,
    output wire       busy,
    output wire [6:0] rec_data,
    output wire       rec_new_data,
    output wire       correct_data
);

    UARTSender #(.BIT_TICKS(BIT_TICKS)) sender (
        .clk(clk),
        .rstN(rstN),
        .new_data(new_data),
        .send_data(send_data),
        .tx(tx),
        .busy(busy)
    );

    UARTReceiver #(.BIT_TICKS(BIT_TICKS)) receiver (
        .clk(clk),
        .rstN(rstN),
        .rx(tx),
        .rec_data(rec_data),
        .rec_new_data(rec_new_data),
        .correct_data(correct_data)
    );

endmodule

DSDL7/final/rtl/tb_uart_all_values.v
`timescale 1ns/1ps

module tb_uart_all_values;

    localparam integer BIT_TICKS = 2;
    localparam integer TIMEOUT_CYCLES = 30 * BIT_TICKS;

    reg clk;
    reg rstN;
    reg new_data;
    reg [6:0] send_data;
    wire tx;
    wire busy;
    wire [6:0] rec_data;
    wire rec_new_data;
    wire correct_data;
    integer value;
    integer cycles;

    UARTTop #(.BIT_TICKS(BIT_TICKS)) dut (
        .clk(clk),
        .rstN(rstN),
        .new_data(new_data),
        .send_data(send_data),
        .tx(tx),
        .busy(busy),
        .rec_data(rec_data),
        .rec_new_data(rec_new_data),
        .correct_data(correct_data)
    );

    initial clk = 1'b0;
    always #5 clk = ~clk;

    initial begin
        $dumpfile("/tmp/tb_uart_all_values.vcd");
        $dumpvars(0, tb_uart_all_values);
        rstN = 1'b1;
        new_data = 1'b0;
        send_data = 7'd0;
        #1 rstN = 1'b0;
        repeat (2) @(negedge clk);
        rstN = 1'b1;

        for (value = 0; value < 128; value = value + 1) begin
            @(negedge clk);
            send_data = value[6:0];
            new_data = 1'b1;
            @(negedge clk);
            new_data = 1'b0;

            cycles = 0;
            while (rec_new_data !== 1'b1 && cycles < TIMEOUT_CYCLES) begin
                @(negedge clk);
                cycles = cycles + 1;
            end
            if (rec_new_data !== 1'b1)
                $fatal(1, "FAIL: value %0d timed out", value);
            if (correct_data !== 1'b1 || rec_data !== value[6:0])
                $fatal(1, "FAIL: sent=%0d received=%0d correct=%b",
                       value, rec_data, correct_data);

            @(negedge clk);
            if (rec_new_data !== 1'b0 || correct_data !== 1'b0)
                $fatal(1, "FAIL: output pulse width for value %0d", value);
        end

        $display("PASS: all 128 UART values");
        $finish;
    end

endmodule

DSDL7/final/sim/tb_uart_all_values.vcd
$date
	Mon Aug 24 09:43:54 2026
$end
$version
	Icarus Verilog
$end
$timescale
	1ps
$end
$scope module tb_uart_all_values $end
$var wire 1 ! tx $end
$var wire 1 " rec_new_data $end
$var wire 7 # rec_data [6:0] $end
$var wire 1 $ correct_data $end
$var wire 1 % busy $end
$var parameter 32 & BIT_TICKS $end
$var parameter 32 ' TIMEOUT_CYCLES $end
$var reg 1 ( clk $end
$var reg 1 ) new_data $end
$var reg 1 * rstN $end
$var reg 7 + send_data [6:0] $end
$var integer 32 , cycles [31:0] $end
$var integer 32 - value [31:0] $end
$scope module dut $end
$var wire 1 ( clk $end
$var wire 1 ) new_data $end
$var wire 1 * rstN $end
$var wire 7 . send_data [6:0] $end
$var wire 1 ! tx $end
$var wire 1 " rec_new_data $end
$var wire 7 / rec_data [6:0] $end
$var wire 1 $ correct_data $end
$var wire 1 % busy $end
$var parameter 32 0 BIT_TICKS $end
$scope module receiver $end
$var wire 1 ( clk $end
$var wire 1 * rstN $end
$var wire 1 ! rx $end
$var parameter 32 1 BIT_TICKS $end
$var parameter 3 2 DATA $end
$var parameter 1 3 HALF_TICK $end
$var parameter 3 4 IDLE $end
$var parameter 1 5 LAST_TICK $end
$var parameter 3 6 PARITY $end
$var parameter 3 7 START $end
$var parameter 3 8 STOP $end
$var parameter 32 9 TICK_WIDTH $end
$var reg 3 : bit_index [2:0] $end
$var reg 1 $ correct_data $end
$var reg 7 ; data_latch [6:0] $end
$var reg 1 < parity_latch $end
$var reg 7 = rec_data [6:0] $end
$var reg 1 " rec_new_data $end
$var reg 1 > rx_meta $end
$var reg 1 ? rx_sync $end
$var reg 3 @ state [2:0] $end
$var reg 1 A tick_count $end
$scope function counter_width $end
$var integer 32 B value [31:0] $end
$var integer 32 C width [31:0] $end
$upscope $end
$upscope $end
$scope module sender $end
$var wire 1 ( clk $end
$var wire 1 ) new_data $end
$var wire 1 * rstN $end
$var wire 7 D send_data [6:0] $end
$var wire 1 ! tx $end
$var wire 1 % busy $end
$var parameter 32 E BIT_TICKS $end
$var parameter 3 F DATA $end
$var parameter 3 G IDLE $end
$var parameter 1 H LAST_TICK $end
$var parameter 3 I PARITY $end
$var parameter 3 J START $end
$var parameter 3 K STOP $end
$var parameter 32 L TICK_WIDTH $end
$var reg 3 M bit_index [2:0] $end
$var reg 7 N data_latch [6:0] $end
$var reg 1 O parity_latch $end
$var reg 3 P state [2:0] $end
$var reg 1 Q tick_count $end
$scope function counter_width $end
$var integer 32 R value [31:0] $end
$var integer 32 S width [31:0] $end
$upscope $end
$upscope $end
$upscope $end
$upscope $end
$enddefinitions $end
$comment Show the parameter values. $end
$dumpall
b1 L
b100 K
b1 J
b10 I
1H
b0 G
b11 F
b10 E
b1 9
b100 8
b1 7
b10 6
15
b0 4
03
b11 2
b10 1
b10 0
b111100 '
b10 &
$end
#0
$dumpvars
bx S
bx R
xQ
bx P
xO
bx N
bx M
b0 D
bx C
bx B
xA
bx @
x?
x>
bx =
x<
bx ;
bx :
bx /
b0 .
bx -
bx ,
b0 +
1*
0)
0(
x%
x$
bx #
x"
x!
$end
#1000
1!
0O
b0 N
b0 M
0Q
0%
b0 P
1?
1>
0$
0"
b0 #
b0 /
b0 =
0<
b0 ;
b0 :
0A
b0 @
0*
#5000
1(
#10000
0(
#15000
1(
#20000
b0 -
1*
0(
#25000
1(
#30000
1)
0(
#35000
0!
1%
b1 P
1(
#40000
b0 ,
0)
0(
#45000
0>
1Q
1(
#50000
b1 ,
0(
#55000
b10 P
0Q
0?
1(
#60000
b10 ,
0(
#65000
b1 @
1Q
1(
#70000
b11 ,
0(
#75000
b11 P
0Q
b10 @
1(
#80000
b100 ,
0(
#85000
1A
1Q
1(
#90000
b101 ,
0(
#95000
b1 M
0Q
b11 @
0A
1(
#100000
b110 ,
0(
#105000
1A
1Q
1(
#110000
b111 ,
0(
#115000
b10 M
0Q
b1 :
0A
1(
#120000
b1000 ,
0(
#125000
1A
1Q
1(
#130000
b1001 ,
0(
#135000
b11 M
0Q
b10 :
0A
1(
#140000
b1010 ,
0(
#145000
1A
1Q
1(
#150000
b1011 ,
0(
#155000
b100 M
0Q
b11 :
0A
1(
#160000
b1100 ,
0(
#165000
1A
1Q
1(
#170000
b1101 ,
0(
#175000
b101 M
0Q
b100 :
0A
1(
#180000
b1110 ,
0(
#185000
1A
1Q
1(
#190000
b1111 ,
0(
#195000
b110 M
0Q
b101 :
0A
1(
#200000
b10000 ,
0(
#205000
1A
1Q
1(
#210000
b10001 ,
0(
#215000
1!
b100 P
0Q
b110 :
0A
1(
#220000
b10010 ,
0(
#225000
1A
1>
1Q
1(
#230000
b10011 ,
0(
#235000
0%
b0 P
0Q
1?
b100 @
0A
1(
#240000
b10100 ,
0(
#245000
1A
b0 M
1(
#250000
b10101 ,
0(
#255000
b0 @
1$
1"
0A
1(
#260000
b10110 ,
0(
#265000
b0 :
0$
0"
1(
#270000
b1 -
0(
#275000
1(
#280000
1)
b1 +
b1 .
b1 D
0(
#285000
0!
1%
b1 P
1O
b1 N
1(
#290000
b0 ,
0)
0(
#295000
1Q
0>
1(
#300000
b1 ,
0(
#305000
1!
0?
b10 P
0Q
1(
#310000
b10 ,
0(
#315000
1Q
1>
b1 @
1(
#320000
b11 ,
0(
#325000
b10 @
1?
b11 P
0Q
1(
#330000
b100 ,
0(
#335000
1Q
1A
1(
#340000
b101 ,
0(
#345000
0!
b11 @
1<
0A
b1 M
0Q
1(
#350000
b110 ,
0(
#355000
1Q
0>
1A
1(
#360000
b111 ,
0(
#365000
b1 :
b1 ;
0A
0?
b10 M
0Q
1(
#370000
b1000 ,
0(
#375000
1Q
1A
1(
#380000
b1001 ,
0(
#385000
b10 :
0A
b11 M
0Q
1(
#390000
b1010 ,
0(
#395000
1Q
1A
1(
#400000
b1011 ,
0(
#405000
b11 :
0A
b100 M
0Q
1(
#410000
b1100 ,
0(
#415000
1Q
1A
1(
#420000
b1101 ,
0(
#425000
b100 :
0A
b101 M
0Q
1(
#430000
b1110 ,
0(
#435000
1Q
1A
1(
#440000
b1111 ,
0(
#445000
b101 :
0A
b110 M
0Q
1(
#450000
b10000 ,
0(
#455000
1Q
1A
1(
#460000
b10001 ,
0(
#465000
1!
b110 :
0A
b100 P
0Q
1(
#470000
b10010 ,
0(
#475000
1Q
1>
1A
1(
#480000
b10011 ,
0(
#485000
b100 @
0A
1?
0%
b0 P
0Q
1(
#490000
b10100 ,
0(
#495000
b0 M
1A
1(
#500000
b10101 ,
0(
#505000
b0 @
1$
b1 #
b1 /
b1 =
1"
0A
1(
#510000
b10110 ,
0(
#515000
b0 :
0$
0"
1(
#520000
b10 -
0(
#525000
1(
#530000
1)
b10 +
b10 .
b10 D
0(
#535000
0!
1%
b1 P
b10 N
1(
#540000
b0 ,
0)
0(
#545000
0>
1Q
1(
#550000
b1 ,
0(
#555000
1!
b10 P
0Q
0?
1(
#560000
b10 ,
0(
#565000
b1 @
1>
1Q
1(
#570000
b11 ,
0(
#575000
0!
b11 P
0Q
1?
b10 @
1(
#580000
b100 ,
0(
#585000
1A
0>
1Q
1(
#590000
b101 ,
0(
#595000
1!
b1 M
0Q
0?
b11 @
0A
1(
#600000
b110 ,
0(
#605000
1A
1>
1Q
1(
#610000
b111 ,
0(
#615000
0!
b10 M
0Q
1?
b1 :
b0 ;
0A
1(
#620000
b1000 ,
0(
#625000
1A
0>
1Q
1(
#630000
b1001 ,
0(
#635000
b11 M
0Q
0?
b10 :
b10 ;
0A
1(
#640000
b1010 ,
0(
#645000
1A
1Q
1(
#650000
b1011 ,
0(
#655000
b100 M
0Q
b11 :
0A
1(
#660000
b1100 ,
0(
#665000
1A
1Q
1(
#670000
b1101 ,
0(
#675000
b101 M
0Q
b100 :
0A
1(
#680000
b1110 ,
0(
#685000
1A
1Q
1(
#690000
b1111 ,
0(
#695000
b110 M
0Q
b101 :
0A
1(
#700000
b10000 ,
0(
#705000
1A
1Q
1(
#710000
b10001 ,
0(
#715000
1!
b100 P
0Q
b110 :
0A
1(
#720000
b10010 ,
0(
#725000
1A
1>
1Q
1(
#730000
b10011 ,
0(
#735000
0%
b0 P
0Q
1?
b100 @
0A
1(
#740000
b10100 ,
0(
#745000
1A
b0 M
1(
#750000
b10101 ,
0(
#755000
b0 @
1$
b10 #
b10 /
b10 =
1"
0A
1(
#760000
b10110 ,
0(
#765000
b0 :
0$
0"
1(
#770000
b11 -
0(
#775000
1(
#780000
1)
b11 +
b11 .
b11 D
0(
#785000
0!
1%
b1 P
0O
b11 N
1(
#790000
b0 ,
0)
0(
#795000
1Q
0>
1(
#800000
b1 ,
0(
#805000
0?
b10 P
0Q
1(
#810000
b10 ,
0(
#815000
1Q
b1 @
1(
#820000
b11 ,
0(
#825000
1!
b10 @
b11 P
0Q
1(
#830000
b100 ,
0(
#835000
1Q
1>
1A
1(
#840000
b101 ,
0(
#845000
b11 @
0<
0A
1?
b1 M
0Q
1(
#850000
b110 ,
0(
#855000
1Q
1A
1(
#860000
b111 ,
0(
#865000
0!
b1 :
b11 ;
0A
b10 M
0Q
1(
#870000
b1000 ,
0(
#875000
1Q
0>
1A
1(
#880000
b1001 ,
0(
#885000
b10 :
0A
0?
b11 M
0Q
1(
#890000
b1010 ,
0(
#895000
1Q
1A
1(
#900000
b1011 ,
0(
#905000
b11 :
0A
b100 M
0Q
1(
#910000
b1100 ,
0(
#915000
1Q
1A
1(
#920000
b1101 ,
0(
#925000
b100 :
0A
b101 M
0Q
1(
#930000
b1110 ,
0(
#935000
1Q
1A
1(
#940000
b1111 ,
0(
#945000
b101 :
0A
b110 M
0Q
1(
#950000
b10000 ,
0(
#955000
1Q
1A
1(
#960000
b10001 ,
0(
#965000
1!
b110 :
0A
b100 P
0Q
1(
#970000
b10010 ,
0(
#975000
1Q
1>
1A
1(
#980000
b10011 ,
0(
#985000
b100 @
0A
1?
0%
b0 P
0Q
1(
#990000
b10100 ,
0(
#995000
b0 M
1A
1(
#1000000
b10101 ,
0(
#1005000
b0 @
1$
b11 #
b11 /
b11 =
1"
0A
1(
#1010000
b10110 ,
0(
#1015000
b0 :
0$
0"
1(
#1020000
b100 -
0(
#1025000
1(
#1030000
1)
b100 +
b100 .
b100 D
0(
#1035000
0!
1%
b1 P
1O
b100 N
1(
#1040000
b0 ,
0)
0(
#1045000
0>
1Q
1(
#1050000
b1 ,
0(
#1055000
1!
b10 P
0Q
0?
1(
#1060000
b10 ,
0(
#1065000
b1 @
1>
1Q
1(
#1070000
b11 ,
0(
#1075000
0!
b11 P
0Q
1?
b10 @
1(
#1080000
b100 ,
0(
#1085000
1A
0>
1Q
1(
#1090000
b101 ,
0(
#1095000
b1 M
0Q
0?
b11 @
1<
0A
1(
#1100000
b110 ,
0(
#1105000
1A
1Q
1(
#1110000
b111 ,
0(
#1115000
1!
b10 M
0Q
b1 :
b10 ;
0A
1(
#1120000
b1000 ,
0(
#1125000
1A
1>
1Q
1(
#1130000
b1001 ,
0(
#1135000
0!
b11 M
0Q
1?
b10 :
b0 ;
0A
1(
#1140000
b1010 ,
0(
#1145000
1A
0>
1Q
1(
#1150000
b1011 ,
0(
#1155000
b100 M
0Q
0?
b11 :
b100 ;
0A
1(
#1160000
b1100 ,
0(
#1165000
1A
1Q
1(
#1170000
b1101 ,
0(
#1175000
b101 M
0Q
b100 :
0A
1(
#1180000
b1110 ,
0(
#1185000
1A
1Q
1(
#1190000
b1111 ,
0(
#1195000
b110 M
0Q
b101 :
0A
1(
#1200000
b10000 ,
0(
#1205000
1A
1Q
1(
#1210000
b10001 ,
0(
#1215000
1!
b100 P
0Q
b110 :
0A
1(
#1220000
b10010 ,
0(
#1225000
1A
1>
1Q
1(
#1230000
b10011 ,
0(
#1235000
0%
b0 P
0Q
1?
b100 @
0A
1(
#1240000
b10100 ,
0(
#1245000
1A
b0 M
1(
#1250000
b10101 ,
0(
#1255000
b0 @
1$
b100 #
b100 /
b100 =
1"
0A
1(
#1260000
b10110 ,
0(
#1265000
b0 :
0$
0"
1(
#1270000
b101 -
0(
#1275000
1(
#1280000
1)
b101 +
b101 .
b101 D
0(
#1285000
0!
1%
b1 P
0O
b101 N
1(
#1290000
b0 ,
0)
0(
#1295000
1Q
0>
1(
#1300000
b1 ,
0(
#1305000
0?
b10 P
0Q
1(
#1310000
b10 ,
0(
#1315000
1Q
b1 @
1(
#1320000
b11 ,
0(
#1325000
1!
b10 @
b11 P
0Q
1(
#1330000
b100 ,
0(
#1335000
1Q
1>
1A
1(
#1340000
b101 ,
0(
#1345000
0!
b11 @
0<
0A
1?
b1 M
0Q
1(
#1350000
b110 ,
0(
#1355000
1Q
0>
1A
1(
#1360000
b111 ,
0(
#1365000
1!
b1 :
b101 ;
0A
0?
b10 M
0Q
1(
#1370000
b1000 ,
0(
#1375000
1Q
1>
1A
1(
#1380000
b1001 ,
0(
#1385000
0!
b10 :
0A
1?
b11 M
0Q
1(
#1390000
b1010 ,
0(
#1395000
1Q
0>
1A
1(
#1400000
b1011 ,
0(
#1405000
b11 :
0A
0?
b100 M
0Q
1(
#1410000
b1100 ,
0(
#1415000
1Q
1A
1(
#1420000
b1101 ,
0(
#1425000
b100 :
0A
b101 M
0Q
1(
#1430000
b1110 ,
0(
#1435000
1Q
1A
1(
#1440000
b1111 ,
0(
#1445000
b101 :
0A
b110 M
0Q
1(
#1450000
b10000 ,
0(
#1455000
1Q
1A
1(
#1460000
b10001 ,
0(
#1465000
1!
b110 :
0A
b100 P
0Q
1(
#1470000
b10010 ,
0(
#1475000
1Q
1>
1A
1(
#1480000
b10011 ,
0(
#1485000
b100 @
0A
1?
0%
b0 P
0Q
1(
#1490000
b10100 ,
0(
#1495000
b0 M
1A
1(
#1500000
b10101 ,
0(
#1505000
b0 @
1$
b101 #
b101 /
b101 =
1"
0A
1(
#1510000
b10110 ,
0(
#1515000
b0 :
0$
0"
1(
#1520000
b110 -
0(
#1525000
1(
#1530000
1)
b110 +
b110 .
b110 D
0(
#1535000
0!
1%
b1 P
b110 N
1(
#1540000
b0 ,
0)
0(
#1545000
0>
1Q
1(
#1550000
b1 ,
0(
#1555000
b10 P
0Q
0?
1(
#1560000
b10 ,
0(
#1565000
b1 @
1Q
1(
#1570000
b11 ,
0(
#1575000
b11 P
0Q
b10 @
1(
#1580000
b100 ,
0(
#1585000
1A
1Q
1(
#1590000
b101 ,
0(
#1595000
1!
b1 M
0Q
b11 @
0A
1(
#1600000
b110 ,
0(
#1605000
1A
1>
1Q
1(
#1610000
b111 ,
0(
#1615000
b10 M
0Q
1?
b1 :
b100 ;
0A
1(
#1620000
b1000 ,
0(
#1625000
1A
1Q
1(
#1630000
b1001 ,
0(
#1635000
0!
b11 M
0Q
b10 :
b110 ;
0A
1(
#1640000
b1010 ,
0(
#1645000
1A
0>
1Q
1(
#1650000
b1011 ,
0(
#1655000
b100 M
0Q
0?
b11 :
0A
1(
#1660000
b1100 ,
0(
#1665000
1A
1Q
1(
#1670000
b1101 ,
0(
#1675000
b101 M
0Q
b100 :
0A
1(
#1680000
b1110 ,
0(
#1685000
1A
1Q
1(
#1690000
b1111 ,
0(
#1695000
b110 M
0Q
b101 :
0A
1(
#1700000
b10000 ,
0(
#1705000
1A
1Q
1(
#1710000
b10001 ,
0(
#1715000
1!
b100 P
0Q
b110 :
0A
1(
#1720000
b10010 ,
0(
#1725000
1A
1>
1Q
1(
#1730000
b10011 ,
0(
#1735000
0%
b0 P
0Q
1?
b100 @
0A
1(
#1740000
b10100 ,
0(
#1745000
1A
b0 M
1(
#1750000
b10101 ,
0(
#1755000
b0 @
1$
b110 #
b110 /
b110 =
1"
0A
1(
#1760000
b10110 ,
0(
#1765000
b0 :
0$
0"
1(
#1770000
b111 -
0(
#1775000
1(
#1780000
1)
b111 +
b111 .
b111 D
0(
#1785000
0!
1%
b1 P
1O
b111 N
1(
#1790000
b0 ,
0)
0(
#1795000
1Q
0>
1(
#1800000
b1 ,
0(
#1805000
1!
0?
b10 P
0Q
1(
#1810000
b10 ,
0(
#1815000
1Q
1>
b1 @
1(
#1820000
b11 ,
0(
#1825000
b10 @
1?
b11 P
0Q
1(
#1830000
b100 ,
0(
#1835000
1Q
1A
1(
#1840000
b101 ,
0(
#1845000
b11 @
1<
0A
b1 M
0Q
1(
#1850000
b110 ,
0(
#1855000
1Q
1A
1(
#1860000
b111 ,
0(
#1865000
b1 :
b111 ;
0A
b10 M
0Q
1(
#1870000
b1000 ,
0(
#1875000
1Q
1A
1(
#1880000
b1001 ,
0(
#1885000
0!
b10 :
0A
b11 M
0Q
1(
#1890000
b1010 ,
0(
#1895000
1Q
0>
1A
1(
#1900000
b1011 ,
0(
#1905000
b11 :
0A
0?
b100 M
0Q
1(
#1910000
b1100 ,
0(
#1915000
1Q
1A
1(
#1920000
b1101 ,
0(
#1925000
b100 :
0A
b101 M
0Q
1(
#1930000
b1110 ,
0(
#1935000
1Q
1A
1(
#1940000
b1111 ,
0(
#1945000
b101 :
0A
b110 M
0Q
1(
#1950000
b10000 ,
0(
#1955000
1Q
1A
1(
#1960000
b10001 ,
0(
#1965000
1!
b110 :
0A
b100 P
0Q
1(
#1970000
b10010 ,
0(
#1975000
1Q
1>
1A
1(
#1980000
b10011 ,
0(
#1985000
b100 @
0A
1?
0%
b0 P
0Q
1(
#1990000
b10100 ,
0(
#1995000
b0 M
1A
1(
#2000000
b10101 ,
0(
#2005000
b0 @
1$
b111 #
b111 /
b111 =
1"
0A
1(
#2010000
b10110 ,
0(
#2015000
b0 :
0$
0"
1(
#2020000
b1000 -
0(
#2025000
1(
#2030000
1)
b1000 +
b1000 .
b1000 D
0(
#2035000
0!
1%
b1 P
b1000 N
1(
#2040000
b0 ,
0)
0(
#2045000
0>
1Q
1(
#2050000
b1 ,
0(
#2055000
1!
b10 P
0Q
0?
1(
#2060000
b10 ,
0(
#2065000
b1 @
1>
1Q
1(
#2070000
b11 ,
0(
#2075000
0!
b11 P
0Q
1?
b10 @
1(
#2080000
b100 ,
0(
#2085000
1A
0>
1Q
1(
#2090000
b101 ,
0(
#2095000
b1 M
0Q
0?
b11 @
0A
1(
#2100000
b110 ,
0(
#2105000
1A
1Q
1(
#2110000
b111 ,
0(
#2115000
b10 M
0Q
b1 :
b110 ;
0A
1(
#2120000
b1000 ,
0(
#2125000
1A
1Q
1(
#2130000
b1001 ,
0(
#2135000
1!
b11 M
0Q
b10 :
b100 ;
0A
1(
#2140000
b1010 ,
0(
#2145000
1A
1>
1Q
1(
#2150000
b1011 ,
0(
#2155000
0!
b100 M
0Q
1?
b11 :
b0 ;
0A
1(
#2160000
b1100 ,
0(
#2165000
1A
0>
1Q
1(
#2170000
b1101 ,
0(
#2175000
b101 M
0Q
0?
b100 :
b1000 ;
0A
1(
#2180000
b1110 ,
0(
#2185000
1A
1Q
1(
#2190000
b1111 ,
0(
#2195000
b110 M
0Q
b101 :
0A
1(
#2200000
b10000 ,
0(
#2205000
1A
1Q
1(
#2210000
b10001 ,
0(
#2215000
1!
b100 P
0Q
b110 :
0A
1(
#2220000
b10010 ,
0(
#2225000
1A
1>
1Q
1(
#2230000
b10011 ,
0(
#2235000
0%
b0 P
0Q
1?
b100 @
0A
1(
#2240000
b10100 ,
0(
#2245000
1A
b0 M
1(
#2250000
b10101 ,
0(
#2255000
b0 @
1$
b1000 #
b1000 /
b1000 =
1"
0A
1(
#2260000
b10110 ,
0(
#2265000
b0 :
0$
0"
1(
#2270000
b1001 -
0(
#2275000
1(
#2280000
1)
b1001 +
b1001 .
b1001 D
0(
#2285000
0!
1%
b1 P
0O
b1001 N
1(
#2290000
b0 ,
0)
0(
#2295000
1Q
0>
1(
#2300000
b1 ,
0(
#2305000
0?
b10 P
0Q
1(
#2310000
b10 ,
0(
#2315000
1Q
b1 @
1(
#2320000
b11 ,
0(
#2325000
1!
b10 @
b11 P
0Q
1(
#2330000
b100 ,
0(
#2335000
1Q
1>
1A
1(
#2340000
b101 ,
0(
#2345000
0!
b11 @
0<
0A
1?
b1 M
0Q
1(
#2350000
b110 ,
0(
#2355000
1Q
0>
1A
1(
#2360000
b111 ,
0(
#2365000
b1 :
b1001 ;
0A
0?
b10 M
0Q
1(
#2370000
b1000 ,
0(
#2375000
1Q
1A
1(
#2380000
b1001 ,
0(
#2385000
1!
b10 :
0A
b11 M
0Q
1(
#2390000
b1010 ,
0(
#2395000
1Q
1>
1A
1(
#2400000
b1011 ,
0(
#2405000
0!
b11 :
0A
1?
b100 M
0Q
1(
#2410000
b1100 ,
0(
#2415000
1Q
0>
1A
1(
#2420000
b1101 ,
0(
#2425000
b100 :
0A
0?
b101 M
0Q
1(
#2430000
b1110 ,
0(
#2435000
1Q
1A
1(
#2440000
b1111 ,
0(
#2445000
b101 :
0A
b110 M
0Q
1(
#2450000
b10000 ,
0(
#2455000
1Q
1A
1(
#2460000
b10001 ,
0(
#2465000
1!
b110 :
0A
b100 P
0Q
1(
#2470000
b10010 ,
0(
#2475000
1Q
1>
1A
1(
#2480000
b10011 ,
0(
