DSDL7/Final/rtl/UARTReceiver.v
`timescale 1ns/1ps

// Seven-bit UART receiver for the assignment-specific parity-before-data frame.
// rx is synchronized, the start bit is confirmed at midpoint, and each later
// symbol is sampled once per BIT_TICKS clocks at the same phase.
module UARTReceiver #(
    parameter integer BIT_TICKS = 434
) (
    input  wire       clk,
    input  wire       rstN,
    input  wire       rx,
    output reg  [6:0] rec_data,
    output reg        rec_new_data,
    output reg        correct_data
);

    function integer counter_width;
        input integer value;
        integer width;
        begin
            value = value - 1;
            width = 0;
            while (value > 0) begin
                value = value >> 1;
                width = width + 1;
            end
            counter_width = width < 1 ? 1 : width;
        end
    endfunction

    localparam integer TICK_WIDTH = counter_width(BIT_TICKS);
    localparam [TICK_WIDTH-1:0] LAST_TICK = BIT_TICKS - 1;
    localparam [TICK_WIDTH-1:0] HALF_TICK = (BIT_TICKS / 2) - 1;

    localparam [2:0] IDLE   = 3'd0;
    localparam [2:0] START  = 3'd1;
    localparam [2:0] PARITY = 3'd2;
    localparam [2:0] DATA   = 3'd3;
    localparam [2:0] STOP   = 3'd4;

    reg rx_meta;
    reg rx_sync;
    reg [2:0] state;
    reg [TICK_WIDTH-1:0] tick_count;
    reg [2:0] bit_index;
    reg [6:0] data_latch;
    reg parity_latch;

    // Two flip-flops isolate the FSM from an asynchronous serial input.
    always @(posedge clk or negedge rstN) begin
        if (!rstN) begin
            rx_meta <= 1'b1;
            rx_sync <= 1'b1;
        end else begin
            rx_meta <= rx;
            rx_sync <= rx_meta;
        end
    end

    always @(posedge clk or negedge rstN) begin
        if (!rstN) begin
            state          <= IDLE;
            tick_count     <= {TICK_WIDTH{1'b0}};
            bit_index      <= 3'd0;
            data_latch     <= 7'd0;
            parity_latch   <= 1'b0;
            rec_data       <= 7'd0;
            rec_new_data   <= 1'b0;
            correct_data   <= 1'b0;
        end else begin
            // Completion and validity are aligned one-clock notifications.
            rec_new_data <= 1'b0;
            correct_data <= 1'b0;

            case (state)
                IDLE: begin
                    tick_count <= {TICK_WIDTH{1'b0}};
                    bit_index <= 3'd0;
                    if (!rx_sync)
                        state <= START;
                end

                START: begin
                    if (tick_count == HALF_TICK) begin
                        tick_count <= {TICK_WIDTH{1'b0}};
                        state <= rx_sync ? IDLE : PARITY;
                    end else begin
                        tick_count <= tick_count + 1'b1;
                    end
                end

                PARITY: begin
                    if (tick_count == LAST_TICK) begin
                        tick_count <= {TICK_WIDTH{1'b0}};
                        bit_index <= 3'd0;
                        parity_latch <= rx_sync;
                        state <= DATA;
                    end else begin
                        tick_count <= tick_count + 1'b1;
                    end
                end

                DATA: begin
                    if (tick_count == LAST_TICK) begin
                        tick_count <= {TICK_WIDTH{1'b0}};
                        data_latch[bit_index] <= rx_sync;
                        if (bit_index == 3'd6) begin
                            state <= STOP;
                        end else begin
                            bit_index <= bit_index + 1'b1;
                        end
                    end else begin
                        tick_count <= tick_count + 1'b1;
                    end
                end

                STOP: begin
                    if (tick_count == LAST_TICK) begin
                        tick_count <= {TICK_WIDTH{1'b0}};
                        rec_new_data <= 1'b1;
                        if (rx_sync && ((^data_latch) == parity_latch)) begin
                            rec_data <= data_latch;
                            correct_data <= 1'b1;
                        end
                        state <= IDLE;
                    end else begin
                        tick_count <= tick_count + 1'b1;
                    end
                end

                default: begin
                    state <= IDLE;
                    tick_count <= {TICK_WIDTH{1'b0}};
                    bit_index <= 3'd0;
                end
            endcase
        end
    end

endmodule

DSDL7/final/quartus/UARTSender.v
`timescale 1ns/1ps

// Seven-bit UART sender for the assignment-specific parity-before-data frame.
// new_data is accepted only while idle; the active frame uses a latched copy.
module UARTSender #(
    parameter integer BIT_TICKS = 434
) (
    input  wire       clk,
    input  wire       rstN,
    input  wire       new_data,
    input  wire [6:0] send_data,
    output wire       tx,
    output wire       busy
);

    function integer counter_width;
        input integer value;
        integer width;
        begin
            value = value - 1;
            width = 0;
            while (value > 0) begin
                value = value >> 1;
                width = width + 1;
            end
            counter_width = width < 1 ? 1 : width;
        end
    endfunction

    localparam integer TICK_WIDTH = counter_width(BIT_TICKS);
    localparam [TICK_WIDTH-1:0] LAST_TICK = BIT_TICKS - 1;

    localparam [2:0] IDLE   = 3'd0;
    localparam [2:0] START  = 3'd1;
    localparam [2:0] PARITY = 3'd2;
    localparam [2:0] DATA   = 3'd3;
    localparam [2:0] STOP   = 3'd4;

    reg [2:0] state;
    reg [TICK_WIDTH-1:0] tick_count;
    reg [2:0] bit_index;
    reg [6:0] data_latch;
    reg parity_latch;

    assign busy = state != IDLE;
    assign tx = state == START  ? 1'b0 :
                state == PARITY ? parity_latch :
                state == DATA   ? data_latch[bit_index] : 1'b1;

    always @(posedge clk or negedge rstN) begin
        if (!rstN) begin
            state        <= IDLE;
            tick_count   <= {TICK_WIDTH{1'b0}};
            bit_index    <= 3'd0;
            data_latch   <= 7'd0;
            parity_latch <= 1'b0;
        end else begin
            case (state)
                IDLE: begin
                    tick_count <= {TICK_WIDTH{1'b0}};
                    bit_index  <= 3'd0;
                    if (new_data) begin
                        data_latch   <= send_data;
                        parity_latch <= ^send_data;
                        state        <= START;
                    end
                end

                START: begin
                    if (tick_count == LAST_TICK) begin
                        tick_count <= {TICK_WIDTH{1'b0}};
                        state <= PARITY;
                    end else begin
                        tick_count <= tick_count + 1'b1;
                    end
                end

                PARITY: begin
                    if (tick_count == LAST_TICK) begin
                        tick_count <= {TICK_WIDTH{1'b0}};
                        bit_index <= 3'd0;
                        state <= DATA;
                    end else begin
                        tick_count <= tick_count + 1'b1;
                    end
                end

                DATA: begin
                    if (tick_count == LAST_TICK) begin
                        tick_count <= {TICK_WIDTH{1'b0}};
                        if (bit_index == 3'd6) begin
                            state <= STOP;
                        end else begin
                            bit_index <= bit_index + 1'b1;
                        end
                    end else begin
                        tick_count <= tick_count + 1'b1;
                    end
                end

                STOP: begin
                    if (tick_count == LAST_TICK) begin
                        tick_count <= {TICK_WIDTH{1'b0}};
                        state <= IDLE;
                    end else begin
                        tick_count <= tick_count + 1'b1;
                    end
                end

                default: begin
                    state <= IDLE;
                    tick_count <= {TICK_WIDTH{1'b0}};
                    bit_index <= 3'd0;
                end
            endcase
        end
    end

endmodule

DSDL7/final/rtl/UARTTop.v
`timescale 1ns/1ps

// Direct internal loopback: the sender's serial output is the receiver input.
module UARTTop #(
    parameter integer BIT_TICKS = 434
) (
    input  wire       clk,
    input  wire       rstN,
    input  wire       new_data,
    input  wire [6:0] send_data,
    output wire       tx,
    output wire       busy,
    output wire [6:0] rec_data,
    output wire       rec_new_data,
    output wire       correct_data
);

    UARTSender #(.BIT_TICKS(BIT_TICKS)) sender (
        .clk(clk),
        .rstN(rstN),
        .new_data(new_data),
        .send_data(send_data),
        .tx(tx),
        .busy(busy)
    );

    UARTReceiver #(.BIT_TICKS(BIT_TICKS)) receiver (
        .clk(clk),
        .rstN(rstN),
        .rx(tx),
        .rec_data(rec_data),
        .rec_new_data(rec_new_data),
        .correct_data(correct_data)
    );

endmodule

DSDL7/final/rtl/tb_uart_busy_ignore.v
`timescale 1ns/1ps

module tb_uart_busy_ignore;

    localparam integer BIT_TICKS = 10;
    localparam integer TIMEOUT_CYCLES = 30 * BIT_TICKS;
    localparam [6:0] ACCEPTED_DATA = 7'b1011001;
    localparam [6:0] IGNORED_DATA = 7'b0101101;

    reg clk;
    reg rstN;
    reg new_data;
    reg [6:0] send_data;
    wire tx;
    wire busy;
    wire [6:0] rec_data;
    wire rec_new_data;
    wire correct_data;
    integer completion_count;
    integer cycles;
    reg [6:0] observed_data;
    reg observed_correct;

    UARTTop #(.BIT_TICKS(BIT_TICKS)) dut (
        .clk(clk),
        .rstN(rstN),
        .new_data(new_data),
        .send_data(send_data),
        .tx(tx),
        .busy(busy),
        .rec_data(rec_data),
        .rec_new_data(rec_new_data),
        .correct_data(correct_data)
    );

    initial clk = 1'b0;
    always #5 clk = ~clk;

    always @(negedge clk) begin
        if (rec_new_data) begin
            completion_count = completion_count + 1;
            observed_data = rec_data;
            observed_correct = correct_data;
        end
    end

    initial begin
        $dumpfile("/tmp/tb_uart_busy_ignore.vcd");
        $dumpvars(0, tb_uart_busy_ignore);
        completion_count = 0;
        observed_data = 7'd0;
        observed_correct = 1'b0;
        rstN = 1'b1;
        new_data = 1'b0;
        send_data = 7'd0;
        #1 rstN = 1'b0;
        repeat (2) @(negedge clk);
        rstN = 1'b1;

        @(negedge clk);
        send_data = ACCEPTED_DATA;
        new_data = 1'b1;
        @(negedge clk);
        new_data = 1'b0;
        if (busy !== 1'b1)
            $fatal(1, "FAIL: sender did not become busy");

        repeat (2 * BIT_TICKS) @(negedge clk);
        if (busy !== 1'b1)
            $fatal(1, "FAIL: sender ended before busy-request test");
        send_data = IGNORED_DATA;
        new_data = 1'b1;
        @(negedge clk);
        new_data = 1'b0;

        cycles = 0;
        while (completion_count < 1 && cycles < TIMEOUT_CYCLES) begin
            @(negedge clk);
            cycles = cycles + 1;
        end
        if (completion_count != 1 || !observed_correct ||
            observed_data !== ACCEPTED_DATA)
            $fatal(1, "FAIL: busy request changed result to %b correct=%b",
                   observed_data, observed_correct);

        repeat (12 * BIT_TICKS) @(negedge clk);
        if (completion_count != 1)
            $fatal(1, "FAIL: busy request was queued as another frame");

        $display("PASS: busy requests are ignored");
        $finish;
    end

endmodule

DSDL7/final/sim/tb_uart_busy_ignore.vcd
$date
	Mon Aug 24 09:43:54 2026
$end
$version
	Icarus Verilog
$end
$timescale
	1ps
$end
$scope module tb_uart_busy_ignore $end
$var wire 1 ! tx $end
$var wire 1 " rec_new_data $end
$var wire 7 # rec_data [6:0] $end
$var wire 1 $ correct_data $end
$var wire 1 % busy $end
$var parameter 7 & ACCEPTED_DATA $end
$var parameter 32 ' BIT_TICKS $end
$var parameter 7 ( IGNORED_DATA $end
$var parameter 32 ) TIMEOUT_CYCLES $end
$var reg 1 * clk $end
$var reg 1 + new_data $end
$var reg 1 , observed_correct $end
$var reg 7 - observed_data [6:0] $end
$var reg 1 . rstN $end
$var reg 7 / send_data [6:0] $end
$var integer 32 0 completion_count [31:0] $end
$var integer 32 1 cycles [31:0] $end
$scope module dut $end
$var wire 1 * clk $end
$var wire 1 + new_data $end
$var wire 1 . rstN $end
$var wire 7 2 send_data [6:0] $end
$var wire 1 ! tx $end
$var wire 1 " rec_new_data $end
$var wire 7 3 rec_data [6:0] $end
$var wire 1 $ correct_data $end
$var wire 1 % busy $end
$var parameter 32 4 BIT_TICKS $end
$scope module receiver $end
$var wire 1 * clk $end
$var wire 1 . rstN $end
$var wire 1 ! rx $end
$var parameter 32 5 BIT_TICKS $end
$var parameter 3 6 DATA $end
$var parameter 4 7 HALF_TICK $end
$var parameter 3 8 IDLE $end
$var parameter 4 9 LAST_TICK $end
$var parameter 3 : PARITY $end
$var parameter 3 ; START $end
$var parameter 3 < STOP $end
$var parameter 32 = TICK_WIDTH $end
$var reg 3 > bit_index [2:0] $end
$var reg 1 $ correct_data $end
$var reg 7 ? data_latch [6:0] $end
$var reg 1 @ parity_latch $end
$var reg 7 A rec_data [6:0] $end
$var reg 1 " rec_new_data $end
$var reg 1 B rx_meta $end
$var reg 1 C rx_sync $end
$var reg 3 D state [2:0] $end
$var reg 4 E tick_count [3:0] $end
$scope function counter_width $end
$var integer 32 F value [31:0] $end
$var integer 32 G width [31:0] $end
$upscope $end
$upscope $end
$scope module sender $end
$var wire 1 * clk $end
$var wire 1 + new_data $end
$var wire 1 . rstN $end
$var wire 7 H send_data [6:0] $end
$var wire 1 ! tx $end
$var wire 1 % busy $end
$var parameter 32 I BIT_TICKS $end
$var parameter 3 J DATA $end
$var parameter 3 K IDLE $end
$var parameter 4 L LAST_TICK $end
$var parameter 3 M PARITY $end
$var parameter 3 N START $end
$var parameter 3 O STOP $end
$var parameter 32 P TICK_WIDTH $end
$var reg 3 Q bit_index [2:0] $end
$var reg 7 R data_latch [6:0] $end
$var reg 1 S parity_latch $end
$var reg 3 T state [2:0] $end
$var reg 4 U tick_count [3:0] $end
$scope function counter_width $end
$var integer 32 V value [31:0] $end
$var integer 32 W width [31:0] $end
$upscope $end
$upscope $end
$upscope $end
$upscope $end
$enddefinitions $end
$comment Show the parameter values. $end
$dumpall
b100 P
b100 O
b1 N
b10 M
b1001 L
b0 K
b11 J
b1010 I
b100 =
b100 <
b1 ;
b10 :
b1001 9
b0 8
b100 7
b11 6
b1010 5
b1010 4
b100101100 )
b101101 (
b1010 '
b1011001 &
$end
#0
$dumpvars
bx W
bx V
bx U
bx T
xS
bx R
bx Q
b0 H
bx G
bx F
bx E
bx D
xC
xB
bx A
x@
bx ?
bx >
bx 3
b0 2
bx 1
b0 0
b0 /
1.
b0 -
0,
0+
0*
x%
x$
bx #
x"
x!
$end
#1000
1!
0S
b0 R
b0 Q
b0 U
0%
b0 T
1C
1B
0$
0"
b0 #
b0 3
b0 A
0@
b0 ?
b0 >
b0 E
b0 D
0.
#5000
1*
#10000
0*
#15000
1*
#20000
1.
0*
#25000
1*
#30000
1+
b1011001 /
b1011001 2
b1011001 H
0*
#35000
0!
1%
b1 T
b1011001 R
1*
#40000
0+
0*
#45000
0B
b1 U
1*
#50000
0*
#55000
b10 U
0C
1*
#60000
0*
#65000
b1 D
b11 U
1*
#70000
0*
#75000
b100 U
b1 E
1*
#80000
0*
#85000
b10 E
b101 U
1*
#90000
0*
#95000
b110 U
b11 E
1*
#100000
0*
#105000
b100 E
b111 U
1*
#110000
0*
#115000
b1000 U
b10 D
b0 E
1*
#120000
0*
#125000
b1 E
b1001 U
1*
#130000
0*
#135000
b10 T
b0 U
b10 E
1*
#140000
0*
#145000
b11 E
b1 U
1*
#150000
0*
#155000
b10 U
b100 E
1*
#160000
0*
#165000
b101 E
b11 U
1*
#170000
0*
#175000
b100 U
b110 E
1*
#180000
0*
#185000
b111 E
b101 U
1*
#190000
0*
#195000
b110 U
b1000 E
1*
#200000
0*
#205000
b1001 E
b111 U
1*
#210000
0*
#215000
b1000 U
b11 D
b0 E
1*
#220000
0*
#225000
b1 E
b1001 U
1*
#230000
0*
#235000
1!
b11 T
b0 U
b10 E
1*
#240000
1+
b101101 /
b101101 2
b101101 H
0*
#245000
b11 E
1B
b1 U
1*
#250000
b0 1
0+
0*
#255000
b10 U
1C
b100 E
1*
#260000
b1 1
0*
#265000
b101 E
b11 U
1*
#270000
b10 1
0*
#275000
b100 U
b110 E
1*
#280000
b11 1
0*
#285000
b111 E
b101 U
1*
#290000
b100 1
0*
#295000
b110 U
b1000 E
1*
#300000
b101 1
0*
#305000
b1001 E
b111 U
1*
#310000
b110 1
0*
#315000
b1000 U
b1 >
b1 ?
b0 E
1*
#320000
b111 1
0*
#325000
b1 E
b1001 U
1*
#330000
b1000 1
0*
#335000
0!
b1 Q
b0 U
b10 E
1*
#340000
b1001 1
0*
#345000
b11 E
0B
b1 U
1*
#350000
b1010 1
0*
#355000
b10 U
0C
b100 E
1*
#360000
b1011 1
0*
#365000
b101 E
b11 U
1*
#370000
b1100 1
0*
#375000
b100 U
b110 E
1*
#380000
b1101 1
0*
#385000
b111 E
b101 U
1*
#390000
b1110 1
0*
#395000
b110 U
b1000 E
1*
#400000
b1111 1
0*
#405000
b1001 E
b111 U
1*
#410000
b10000 1
0*
#415000
b1000 U
b10 >
b0 E
1*
#420000
b10001 1
0*
#425000
b1 E
b1001 U
1*
#430000
b10010 1
0*
#435000
b10 Q
b0 U
b10 E
1*
#440000
b10011 1
0*
#445000
b11 E
b1 U
1*
#450000
b10100 1
0*
#455000
b10 U
b100 E
1*
#460000
b10101 1
0*
#465000
b101 E
b11 U
1*
#470000
b10110 1
0*
#475000
b100 U
b110 E
1*
#480000
b10111 1
0*
#485000
b111 E
b101 U
1*
#490000
b11000 1
0*
#495000
b110 U
b1000 E
1*
#500000
b11001 1
0*
#505000
b1001 E
b111 U
1*
#510000
b11010 1
0*
#515000
b1000 U
b11 >
b0 E
1*
#520000
b11011 1
0*
#525000
b1 E
b1001 U
1*
#530000
b11100 1
0*
#535000
1!
b11 Q
b0 U
b10 E
1*
#540000
b11101 1
0*
#545000
b11 E
1B
b1 U
1*
#550000
b11110 1
0*
#555000
b10 U
1C
b100 E
1*
#560000
b11111 1
0*
#565000
b101 E
b11 U
1*
#570000
b100000 1
0*
#575000
b100 U
b110 E
1*
#580000
b100001 1
0*
#585000
b111 E
b101 U
1*
#590000
b100010 1
0*
#595000
b110 U
b1000 E
1*
#600000
b100011 1
0*
#605000
b1001 E
b111 U
1*
#610000
b100100 1
0*
#615000
b1000 U
b100 >
b1001 ?
b0 E
1*
#620000
b100101 1
0*
#625000
b1 E
b1001 U
1*
#630000
b100110 1
0*
#635000
b100 Q
b0 U
b10 E
1*
#640000
b100111 1
0*
#645000
b11 E
b1 U
1*
#650000
b101000 1
0*
#655000
b10 U
b100 E
1*
#660000
b101001 1
0*
#665000
b101 E
b11 U
1*
#670000
b101010 1
0*
#675000
b100 U
b110 E
1*
#680000
b101011 1
0*
#685000
b111 E
b101 U
1*
#690000
b101100 1
0*
#695000
b110 U
b1000 E
1*
#700000
b101101 1
0*
#705000
b1001 E
b111 U
1*
#710000
b101110 1
0*
#715000
b1000 U
b101 >
b11001 ?
b0 E
1*
#720000
b101111 1
0*
#725000
b1 E
b1001 U
1*
#730000
b110000 1
0*
#735000
0!
b101 Q
b0 U
b10 E
1*
#740000
b110001 1
0*
#745000
b11 E
0B
b1 U
1*
#750000
b110010 1
0*
#755000
b10 U
0C
b100 E
1*
#760000
b110011 1
0*
#765000
b101 E
b11 U
1*
#770000
b110100 1
0*
#775000
b100 U
b110 E
1*
#780000
b110101 1
0*
#785000
b111 E
b101 U
1*
#790000
b110110 1
0*
#795000
b110 U
b1000 E
1*
#800000
b110111 1
0*
#805000
b1001 E
b111 U
1*
#810000
b111000 1
0*
#815000
b1000 U
b110 >
b0 E
1*
#820000
b111001 1
0*
#825000
b1 E
b1001 U
1*
#830000
b111010 1
0*
#835000
1!
b110 Q
b0 U
b10 E
1*
#840000
b111011 1
0*
#845000
b11 E
1B
b1 U
1*
#850000
b111100 1
0*
#855000
b10 U
1C
b100 E
1*
#860000
b111101 1
0*
#865000
b101 E
b11 U
1*
#870000
b111110 1
0*
#875000
b100 U
b110 E
1*
#880000
b111111 1
0*
#885000
b111 E
b101 U
1*
#890000
b1000000 1
0*
#895000
b110 U
b1000 E
1*
#900000
b1000001 1
0*
#905000
b1001 E
b111 U
1*
#910000
b1000010 1
0*
#915000
b1000 U
b100 D
b1011001 ?
b0 E
1*
#920000
b1000011 1
0*
#925000
b1 E
b1001 U
1*
#930000
b1000100 1
0*
#935000
b100 T
b0 U
b10 E
1*
#940000
b1000101 1
0*
#945000
b11 E
b1 U
1*
#950000
b1000110 1
0*
#955000
b10 U
b100 E
1*
#960000
b1000111 1
0*
#965000
b101 E
b11 U
1*
#970000
b1001000 1
0*
#975000
b100 U
b110 E
1*
#980000
b1001001 1
0*
#985000
b111 E
b101 U
1*
#990000
b1001010 1
0*
#995000
b110 U
b1000 E
1*
#1000000
b1001011 1
0*
#1005000
b1001 E
b111 U
1*
#1010000
b1001100 1
0*
#1015000
b1000 U
b0 D
1$
b1011001 #
b1011001 3
b1011001 A
1"
b0 E
1*
#1020000
b1001101 1
1,
b1011001 -
b1 0
0*
#1025000
b0 >
0$
0"
b1001 U
1*
#1030000
0*
#1035000
0%
b0 T
b0 U
1*
#1040000
0*
#1045000
b0 Q
1*
