DSDL7/Final/rtl/UARTReceiver.v
`timescale 1ns/1ps

// Seven-bit UART receiver for the assignment-specific parity-before-data frame.
// rx is synchronized, the start bit is confirmed at midpoint, and each later
// symbol is sampled once per BIT_TICKS clocks at the same phase.
module UARTReceiver #(
    parameter integer BIT_TICKS = 434
) (
    input  wire       clk,
    input  wire       rstN,
    input  wire       rx,
    output reg  [6:0] rec_data,
    output reg        rec_new_data,
    output reg        correct_data
);

    function integer counter_width;
        input integer value;
        integer width;
        begin
            value = value - 1;
            width = 0;
            while (value > 0) begin
                value = value >> 1;
                width = width + 1;
            end
            counter_width = width < 1 ? 1 : width;
        end
    endfunction

    localparam integer TICK_WIDTH = counter_width(BIT_TICKS);
    localparam [TICK_WIDTH-1:0] LAST_TICK = BIT_TICKS - 1;
    localparam [TICK_WIDTH-1:0] HALF_TICK = (BIT_TICKS / 2) - 1;

    localparam [2:0] IDLE   = 3'd0;
    localparam [2:0] START  = 3'd1;
    localparam [2:0] PARITY = 3'd2;
    localparam [2:0] DATA   = 3'd3;
    localparam [2:0] STOP   = 3'd4;

    reg rx_meta;
    reg rx_sync;
    reg [2:0] state;
    reg [TICK_WIDTH-1:0] tick_count;
    reg [2:0] bit_index;
    reg [6:0] data_latch;
    reg parity_latch;

    // Two flip-flops isolate the FSM from an asynchronous serial input.
    always @(posedge clk or negedge rstN) begin
        if (!rstN) begin
            rx_meta <= 1'b1;
            rx_sync <= 1'b1;
        end else begin
            rx_meta <= rx;
            rx_sync <= rx_meta;
        end
    end

    always @(posedge clk or negedge rstN) begin
        if (!rstN) begin
            state          <= IDLE;
            tick_count     <= {TICK_WIDTH{1'b0}};
            bit_index      <= 3'd0;
            data_latch     <= 7'd0;
            parity_latch   <= 1'b0;
            rec_data       <= 7'd0;
            rec_new_data   <= 1'b0;
            correct_data   <= 1'b0;
        end else begin
            // Completion and validity are aligned one-clock notifications.
            rec_new_data <= 1'b0;
            correct_data <= 1'b0;

            case (state)
                IDLE: begin
                    tick_count <= {TICK_WIDTH{1'b0}};
                    bit_index <= 3'd0;
                    if (!rx_sync)
                        state <= START;
                end

                START: begin
                    if (tick_count == HALF_TICK) begin
                        tick_count <= {TICK_WIDTH{1'b0}};
                        state <= rx_sync ? IDLE : PARITY;
                    end else begin
                        tick_count <= tick_count + 1'b1;
                    end
                end

                PARITY: begin
                    if (tick_count == LAST_TICK) begin
                        tick_count <= {TICK_WIDTH{1'b0}};
                        bit_index <= 3'd0;
                        parity_latch <= rx_sync;
                        state <= DATA;
                    end else begin
                        tick_count <= tick_count + 1'b1;
                    end
                end

                DATA: begin
                    if (tick_count == LAST_TICK) begin
                        tick_count <= {TICK_WIDTH{1'b0}};
                        data_latch[bit_index] <= rx_sync;
                        if (bit_index == 3'd6) begin
                            state <= STOP;
                        end else begin
                            bit_index <= bit_index + 1'b1;
                        end
                    end else begin
                        tick_count <= tick_count + 1'b1;
                    end
                end

                STOP: begin
                    if (tick_count == LAST_TICK) begin
                        tick_count <= {TICK_WIDTH{1'b0}};
                        rec_new_data <= 1'b1;
                        if (rx_sync && ((^data_latch) == parity_latch)) begin
                            rec_data <= data_latch;
                            correct_data <= 1'b1;
                        end
                        state <= IDLE;
                    end else begin
                        tick_count <= tick_count + 1'b1;
                    end
                end

                default: begin
                    state <= IDLE;
                    tick_count <= {TICK_WIDTH{1'b0}};
                    bit_index <= 3'd0;
                end
            endcase
        end
    end

endmodule

DSDL7/final/rtl/tb_uart_false_start.v
`timescale 1ns/1ps

module tb_uart_false_start;

    localparam integer BIT_TICKS = 10;
    localparam integer TIMEOUT_CYCLES = 20 * BIT_TICKS;
    localparam [6:0] TEST_DATA = 7'b1011001;

    reg clk;
    reg rstN;
    reg rx;
    wire [6:0] rec_data;
    wire rec_new_data;
    wire correct_data;
    integer completion_count;

    UARTReceiver #(.BIT_TICKS(BIT_TICKS)) dut (
        .clk(clk),
        .rstN(rstN),
        .rx(rx),
        .rec_data(rec_data),
        .rec_new_data(rec_new_data),
        .correct_data(correct_data)
    );

    initial clk = 1'b0;
    always #5 clk = ~clk;

    always @(negedge clk) begin
        if (rec_new_data)
            completion_count = completion_count + 1;
    end

    task hold_rx;
        input value;
        integer cycle;
        begin
            rx = value;
            for (cycle = 0; cycle < BIT_TICKS; cycle = cycle + 1)
                @(negedge clk);
        end
    endtask

    task drive_valid_frame;
        input [6:0] data;
        integer bit_index;
        begin
            @(negedge clk);
            hold_rx(1'b0);
            hold_rx(^data);
            for (bit_index = 0; bit_index < 7; bit_index = bit_index + 1)
                hold_rx(data[bit_index]);
            rx = 1'b1;
        end
    endtask

    task wait_completion;
        integer cycles;
        begin
            cycles = 0;
            while (rec_new_data !== 1'b1 && cycles < TIMEOUT_CYCLES) begin
                @(negedge clk);
                cycles = cycles + 1;
            end
            if (rec_new_data !== 1'b1)
                $fatal(1, "FAIL: receiver completion timeout");
        end
    endtask

    initial begin
        $dumpfile("/tmp/tb_uart_false_start.vcd");
        $dumpvars(0, tb_uart_false_start);
        completion_count = 0;
        rstN = 1'b1;
        rx = 1'b1;
        #1 rstN = 1'b0;
        repeat (2) @(negedge clk);
        rstN = 1'b1;
        repeat (2) @(negedge clk);

        @(negedge clk);
        rx = 1'b0;
        @(negedge clk);
        rx = 1'b1;
        repeat (3 * BIT_TICKS) @(negedge clk);
        if (completion_count != 0)
            $fatal(1, "FAIL: false start produced a completed frame");

        drive_valid_frame(TEST_DATA);
        wait_completion;
        if (correct_data !== 1'b1 || rec_data !== TEST_DATA)
            $fatal(1, "FAIL: receiver did not recover after false start");
        @(negedge clk);
        if (completion_count != 1)
            $fatal(1, "FAIL: expected one completion, observed %0d",
                   completion_count);

        $display("PASS: false starts are rejected");
        $finish;
    end

endmodule

DSDL7/final/sim/tb_uart_false_start.vcd
$date
	Mon Aug 24 09:43:54 2026
$end
$version
	Icarus Verilog
$end
$timescale
	1ps
$end
$scope module tb_uart_false_start $end
$var wire 1 ! rec_new_data $end
$var wire 7 " rec_data [6:0] $end
$var wire 1 # correct_data $end
$var parameter 32 $ BIT_TICKS $end
$var parameter 7 % TEST_DATA $end
$var parameter 32 & TIMEOUT_CYCLES $end
$var reg 1 ' clk $end
$var reg 1 ( rstN $end
$var reg 1 ) rx $end
$var integer 32 * completion_count [31:0] $end
$scope module dut $end
$var wire 1 ' clk $end
$var wire 1 ( rstN $end
$var wire 1 ) rx $end
$var parameter 32 + BIT_TICKS $end
$var parameter 3 , DATA $end
$var parameter 4 - HALF_TICK $end
$var parameter 3 . IDLE $end
$var parameter 4 / LAST_TICK $end
$var parameter 3 0 PARITY $end
$var parameter 3 1 START $end
$var parameter 3 2 STOP $end
$var parameter 32 3 TICK_WIDTH $end
$var reg 3 4 bit_index [2:0] $end
$var reg 1 # correct_data $end
$var reg 7 5 data_latch [6:0] $end
$var reg 1 6 parity_latch $end
$var reg 7 7 rec_data [6:0] $end
$var reg 1 ! rec_new_data $end
$var reg 1 8 rx_meta $end
$var reg 1 9 rx_sync $end
$var reg 3 : state [2:0] $end
$var reg 4 ; tick_count [3:0] $end
$scope function counter_width $end
$var integer 32 < value [31:0] $end
$var integer 32 = width [31:0] $end
$upscope $end
$upscope $end
$scope task drive_valid_frame $end
$var reg 7 > data [6:0] $end
$var integer 32 ? bit_index [31:0] $end
$upscope $end
$scope task hold_rx $end
$var reg 1 @ value $end
$var integer 32 A cycle [31:0] $end
$upscope $end
$scope task wait_completion $end
$var integer 32 B cycles [31:0] $end
$upscope $end
$upscope $end
$enddefinitions $end
$comment Show the parameter values. $end
$dumpall
b100 3
b100 2
b1 1
b10 0
b1001 /
b0 .
b100 -
b11 ,
b1010 +
b11001000 &
b1011001 %
b1010 $
$end
#0
$dumpvars
bx B
bx A
x@
bx ?
bx >
bx =
bx <
bx ;
bx :
x9
x8
bx 7
x6
bx 5
bx 4
b0 *
1)
1(
0'
x#
bx "
x!
$end
#1000
19
18
0#
0!
b0 "
b0 7
06
b0 5
b0 4
b0 ;
b0 :
0(
#5000
1'
#10000
0'
#15000
1'
#20000
1(
0'
#25000
1'
#30000
0'
#35000
1'
#40000
0'
#45000
1'
#50000
0)
0'
#55000
08
1'
#60000
1)
0'
#65000
09
18
1'
#70000
0'
#75000
19
b1 :
1'
#80000
0'
#85000
b1 ;
1'
#90000
0'
#95000
b10 ;
1'
#100000
0'
#105000
b11 ;
1'
#110000
0'
#115000
b100 ;
1'
#120000
0'
#125000
b0 :
b0 ;
1'
