DSDL7/Final/rtl/UARTReceiver.v
`timescale 1ns/1ps

// Seven-bit UART receiver for the assignment-specific parity-before-data frame.
// rx is synchronized, the start bit is confirmed at midpoint, and each later
// symbol is sampled once per BIT_TICKS clocks at the same phase.
module UARTReceiver #(
    parameter integer BIT_TICKS = 434
) (
    input  wire       clk,
    input  wire       rstN,
    input  wire       rx,
    output reg  [6:0] rec_data,
    output reg        rec_new_data,
    output reg        correct_data
);

    function integer counter_width;
        input integer value;
        integer width;
        begin
            value = value - 1;
            width = 0;
            while (value > 0) begin
                value = value >> 1;
                width = width + 1;
            end
            counter_width = width < 1 ? 1 : width;
        end
    endfunction

    localparam integer TICK_WIDTH = counter_width(BIT_TICKS);
    localparam [TICK_WIDTH-1:0] LAST_TICK = BIT_TICKS - 1;
    localparam [TICK_WIDTH-1:0] HALF_TICK = (BIT_TICKS / 2) - 1;

    localparam [2:0] IDLE   = 3'd0;
    localparam [2:0] START  = 3'd1;
    localparam [2:0] PARITY = 3'd2;
    localparam [2:0] DATA   = 3'd3;
    localparam [2:0] STOP   = 3'd4;

    reg rx_meta;
    reg rx_sync;
    reg [2:0] state;
    reg [TICK_WIDTH-1:0] tick_count;
    reg [2:0] bit_index;
    reg [6:0] data_latch;
    reg parity_latch;

    // Two flip-flops isolate the FSM from an asynchronous serial input.
    always @(posedge clk or negedge rstN) begin
        if (!rstN) begin
            rx_meta <= 1'b1;
            rx_sync <= 1'b1;
        end else begin
            rx_meta <= rx;
            rx_sync <= rx_meta;
        end
    end

    always @(posedge clk or negedge rstN) begin
        if (!rstN) begin
            state          <= IDLE;
            tick_count     <= {TICK_WIDTH{1'b0}};
            bit_index      <= 3'd0;
            data_latch     <= 7'd0;
            parity_latch   <= 1'b0;
            rec_data       <= 7'd0;
            rec_new_data   <= 1'b0;
            correct_data   <= 1'b0;
        end else begin
            // Completion and validity are aligned one-clock notifications.
            rec_new_data <= 1'b0;
            correct_data <= 1'b0;

            case (state)
                IDLE: begin
                    tick_count <= {TICK_WIDTH{1'b0}};
                    bit_index <= 3'd0;
                    if (!rx_sync)
                        state <= START;
                end

                START: begin
                    if (tick_count == HALF_TICK) begin
                        tick_count <= {TICK_WIDTH{1'b0}};
                        state <= rx_sync ? IDLE : PARITY;
                    end else begin
                        tick_count <= tick_count + 1'b1;
                    end
                end

                PARITY: begin
                    if (tick_count == LAST_TICK) begin
                        tick_count <= {TICK_WIDTH{1'b0}};
                        bit_index <= 3'd0;
                        parity_latch <= rx_sync;
                        state <= DATA;
                    end else begin
                        tick_count <= tick_count + 1'b1;
                    end
                end

                DATA: begin
                    if (tick_count == LAST_TICK) begin
                        tick_count <= {TICK_WIDTH{1'b0}};
                        data_latch[bit_index] <= rx_sync;
                        if (bit_index == 3'd6) begin
                            state <= STOP;
                        end else begin
                            bit_index <= bit_index + 1'b1;
                        end
                    end else begin
                        tick_count <= tick_count + 1'b1;
                    end
                end

                STOP: begin
                    if (tick_count == LAST_TICK) begin
                        tick_count <= {TICK_WIDTH{1'b0}};
                        rec_new_data <= 1'b1;
                        if (rx_sync && ((^data_latch) == parity_latch)) begin
                            rec_data <= data_latch;
                            correct_data <= 1'b1;
                        end
                        state <= IDLE;
                    end else begin
                        tick_count <= tick_count + 1'b1;
                    end
                end

                default: begin
                    state <= IDLE;
                    tick_count <= {TICK_WIDTH{1'b0}};
                    bit_index <= 3'd0;
                end
            endcase
        end
    end

endmodule

DSDL7/final/quartus/UARTSender.v
`timescale 1ns/1ps

// Seven-bit UART sender for the assignment-specific parity-before-data frame.
// new_data is accepted only while idle; the active frame uses a latched copy.
module UARTSender #(
    parameter integer BIT_TICKS = 434
) (
    input  wire       clk,
    input  wire       rstN,
    input  wire       new_data,
    input  wire [6:0] send_data,
    output wire       tx,
    output wire       busy
);

    function integer counter_width;
        input integer value;
        integer width;
        begin
            value = value - 1;
            width = 0;
            while (value > 0) begin
                value = value >> 1;
                width = width + 1;
            end
            counter_width = width < 1 ? 1 : width;
        end
    endfunction

    localparam integer TICK_WIDTH = counter_width(BIT_TICKS);
    localparam [TICK_WIDTH-1:0] LAST_TICK = BIT_TICKS - 1;

    localparam [2:0] IDLE   = 3'd0;
    localparam [2:0] START  = 3'd1;
    localparam [2:0] PARITY = 3'd2;
    localparam [2:0] DATA   = 3'd3;
    localparam [2:0] STOP   = 3'd4;

    reg [2:0] state;
    reg [TICK_WIDTH-1:0] tick_count;
    reg [2:0] bit_index;
    reg [6:0] data_latch;
    reg parity_latch;

    assign busy = state != IDLE;
    assign tx = state == START  ? 1'b0 :
                state == PARITY ? parity_latch :
                state == DATA   ? data_latch[bit_index] : 1'b1;

    always @(posedge clk or negedge rstN) begin
        if (!rstN) begin
            state        <= IDLE;
            tick_count   <= {TICK_WIDTH{1'b0}};
            bit_index    <= 3'd0;
            data_latch   <= 7'd0;
            parity_latch <= 1'b0;
        end else begin
            case (state)
                IDLE: begin
                    tick_count <= {TICK_WIDTH{1'b0}};
                    bit_index  <= 3'd0;
                    if (new_data) begin
                        data_latch   <= send_data;
                        parity_latch <= ^send_data;
                        state        <= START;
                    end
                end

                START: begin
                    if (tick_count == LAST_TICK) begin
                        tick_count <= {TICK_WIDTH{1'b0}};
                        state <= PARITY;
                    end else begin
                        tick_count <= tick_count + 1'b1;
                    end
                end

                PARITY: begin
                    if (tick_count == LAST_TICK) begin
                        tick_count <= {TICK_WIDTH{1'b0}};
                        bit_index <= 3'd0;
                        state <= DATA;
                    end else begin
                        tick_count <= tick_count + 1'b1;
                    end
                end

                DATA: begin
                    if (tick_count == LAST_TICK) begin
                        tick_count <= {TICK_WIDTH{1'b0}};
                        if (bit_index == 3'd6) begin
                            state <= STOP;
                        end else begin
                            bit_index <= bit_index + 1'b1;
                        end
                    end else begin
                        tick_count <= tick_count + 1'b1;
                    end
                end

                STOP: begin
                    if (tick_count == LAST_TICK) begin
                        tick_count <= {TICK_WIDTH{1'b0}};
                        state <= IDLE;
                    end else begin
                        tick_count <= tick_count + 1'b1;
                    end
                end

                default: begin
                    state <= IDLE;
                    tick_count <= {TICK_WIDTH{1'b0}};
                    bit_index <= 3'd0;
                end
            endcase
        end
    end

endmodule

DSDL7/final/rtl/UARTTop.v
`timescale 1ns/1ps

// Direct internal loopback: the sender's serial output is the receiver input.
module UARTTop #(
    parameter integer BIT_TICKS = 434
) (
    input  wire       clk,
    input  wire       rstN,
    input  wire       new_data,
    input  wire [6:0] send_data,
    output wire       tx,
    output wire       busy,
    output wire [6:0] rec_data,
    output wire       rec_new_data,
    output wire       correct_data
);

    UARTSender #(.BIT_TICKS(BIT_TICKS)) sender (
        .clk(clk),
        .rstN(rstN),
        .new_data(new_data),
        .send_data(send_data),
        .tx(tx),
        .busy(busy)
    );

    UARTReceiver #(.BIT_TICKS(BIT_TICKS)) receiver (
        .clk(clk),
        .rstN(rstN),
        .rx(tx),
        .rec_data(rec_data),
        .rec_new_data(rec_new_data),
        .correct_data(correct_data)
    );

endmodule

DSDL7/final/rtl/tb_uart_back_to_back.v
`timescale 1ns/1ps

module tb_uart_back_to_back;

    localparam integer BIT_TICKS = 10;
    localparam integer TIMEOUT_CYCLES = 30 * BIT_TICKS;
    localparam [6:0] FIRST_DATA = 7'b1011001;
    localparam [6:0] SECOND_DATA = 7'b0101101;

    reg clk;
    reg rstN;
    reg new_data;
    reg [6:0] send_data;
    wire tx;
    wire busy;
    wire [6:0] rec_data;
    wire rec_new_data;
    wire correct_data;
    integer completion_count;
    integer cycles;
    reg [6:0] first_received;
    reg [6:0] second_received;
    reg first_correct;
    reg second_correct;

    UARTTop #(.BIT_TICKS(BIT_TICKS)) dut (
        .clk(clk),
        .rstN(rstN),
        .new_data(new_data),
        .send_data(send_data),
        .tx(tx),
        .busy(busy),
        .rec_data(rec_data),
        .rec_new_data(rec_new_data),
        .correct_data(correct_data)
    );

    initial clk = 1'b0;
    always #5 clk = ~clk;

    always @(negedge clk) begin
        if (rec_new_data) begin
            if (completion_count == 0) begin
                first_received = rec_data;
                first_correct = correct_data;
            end else if (completion_count == 1) begin
                second_received = rec_data;
                second_correct = correct_data;
            end
            completion_count = completion_count + 1;
        end
    end

    task pulse_request;
        input [6:0] value;
        begin
            send_data = value;
            new_data = 1'b1;
            @(negedge clk);
            new_data = 1'b0;
        end
    endtask

    initial begin
        $dumpfile("/tmp/tb_uart_back_to_back.vcd");
        $dumpvars(0, tb_uart_back_to_back);
        completion_count = 0;
        first_received = 7'd0;
        second_received = 7'd0;
        first_correct = 1'b0;
        second_correct = 1'b0;
        rstN = 1'b1;
        new_data = 1'b0;
        send_data = 7'd0;
        #1 rstN = 1'b0;
        repeat (2) @(negedge clk);
        rstN = 1'b1;

        @(negedge clk);
        pulse_request(FIRST_DATA);
        if (busy !== 1'b1)
            $fatal(1, "FAIL: sender did not become busy");

        while (busy !== 1'b0)
            @(negedge clk);
        pulse_request(SECOND_DATA);

        cycles = 0;
        while (completion_count < 2 && cycles < 2 * TIMEOUT_CYCLES) begin
            @(negedge clk);
            cycles = cycles + 1;
        end
        if (completion_count != 2)
            $fatal(1, "FAIL: expected two completions, observed %0d",
                   completion_count);
        if (!first_correct || first_received !== FIRST_DATA)
            $fatal(1, "FAIL: first frame received=%b correct=%b",
                   first_received, first_correct);
        if (!second_correct || second_received !== SECOND_DATA)
            $fatal(1, "FAIL: second frame received=%b correct=%b",
                   second_received, second_correct);

        $display("PASS: consecutive UART frames");
        $finish;
    end

endmodule

DSDL7/final/sim/tb_uart_back_to_back.vcd
$date
	Mon Aug 24 09:43:54 2026
$end
$version
	Icarus Verilog
$end
$timescale
	1ps
$end
$scope module tb_uart_back_to_back $end
$var wire 1 ! tx $end
$var wire 1 " rec_new_data $end
$var wire 7 # rec_data [6:0] $end
$var wire 1 $ correct_data $end
$var wire 1 % busy $end
$var parameter 32 & BIT_TICKS $end
$var parameter 7 ' FIRST_DATA $end
$var parameter 7 ( SECOND_DATA $end
$var parameter 32 ) TIMEOUT_CYCLES $end
$var reg 1 * clk $end
$var reg 1 + first_correct $end
$var reg 7 , first_received [6:0] $end
$var reg 1 - new_data $end
$var reg 1 . rstN $end
$var reg 1 / second_correct $end
$var reg 7 0 second_received [6:0] $end
$var reg 7 1 send_data [6:0] $end
$var integer 32 2 completion_count [31:0] $end
$var integer 32 3 cycles [31:0] $end
$scope module dut $end
$var wire 1 * clk $end
$var wire 1 - new_data $end
$var wire 1 . rstN $end
$var wire 7 4 send_data [6:0] $end
$var wire 1 ! tx $end
$var wire 1 " rec_new_data $end
$var wire 7 5 rec_data [6:0] $end
$var wire 1 $ correct_data $end
$var wire 1 % busy $end
$var parameter 32 6 BIT_TICKS $end
$scope module receiver $end
$var wire 1 * clk $end
$var wire 1 . rstN $end
$var wire 1 ! rx $end
$var parameter 32 7 BIT_TICKS $end
$var parameter 3 8 DATA $end
$var parameter 4 9 HALF_TICK $end
$var parameter 3 : IDLE $end
$var parameter 4 ; LAST_TICK $end
$var parameter 3 < PARITY $end
$var parameter 3 = START $end
$var parameter 3 > STOP $end
$var parameter 32 ? TICK_WIDTH $end
$var reg 3 @ bit_index [2:0] $end
$var reg 1 $ correct_data $end
$var reg 7 A data_latch [6:0] $end
$var reg 1 B parity_latch $end
$var reg 7 C rec_data [6:0] $end
$var reg 1 " rec_new_data $end
$var reg 1 D rx_meta $end
$var reg 1 E rx_sync $end
$var reg 3 F state [2:0] $end
$var reg 4 G tick_count [3:0] $end
$scope function counter_width $end
$var integer 32 H value [31:0] $end
$var integer 32 I width [31:0] $end
$upscope $end
$upscope $end
$scope module sender $end
$var wire 1 * clk $end
$var wire 1 - new_data $end
$var wire 1 . rstN $end
$var wire 7 J send_data [6:0] $end
$var wire 1 ! tx $end
$var wire 1 % busy $end
$var parameter 32 K BIT_TICKS $end
$var parameter 3 L DATA $end
$var parameter 3 M IDLE $end
$var parameter 4 N LAST_TICK $end
$var parameter 3 O PARITY $end
$var parameter 3 P START $end
$var parameter 3 Q STOP $end
$var parameter 32 R TICK_WIDTH $end
$var reg 3 S bit_index [2:0] $end
$var reg 7 T data_latch [6:0] $end
$var reg 1 U parity_latch $end
$var reg 3 V state [2:0] $end
$var reg 4 W tick_count [3:0] $end
$scope function counter_width $end
$var integer 32 X value [31:0] $end
$var integer 32 Y width [31:0] $end
$upscope $end
$upscope $end
$upscope $end
$scope task pulse_request $end
$var reg 7 Z value [6:0] $end
$upscope $end
$upscope $end
$enddefinitions $end
$comment Show the parameter values. $end
$dumpall
b100 R
b100 Q
b1 P
b10 O
b1001 N
b0 M
b11 L
b1010 K
b100 ?
b100 >
b1 =
b10 <
b1001 ;
b0 :
b100 9
b11 8
b1010 7
b1010 6
b100101100 )
b101101 (
b1011001 '
b1010 &
$end
#0
$dumpvars
bx Z
bx Y
bx X
bx W
bx V
xU
bx T
bx S
b0 J
bx I
bx H
bx G
bx F
xE
xD
bx C
xB
bx A
bx @
bx 5
b0 4
bx 3
b0 2
b0 1
b0 0
0/
1.
0-
b0 ,
0+
0*
x%
x$
bx #
x"
x!
$end
#1000
1!
0U
b0 T
b0 S
b0 W
0%
b0 V
1E
1D
0$
0"
b0 #
b0 5
b0 C
0B
b0 A
b0 @
b0 G
b0 F
0.
#5000
1*
#10000
0*
#15000
1*
#20000
1.
0*
#25000
1*
#30000
1-
b1011001 1
b1011001 4
b1011001 J
b1011001 Z
0*
#35000
0!
1%
b1 V
b1011001 T
1*
#40000
0-
0*
#45000
0D
b1 W
1*
#50000
0*
#55000
b10 W
0E
1*
#60000
0*
#65000
b1 F
b11 W
1*
#70000
0*
#75000
b100 W
b1 G
1*
#80000
0*
#85000
b10 G
b101 W
1*
#90000
0*
#95000
b110 W
b11 G
1*
#100000
0*
#105000
b100 G
b111 W
1*
#110000
0*
#115000
b1000 W
b10 F
b0 G
1*
#120000
0*
#125000
b1 G
b1001 W
1*
#130000
0*
#135000
b10 V
b0 W
b10 G
1*
#140000
0*
#145000
b11 G
b1 W
1*
#150000
0*
#155000
b10 W
b100 G
1*
#160000
0*
#165000
b101 G
b11 W
1*
#170000
0*
#175000
b100 W
b110 G
1*
#180000
0*
#185000
b111 G
b101 W
1*
#190000
0*
#195000
b110 W
b1000 G
1*
#200000
0*
#205000
b1001 G
b111 W
1*
#210000
0*
#215000
b1000 W
b11 F
b0 G
1*
#220000
0*
#225000
b1 G
b1001 W
1*
#230000
0*
#235000
1!
b11 V
b0 W
b10 G
1*
#240000
0*
#245000
b11 G
1D
b1 W
1*
#250000
0*
#255000
b10 W
1E
b100 G
1*
#260000
0*
#265000
b101 G
b11 W
1*
#270000
0*
#275000
b100 W
b110 G
1*
#280000
0*
#285000
b111 G
b101 W
1*
#290000
0*
#295000
b110 W
b1000 G
1*
#300000
0*
#305000
b1001 G
b111 W
1*
#310000
0*
#315000
b1000 W
b1 @
b1 A
b0 G
1*
#320000
0*
#325000
b1 G
b1001 W
1*
#330000
0*
#335000
0!
b1 S
b0 W
b10 G
1*
#340000
0*
#345000
b11 G
0D
b1 W
1*
#350000
0*
#355000
b10 W
0E
b100 G
1*
#360000
0*
#365000
b101 G
b11 W
1*
#370000
0*
#375000
b100 W
b110 G
1*
#380000
0*
#385000
b111 G
b101 W
1*
#390000
0*
#395000
b110 W
b1000 G
1*
#400000
0*
#405000
b1001 G
b111 W
1*
#410000
0*
#415000
b1000 W
b10 @
b0 G
1*
#420000
0*
#425000
b1 G
b1001 W
1*
#430000
0*
#435000
b10 S
b0 W
b10 G
1*
#440000
0*
#445000
b11 G
b1 W
1*
#450000
0*
#455000
b10 W
b100 G
1*
#460000
0*
#465000
b101 G
b11 W
1*
#470000
0*
#475000
b100 W
b110 G
1*
#480000
0*
#485000
b111 G
b101 W
1*
#490000
0*
#495000
b110 W
b1000 G
1*
#500000
0*
#505000
b1001 G
b111 W
1*
#510000
0*
#515000
b1000 W
b11 @
b0 G
1*
#520000
0*
#525000
b1 G
b1001 W
1*
#530000
0*
#535000
1!
b11 S
b0 W
b10 G
1*
#540000
0*
#545000
b11 G
1D
b1 W
1*
#550000
0*
#555000
b10 W
1E
b100 G
1*
#560000
0*
#565000
b101 G
b11 W
1*
#570000
0*
#575000
b100 W
b110 G
1*
#580000
0*
#585000
b111 G
b101 W
1*
#590000
0*
#595000
b110 W
b1000 G
1*
#600000
0*
#605000
b1001 G
b111 W
1*
#610000
0*
#615000
b1000 W
b100 @
b1001 A
b0 G
1*
#620000
0*
#625000
b1 G
b1001 W
1*
#630000
0*
#635000
b100 S
b0 W
b10 G
1*
#640000
0*
#645000
b11 G
b1 W
1*
#650000
0*
#655000
b10 W
b100 G
1*
#660000
0*
#665000
b101 G
b11 W
1*
#670000
0*
#675000
b100 W
b110 G
1*
#680000
0*
#685000
b111 G
b101 W
1*
#690000
0*
#695000
b110 W
b1000 G
1*
#700000
0*
#705000
b1001 G
b111 W
1*
#710000
0*
#715000
b1000 W
b101 @
b11001 A
b0 G
1*
#720000
0*
#725000
b1 G
b1001 W
1*
#730000
0*
#735000
0!
b101 S
b0 W
b10 G
1*
#740000
0*
#745000
b11 G
0D
b1 W
1*
#750000
0*
#755000
b10 W
0E
b100 G
1*
#760000
0*
#765000
b101 G
b11 W
1*
#770000
0*
#775000
b100 W
b110 G
1*
#780000
0*
#785000
b111 G
b101 W
1*
#790000
0*
#795000
b110 W
b1000 G
1*
#800000
0*
#805000
b1001 G
b111 W
1*
#810000
0*
#815000
b1000 W
b110 @
b0 G
1*
#820000
0*
#825000
b1 G
b1001 W
1*
#830000
0*
#835000
1!
b110 S
b0 W
b10 G
1*
#840000
0*
#845000
b11 G
1D
b1 W
1*
#850000
0*
#855000
b10 W
1E
b100 G
1*
#860000
0*
#865000
b101 G
b11 W
1*
#870000
0*
#875000
b100 W
b110 G
1*
#880000
0*
#885000
b111 G
b101 W
1*
#890000
0*
#895000
b110 W
b1000 G
1*
#900000
0*
#905000
b1001 G
b111 W
1*
#910000
0*
#915000
b1000 W
b100 F
b1011001 A
b0 G
1*
#920000
0*
#925000
b1 G
b1001 W
1*
#930000
0*
#935000
b100 V
b0 W
b10 G
1*
#940000
0*
#945000
b11 G
b1 W
1*
#950000
0*
#955000
b10 W
b100 G
1*
#960000
0*
#965000
b101 G
b11 W
1*
#970000
0*
#975000
b100 W
b110 G
1*
#980000
0*
#985000
b111 G
b101 W
1*
#990000
0*
#995000
b110 W
b1000 G
1*
#1000000
0*
#1005000
b1001 G
b111 W
1*
#1010000
0*
#1015000
b1000 W
b0 F
1$
b1011001 #
b1011001 5
b1011001 C
1"
b0 G
1*
#1020000
b1 2
1+
b1011001 ,
0*
#1025000
b0 @
0$
0"
b1001 W
1*
#1030000
0*
#1035000
0%
b0 V
b0 W
1*
#1040000
1-
b101101 1
b101101 4
b101101 J
b101101 Z
0*
#1045000
0!
1%
b1 V
b101101 T
b0 S
1*
#1050000
b0 3
0-
0*
#1055000
b1 W
0D
1*
#1060000
b1 3
0*
#1065000
0E
b10 W
1*
#1070000
b10 3
0*
#1075000
b11 W
b1 F
1*
#1080000
b11 3
0*
#1085000
b1 G
b100 W
1*
#1090000
b100 3
0*
#1095000
b101 W
b10 G
1*
#1100000
b101 3
0*
#1105000
b11 G
b110 W
1*
#1110000
b110 3
0*
#1115000
b111 W
b100 G
1*
#1120000
b111 3
0*
#1125000
b10 F
b0 G
b1000 W
1*
#1130000
b1000 3
0*
#1135000
b1001 W
b1 G
1*
#1140000
b1001 3
0*
#1145000
b10 G
b10 V
b0 W
1*
#1150000
b1010 3
0*
#1155000
b1 W
b11 G
1*
#1160000
b1011 3
0*
#1165000
b100 G
b10 W
1*
#1170000
b1100 3
0*
#1175000
b11 W
b101 G
1*
#1180000
b1101 3
0*
#1185000
b110 G
b100 W
1*
#1190000
b1110 3
0*
#1195000
b101 W
b111 G
1*
#1200000
b1111 3
0*
#1205000
b1000 G
b110 W
1*
#1210000
b10000 3
0*
#1215000
b111 W
b1001 G
1*
#1220000
b10001 3
0*
#1225000
b11 F
b0 G
b1000 W
1*
#1230000
b10010 3
0*
#1235000
b1001 W
b1 G
1*
#1240000
b10011 3
0*
#1245000
1!
b10 G
b11 V
b0 W
1*
#1250000
b10100 3
0*
#1255000
b1 W
1D
b11 G
1*
#1260000
b10101 3
0*
#1265000
b100 G
1E
b10 W
1*
#1270000
b10110 3
0*
#1275000
b11 W
b101 G
1*
#1280000
b10111 3
0*
#1285000
b110 G
b100 W
1*
#1290000
b11000 3
0*
#1295000
b101 W
b111 G
1*
#1300000
b11001 3
0*
#1305000
b1000 G
b110 W
1*
#1310000
b11010 3
0*
#1315000
b111 W
b1001 G
1*
#1320000
b11011 3
0*
#1325000
b1 @
b0 G
b1000 W
1*
#1330000
b11100 3
0*
#1335000
b1001 W
b1 G
1*
#1340000
b11101 3
0*
#1345000
0!
b10 G
b1 S
b0 W
1*
#1350000
b11110 3
0*
#1355000
b1 W
0D
b11 G
1*
#1360000
b11111 3
0*
#1365000
b100 G
0E
b10 W
1*
#1370000
b100000 3
0*
#1375000
b11 W
b101 G
1*
#1380000
b100001 3
0*
#1385000
b110 G
b100 W
1*
#1390000
b100010 3
0*
#1395000
b101 W
b111 G
1*
#1400000
b100011 3
0*
#1405000
b1000 G
b110 W
1*
#1410000
b100100 3
0*
#1415000
b111 W
b1001 G
1*
#1420000
b100101 3
0*
#1425000
b10 @
b0 G
b1000 W
1*
#1430000
b100110 3
0*
#1435000
b1001 W
b1 G
1*
#1440000
b100111 3
0*
#1445000
1!
b10 G
b10 S
b0 W
1*
#1450000
b101000 3
0*
#1455000
b1 W
1D
b11 G
1*
#1460000
b101001 3
0*
#1465000
b100 G
1E
b10 W
1*
#1470000
b101010 3
0*
#1475000
b11 W
b101 G
1*
#1480000
b101011 3
0*
#1485000
b110 G
b100 W
1*
#1490000
b101100 3
0*
#1495000
b101 W
b111 G
1*
#1500000
b101101 3
0*
#1505000
b1000 G
b110 W
1*
#1510000
b101110 3
0*
#1515000
b111 W
b1001 G
1*
#1520000
b101111 3
0*
#1525000
b11 @
b1011101 A
b0 G
b1000 W
1*
#1530000
b110000 3
0*
#1535000
b1001 W
b1 G
1*
#1540000
b110001 3
0*
#1545000
b10 G
b11 S
b0 W
1*
#1550000
b110010 3
0*
#1555000
b1 W
b11 G
1*
#1560000
b110011 3
0*
#1565000
b100 G
b10 W
1*
#1570000
b110100 3
0*
#1575000
b11 W
b101 G
1*
#1580000
b110101 3
0*
#1585000
b110 G
b100 W
1*
#1590000
b110110 3
0*
#1595000
b101 W
b111 G
1*
#1600000
b110111 3
0*
#1605000
b1000 G
b110 W
1*
#1610000
b111000 3
0*
#1615000
b111 W
b1001 G
1*
#1620000
b111001 3
0*
#1625000
b100 @
b0 G
b1000 W
1*
#1630000
b111010 3
0*
#1635000
b1001 W
b1 G
1*
#1640000
b111011 3
0*
#1645000
0!
b10 G
b100 S
b0 W
1*
#1650000
b111100 3
0*
#1655000
b1 W
0D
b11 G
1*
#1660000
b111101 3
0*
#1665000
b100 G
0E
b10 W
1*
#1670000
b111110 3
0*
#1675000
b11 W
b101 G
1*
#1680000
b111111 3
0*
#1685000
b110 G
b100 W
1*
#1690000
b1000000 3
0*
#1695000
b101 W
b111 G
1*
#1700000
b1000001 3
0*
#1705000
b1000 G
b110 W
1*
#1710000
b1000010 3
0*
#1715000
b111 W
b1001 G
1*
#1720000
b1000011 3
0*
#1725000
b101 @
b1001101 A
b0 G
b1000 W
1*
#1730000
b1000100 3
0*
#1735000
b1001 W
b1 G
1*
#1740000
b1000101 3
0*
#1745000
1!
b10 G
b101 S
b0 W
1*
#1750000
b1000110 3
0*
#1755000
b1 W
1D
b11 G
1*
#1760000
b1000111 3
0*
#1765000
b100 G
1E
b10 W
1*
#1770000
b1001000 3
0*
#1775000
b11 W
b101 G
1*
#1780000
b1001001 3
0*
#1785000
b110 G
b100 W
1*
#1790000
b1001010 3
0*
#1795000
b101 W
b111 G
1*
#1800000
b1001011 3
0*
#1805000
b1000 G
b110 W
1*
#1810000
b1001100 3
0*
#1815000
b111 W
b1001 G
1*
#1820000
b1001101 3
0*
#1825000
b110 @
b1101101 A
b0 G
b1000 W
1*
#1830000
b1001110 3
0*
#1835000
b1001 W
b1 G
1*
#1840000
b1001111 3
0*
#1845000
0!
b10 G
b110 S
b0 W
1*
#1850000
b1010000 3
0*
#1855000
b1 W
0D
b11 G
1*
#1860000
b1010001 3
0*
#1865000
b100 G
0E
b10 W
1*
#1870000
b1010010 3
0*
#1875000
b11 W
b101 G
1*
#1880000
b1010011 3
0*
#1885000
b110 G
b100 W
1*
#1890000
b1010100 3
0*
#1895000
b101 W
b111 G
1*
#1900000
b1010101 3
0*
#1905000
b1000 G
b110 W
1*
#1910000
b1010110 3
0*
#1915000
b111 W
b1001 G
1*
#1920000
b1010111 3
0*
#1925000
b100 F
b101101 A
b0 G
b1000 W
1*
#1930000
b1011000 3
0*
#1935000
b1001 W
b1 G
1*
#1940000
b1011001 3
0*
#1945000
1!
b10 G
b100 V
b0 W
1*
#1950000
b1011010 3
0*
#1955000
b1 W
1D
b11 G
1*
#1960000
b1011011 3
0*
#1965000
b100 G
1E
b10 W
1*
#1970000
b1011100 3
0*
#1975000
b11 W
b101 G
1*
#1980000
b1011101 3
0*
#1985000
b110 G
b100 W
1*
#1990000
b1011110 3
0*
#1995000
b101 W
b111 G
1*
#2000000
b1011111 3
0*
#2005000
b1000 G
b110 W
1*
#2010000
b1100000 3
0*
#2015000
b111 W
b1001 G
1*
#2020000
b1100001 3
0*
#2025000
b0 F
1$
b101101 #
b101101 5
b101101 C
1"
b0 G
b1000 W
1*
#2030000
b1100010 3
b10 2
1/
b101101 0
0*
