DSDL7/Final/rtl/UARTReceiver.v
`timescale 1ns/1ps

// Seven-bit UART receiver for the assignment-specific parity-before-data frame.
// rx is synchronized, the start bit is confirmed at midpoint, and each later
// symbol is sampled once per BIT_TICKS clocks at the same phase.
module UARTReceiver #(
    parameter integer BIT_TICKS = 434
) (
    input  wire       clk,
    input  wire       rstN,
    input  wire       rx,
    output reg  [6:0] rec_data,
    output reg        rec_new_data,
    output reg        correct_data
);

    function integer counter_width;
        input integer value;
        integer width;
        begin
            value = value - 1;
            width = 0;
            while (value > 0) begin
                value = value >> 1;
                width = width + 1;
            end
            counter_width = width < 1 ? 1 : width;
        end
    endfunction

    localparam integer TICK_WIDTH = counter_width(BIT_TICKS);
    localparam [TICK_WIDTH-1:0] LAST_TICK = BIT_TICKS - 1;
    localparam [TICK_WIDTH-1:0] HALF_TICK = (BIT_TICKS / 2) - 1;

    localparam [2:0] IDLE   = 3'd0;
    localparam [2:0] START  = 3'd1;
    localparam [2:0] PARITY = 3'd2;
    localparam [2:0] DATA   = 3'd3;
    localparam [2:0] STOP   = 3'd4;

    reg rx_meta;
    reg rx_sync;
    reg [2:0] state;
    reg [TICK_WIDTH-1:0] tick_count;
    reg [2:0] bit_index;
    reg [6:0] data_latch;
    reg parity_latch;

    // Two flip-flops isolate the FSM from an asynchronous serial input.
    always @(posedge clk or negedge rstN) begin
        if (!rstN) begin
            rx_meta <= 1'b1;
            rx_sync <= 1'b1;
        end else begin
            rx_meta <= rx;
            rx_sync <= rx_meta;
        end
    end

    always @(posedge clk or negedge rstN) begin
        if (!rstN) begin
            state          <= IDLE;
            tick_count     <= {TICK_WIDTH{1'b0}};
            bit_index      <= 3'd0;
            data_latch     <= 7'd0;
            parity_latch   <= 1'b0;
            rec_data       <= 7'd0;
            rec_new_data   <= 1'b0;
            correct_data   <= 1'b0;
        end else begin
            // Completion and validity are aligned one-clock notifications.
            rec_new_data <= 1'b0;
            correct_data <= 1'b0;

            case (state)
                IDLE: begin
                    tick_count <= {TICK_WIDTH{1'b0}};
                    bit_index <= 3'd0;
                    if (!rx_sync)
                        state <= START;
                end

                START: begin
                    if (tick_count == HALF_TICK) begin
                        tick_count <= {TICK_WIDTH{1'b0}};
                        state <= rx_sync ? IDLE : PARITY;
                    end else begin
                        tick_count <= tick_count + 1'b1;
                    end
                end

                PARITY: begin
                    if (tick_count == LAST_TICK) begin
                        tick_count <= {TICK_WIDTH{1'b0}};
                        bit_index <= 3'd0;
                        parity_latch <= rx_sync;
                        state <= DATA;
                    end else begin
                        tick_count <= tick_count + 1'b1;
                    end
                end

                DATA: begin
                    if (tick_count == LAST_TICK) begin
                        tick_count <= {TICK_WIDTH{1'b0}};
                        data_latch[bit_index] <= rx_sync;
                        if (bit_index == 3'd6) begin
                            state <= STOP;
                        end else begin
                            bit_index <= bit_index + 1'b1;
                        end
                    end else begin
                        tick_count <= tick_count + 1'b1;
                    end
                end

                STOP: begin
                    if (tick_count == LAST_TICK) begin
                        tick_count <= {TICK_WIDTH{1'b0}};
                        rec_new_data <= 1'b1;
                        if (rx_sync && ((^data_latch) == parity_latch)) begin
                            rec_data <= data_latch;
                            correct_data <= 1'b1;
                        end
                        state <= IDLE;
                    end else begin
                        tick_count <= tick_count + 1'b1;
                    end
                end

                default: begin
                    state <= IDLE;
                    tick_count <= {TICK_WIDTH{1'b0}};
                    bit_index <= 3'd0;
                end
            endcase
        end
    end

endmodule

DSDL7/final/quartus/UARTSender.v
`timescale 1ns/1ps

// Seven-bit UART sender for the assignment-specific parity-before-data frame.
// new_data is accepted only while idle; the active frame uses a latched copy.
module UARTSender #(
    parameter integer BIT_TICKS = 434
) (
    input  wire       clk,
    input  wire       rstN,
    input  wire       new_data,
    input  wire [6:0] send_data,
    output wire       tx,
    output wire       busy
);

    function integer counter_width;
        input integer value;
        integer width;
        begin
            value = value - 1;
            width = 0;
            while (value > 0) begin
                value = value >> 1;
                width = width + 1;
            end
            counter_width = width < 1 ? 1 : width;
        end
    endfunction

    localparam integer TICK_WIDTH = counter_width(BIT_TICKS);
    localparam [TICK_WIDTH-1:0] LAST_TICK = BIT_TICKS - 1;

    localparam [2:0] IDLE   = 3'd0;
    localparam [2:0] START  = 3'd1;
    localparam [2:0] PARITY = 3'd2;
    localparam [2:0] DATA   = 3'd3;
    localparam [2:0] STOP   = 3'd4;

    reg [2:0] state;
    reg [TICK_WIDTH-1:0] tick_count;
    reg [2:0] bit_index;
    reg [6:0] data_latch;
    reg parity_latch;

    assign busy = state != IDLE;
    assign tx = state == START  ? 1'b0 :
                state == PARITY ? parity_latch :
                state == DATA   ? data_latch[bit_index] : 1'b1;

    always @(posedge clk or negedge rstN) begin
        if (!rstN) begin
            state        <= IDLE;
            tick_count   <= {TICK_WIDTH{1'b0}};
            bit_index    <= 3'd0;
            data_latch   <= 7'd0;
            parity_latch <= 1'b0;
        end else begin
            case (state)
                IDLE: begin
                    tick_count <= {TICK_WIDTH{1'b0}};
                    bit_index  <= 3'd0;
                    if (new_data) begin
                        data_latch   <= send_data;
                        parity_latch <= ^send_data;
                        state        <= START;
                    end
                end

                START: begin
                    if (tick_count == LAST_TICK) begin
                        tick_count <= {TICK_WIDTH{1'b0}};
                        state <= PARITY;
                    end else begin
                        tick_count <= tick_count + 1'b1;
                    end
                end

                PARITY: begin
                    if (tick_count == LAST_TICK) begin
                        tick_count <= {TICK_WIDTH{1'b0}};
                        bit_index <= 3'd0;
                        state <= DATA;
                    end else begin
                        tick_count <= tick_count + 1'b1;
                    end
                end

                DATA: begin
                    if (tick_count == LAST_TICK) begin
                        tick_count <= {TICK_WIDTH{1'b0}};
                        if (bit_index == 3'd6) begin
                            state <= STOP;
                        end else begin
                            bit_index <= bit_index + 1'b1;
                        end
                    end else begin
                        tick_count <= tick_count + 1'b1;
                    end
                end

                STOP: begin
                    if (tick_count == LAST_TICK) begin
                        tick_count <= {TICK_WIDTH{1'b0}};
                        state <= IDLE;
                    end else begin
                        tick_count <= tick_count + 1'b1;
                    end
                end

                default: begin
                    state <= IDLE;
                    tick_count <= {TICK_WIDTH{1'b0}};
                    bit_index <= 3'd0;
                end
            endcase
        end
    end

endmodule

DSDL7/final/rtl/UARTTop.v
`timescale 1ns/1ps

// Direct internal loopback: the sender's serial output is the receiver input.
module UARTTop #(
    parameter integer BIT_TICKS = 434
) (
    input  wire       clk,
    input  wire       rstN,
    input  wire       new_data,
    input  wire [6:0] send_data,
    output wire       tx,
    output wire       busy,
    output wire [6:0] rec_data,
    output wire       rec_new_data,
    output wire       correct_data
);

    UARTSender #(.BIT_TICKS(BIT_TICKS)) sender (
        .clk(clk),
        .rstN(rstN),
        .new_data(new_data),
        .send_data(send_data),
        .tx(tx),
        .busy(busy)
    );

    UARTReceiver #(.BIT_TICKS(BIT_TICKS)) receiver (
        .clk(clk),
        .rstN(rstN),
        .rx(tx),
        .rec_data(rec_data),
        .rec_new_data(rec_new_data),
        .correct_data(correct_data)
    );

endmodule

DSDL7/final/rtl/Tester.v
`timescale 1ns/1ps

// Complete Experiment 7 regression. The loopback instance checks sender/top
// behavior; the standalone receiver accepts deliberately malformed raw frames.
module Tester;

    localparam integer BIT_TICKS = 2;
    localparam integer TIMEOUT_CYCLES = 40 * BIT_TICKS;
    localparam [6:0] FIRST_DATA = 7'b1011001;
    localparam [6:0] SECOND_DATA = 7'b0101101;

    reg clk;
    reg rstN;
    reg new_data;
    reg [6:0] send_data;
    wire tx;
    wire busy;
    wire [6:0] rec_data;
    wire rec_new_data;
    wire correct_data;

    reg raw_rx;
    wire [6:0] raw_rec_data;
    wire raw_rec_new_data;
    wire raw_correct_data;

    integer top_completion_count;
    integer raw_completion_count;
    reg [6:0] top_data_history [0:255];
    reg top_correct_history [0:255];
    reg [6:0] raw_data_history [0:15];
    reg raw_correct_history [0:15];
    reg previous_top_new;
    reg previous_raw_new;
    integer base_count;
    integer value;

    UARTTop #(.BIT_TICKS(BIT_TICKS)) loopback (
        .clk(clk),
        .rstN(rstN),
        .new_data(new_data),
        .send_data(send_data),
        .tx(tx),
        .busy(busy),
        .rec_data(rec_data),
        .rec_new_data(rec_new_data),
        .correct_data(correct_data)
    );

    UARTReceiver #(.BIT_TICKS(BIT_TICKS)) raw_receiver (
        .clk(clk),
        .rstN(rstN),
        .rx(raw_rx),
        .rec_data(raw_rec_data),
        .rec_new_data(raw_rec_new_data),
        .correct_data(raw_correct_data)
    );

    initial clk = 1'b0;
    always #5 clk = ~clk;

    // Record every completion and enforce the one-cycle output contract.
    always @(negedge clk or negedge rstN) begin
        if (!rstN) begin
            top_completion_count = 0;
            raw_completion_count = 0;
            previous_top_new = 1'b0;
            previous_raw_new = 1'b0;
        end else begin
            if (rec_new_data && previous_top_new)
                $fatal(1, "FAIL: loopback rec_new_data exceeded one cycle");
            if (raw_rec_new_data && previous_raw_new)
                $fatal(1, "FAIL: raw rec_new_data exceeded one cycle");
            if (correct_data && !rec_new_data)
                $fatal(1, "FAIL: loopback correct_data is not completion-aligned");
            if (raw_correct_data && !raw_rec_new_data)
                $fatal(1, "FAIL: raw correct_data is not completion-aligned");

            if (rec_new_data) begin
                top_data_history[top_completion_count] = rec_data;
                top_correct_history[top_completion_count] = correct_data;
                top_completion_count = top_completion_count + 1;
            end
            if (raw_rec_new_data) begin
                raw_data_history[raw_completion_count] = raw_rec_data;
                raw_correct_history[raw_completion_count] = raw_correct_data;
                raw_completion_count = raw_completion_count + 1;
            end

            previous_top_new = rec_new_data;
            previous_raw_new = raw_rec_new_data;
        end
    end

    task wait_top_count;
        input integer target;
        integer cycles;
        begin
            cycles = 0;
            while (top_completion_count < target && cycles < TIMEOUT_CYCLES) begin
                @(negedge clk);
                cycles = cycles + 1;
            end
            if (top_completion_count < target)
                $fatal(1, "FAIL: loopback completion timeout at count %0d",
                       target);
        end
    endtask

    task wait_raw_count;
        input integer target;
        integer cycles;
        begin
            cycles = 0;
            while (raw_completion_count < target && cycles < TIMEOUT_CYCLES) begin
                @(negedge clk);
                cycles = cycles + 1;
            end
            if (raw_completion_count < target)
                $fatal(1, "FAIL: raw receiver completion timeout at count %0d",
                       target);
        end
    endtask

    task check_top_result;
        input integer index;
        input [6:0] expected_data;
        begin
            if (top_correct_history[index] !== 1'b1 ||
                top_data_history[index] !== expected_data)
                $fatal(1, "FAIL: loopback[%0d] expected=%b got=%b correct=%b",
                       index, expected_data, top_data_history[index],
                       top_correct_history[index]);
        end
    endtask

    task pulse_request;
        input [6:0] data;
        begin
            @(negedge clk);
            send_data = data;
            new_data = 1'b1;
            @(negedge clk);
            new_data = 1'b0;
        end
    endtask

    task check_symbol;
        input expected_tx;
        integer cycle;
        begin
            for (cycle = 0; cycle < BIT_TICKS; cycle = cycle + 1) begin
                if (tx !== expected_tx || busy !== 1'b1)
                    $fatal(1, "FAIL: frame symbol=%b cycle=%0d tx=%b busy=%b",
                           expected_tx, cycle, tx, busy);
                @(negedge clk);
            end
        end
    endtask

    task send_and_check_frame;
        input [6:0] data;
        integer bit_index;
        begin
            @(negedge clk);
            send_data = data;
            new_data = 1'b1;
            @(negedge clk);
            new_data = 1'b0;

            check_symbol(1'b0);
            check_symbol(^data);
            for (bit_index = 0; bit_index < 7; bit_index = bit_index + 1)
                check_symbol(data[bit_index]);
            check_symbol(1'b1);

            if (tx !== 1'b1 || busy !== 1'b0)
                $fatal(1, "FAIL: sender did not return to idle after frame");
        end
    endtask

    task hold_raw_rx;
        input level;
        integer cycle;
        begin
            raw_rx = level;
            for (cycle = 0; cycle < BIT_TICKS; cycle = cycle + 1)
                @(negedge clk);
        end
    endtask

    task drive_raw_frame;
        input [6:0] data;
        input parity_bit;
        input stop_bit;
        integer bit_index;
        begin
            @(negedge clk);
            hold_raw_rx(1'b0);
            hold_raw_rx(parity_bit);
            for (bit_index = 0; bit_index < 7; bit_index = bit_index + 1)
                hold_raw_rx(data[bit_index]);
            hold_raw_rx(stop_bit);
            raw_rx = 1'b1;
        end
    endtask

    initial begin
        $dumpfile("/tmp/Tester.vcd");
        $dumpvars(0, Tester);
        rstN = 1'b1;
        new_data = 1'b0;
        send_data = 7'd0;
        raw_rx = 1'b1;

        #1 rstN = 1'b0;
        #1;
        if (tx !== 1'b1 || busy !== 1'b0 || rec_data !== 7'd0 ||
            rec_new_data !== 1'b0 || correct_data !== 1'b0 ||
            raw_rec_data !== 7'd0 || raw_rec_new_data !== 1'b0 ||
            raw_correct_data !== 1'b0)
            $fatal(1, "FAIL: asynchronous reset outputs");
        repeat (2) @(negedge clk);
        rstN = 1'b1;
        repeat (2) @(negedge clk);
        $display("PASS: reset and idle outputs");

        $display("TEST: exact valid frame and symbol timing");
        base_count = top_completion_count;
        send_and_check_frame(FIRST_DATA);
        wait_top_count(base_count + 1);
        check_top_result(base_count, FIRST_DATA);

        $display("TEST: request asserted while busy");
        base_count = top_completion_count;
        pulse_request(FIRST_DATA);
        if (busy !== 1'b1)
            $fatal(1, "FAIL: sender did not become busy");
        repeat (2 * BIT_TICKS) @(negedge clk);
        send_data = SECOND_DATA;
        new_data = 1'b1;
        @(negedge clk);
        new_data = 1'b0;
        wait_top_count(base_count + 1);
        check_top_result(base_count, FIRST_DATA);
        repeat (12 * BIT_TICKS) @(negedge clk);
        if (top_completion_count != base_count + 1)
            $fatal(1, "FAIL: busy request was queued");

        $display("TEST: required consecutive frames");
        base_count = top_completion_count;
        pulse_request(FIRST_DATA);
        while (busy !== 1'b0)
            @(negedge clk);
        send_data = SECOND_DATA;
        new_data = 1'b1;
        @(negedge clk);
        new_data = 1'b0;
        wait_top_count(base_count + 2);
        check_top_result(base_count, FIRST_DATA);
        check_top_result(base_count + 1, SECOND_DATA);

        $display("TEST: exhaustive seven-bit loopback");
        for (value = 0; value < 128; value = value + 1) begin
            base_count = top_completion_count;
            pulse_request(value[6:0]);
            wait_top_count(base_count + 1);
            check_top_result(base_count, value[6:0]);
        end

        $display("TEST: valid raw receiver frame");
        base_count = raw_completion_count;
        drive_raw_frame(FIRST_DATA, ^FIRST_DATA, 1'b1);
        wait_raw_count(base_count + 1);
        if (raw_correct_history[base_count] !== 1'b1 ||
            raw_data_history[base_count] !== FIRST_DATA)
            $fatal(1, "FAIL: valid raw frame");

        $display("TEST: required parity error");
        base_count = raw_completion_count;
        drive_raw_frame(SECOND_DATA, ~(^SECOND_DATA), 1'b1);
        wait_raw_count(base_count + 1);
        if (raw_correct_history[base_count] !== 1'b0 ||
            raw_data_history[base_count] !== FIRST_DATA)
            $fatal(1, "FAIL: parity error semantics");

        $display("TEST: required stop-bit error");
        base_count = raw_completion_count;
        drive_raw_frame(SECOND_DATA, ^SECOND_DATA, 1'b0);
        wait_raw_count(base_count + 1);
        if (raw_correct_history[base_count] !== 1'b0 ||
            raw_data_history[base_count] !== FIRST_DATA)
            $fatal(1, "FAIL: stop-bit error semantics");

        $display("TEST: false-start rejection and recovery");
        base_count = raw_completion_count;
        @(negedge clk);
        raw_rx = 1'b0;
        @(negedge clk);
        raw_rx = 1'b1;
        repeat (4 * BIT_TICKS) @(negedge clk);
        if (raw_completion_count != base_count)
            $fatal(1, "FAIL: false start completed a frame");
        drive_raw_frame(SECOND_DATA, ^SECOND_DATA, 1'b1);
        wait_raw_count(base_count + 1);
        if (raw_correct_history[base_count] !== 1'b1 ||
            raw_data_history[base_count] !== SECOND_DATA)
            $fatal(1, "FAIL: recovery after false start");

        @(negedge clk);
        $display("PASS: complete DSDL7 UART regression");
        $finish;
    end

endmodule

DSDL7/final/sim/Tester.vcd
$date
	Mon Aug 24 09:43:54 2026
$end
$version
	Icarus Verilog
$end
$timescale
	1ps
$end
$scope module Tester $end
$var wire 1 ! tx $end
$var wire 1 " rec_new_data $end
$var wire 7 # rec_data [6:0] $end
$var wire 1 $ raw_rec_new_data $end
$var wire 7 % raw_rec_data [6:0] $end
$var wire 1 & raw_correct_data $end
$var wire 1 ' correct_data $end
$var wire 1 ( busy $end
$var parameter 32 ) BIT_TICKS $end
$var parameter 7 * FIRST_DATA $end
$var parameter 7 + SECOND_DATA $end
$var parameter 32 , TIMEOUT_CYCLES $end
$var reg 1 - clk $end
$var reg 1 . new_data $end
$var reg 1 / previous_raw_new $end
$var reg 1 0 previous_top_new $end
$var reg 1 1 raw_rx $end
$var reg 1 2 rstN $end
$var reg 7 3 send_data [6:0] $end
$var integer 32 4 base_count [31:0] $end
$var integer 32 5 raw_completion_count [31:0] $end
$var integer 32 6 top_completion_count [31:0] $end
$var integer 32 7 value [31:0] $end
$scope module loopback $end
$var wire 1 - clk $end
$var wire 1 . new_data $end
$var wire 1 2 rstN $end
$var wire 7 8 send_data [6:0] $end
$var wire 1 ! tx $end
$var wire 1 " rec_new_data $end
$var wire 7 9 rec_data [6:0] $end
$var wire 1 ' correct_data $end
$var wire 1 ( busy $end
$var parameter 32 : BIT_TICKS $end
$scope module receiver $end
$var wire 1 - clk $end
$var wire 1 2 rstN $end
$var wire 1 ! rx $end
$var parameter 32 ; BIT_TICKS $end
$var parameter 3 < DATA $end
$var parameter 1 = HALF_TICK $end
$var parameter 3 > IDLE $end
$var parameter 1 ? LAST_TICK $end
$var parameter 3 @ PARITY $end
$var parameter 3 A START $end
$var parameter 3 B STOP $end
$var parameter 32 C TICK_WIDTH $end
$var reg 3 D bit_index [2:0] $end
$var reg 1 ' correct_data $end
$var reg 7 E data_latch [6:0] $end
$var reg 1 F parity_latch $end
$var reg 7 G rec_data [6:0] $end
$var reg 1 " rec_new_data $end
$var reg 1 H rx_meta $end
$var reg 1 I rx_sync $end
$var reg 3 J state [2:0] $end
$var reg 1 K tick_count $end
$scope function counter_width $end
$var integer 32 L value [31:0] $end
$var integer 32 M width [31:0] $end
$upscope $end
$upscope $end
$scope module sender $end
$var wire 1 - clk $end
$var wire 1 . new_data $end
$var wire 1 2 rstN $end
$var wire 7 N send_data [6:0] $end
$var wire 1 ! tx $end
$var wire 1 ( busy $end
$var parameter 32 O BIT_TICKS $end
$var parameter 3 P DATA $end
$var parameter 3 Q IDLE $end
$var parameter 1 R LAST_TICK $end
$var parameter 3 S PARITY $end
$var parameter 3 T START $end
$var parameter 3 U STOP $end
$var parameter 32 V TICK_WIDTH $end
$var reg 3 W bit_index [2:0] $end
$var reg 7 X data_latch [6:0] $end
$var reg 1 Y parity_latch $end
$var reg 3 Z state [2:0] $end
$var reg 1 [ tick_count $end
$scope function counter_width $end
$var integer 32 \ value [31:0] $end
$var integer 32 ] width [31:0] $end
$upscope $end
$upscope $end
$upscope $end
$scope module raw_receiver $end
$var wire 1 - clk $end
$var wire 1 2 rstN $end
$var wire 1 1 rx $end
$var parameter 32 ^ BIT_TICKS $end
$var parameter 3 _ DATA $end
$var parameter 1 ` HALF_TICK $end
$var parameter 3 a IDLE $end
$var parameter 1 b LAST_TICK $end
$var parameter 3 c PARITY $end
$var parameter 3 d START $end
$var parameter 3 e STOP $end
$var parameter 32 f TICK_WIDTH $end
$var reg 3 g bit_index [2:0] $end
$var reg 1 & correct_data $end
$var reg 7 h data_latch [6:0] $end
$var reg 1 i parity_latch $end
$var reg 7 j rec_data [6:0] $end
$var reg 1 $ rec_new_data $end
$var reg 1 k rx_meta $end
$var reg 1 l rx_sync $end
$var reg 3 m state [2:0] $end
$var reg 1 n tick_count $end
$scope function counter_width $end
$var integer 32 o value [31:0] $end
$var integer 32 p width [31:0] $end
$upscope $end
$upscope $end
$scope task check_symbol $end
$var reg 1 q expected_tx $end
$var integer 32 r cycle [31:0] $end
$upscope $end
$scope task check_top_result $end
$var reg 7 s expected_data [6:0] $end
$var integer 32 t index [31:0] $end
$upscope $end
$scope task drive_raw_frame $end
$var reg 7 u data [6:0] $end
$var reg 1 v parity_bit $end
$var reg 1 w stop_bit $end
$var integer 32 x bit_index [31:0] $end
$upscope $end
$scope task hold_raw_rx $end
$var reg 1 y level $end
$var integer 32 z cycle [31:0] $end
$upscope $end
$scope task pulse_request $end
$var reg 7 { data [6:0] $end
$upscope $end
$scope task send_and_check_frame $end
$var reg 7 | data [6:0] $end
$var integer 32 } bit_index [31:0] $end
$upscope $end
$scope task wait_raw_count $end
$var integer 32 ~ cycles [31:0] $end
$var integer 32 !" target [31:0] $end
$upscope $end
$scope task wait_top_count $end
$var integer 32 "" cycles [31:0] $end
$var integer 32 #" target [31:0] $end
$upscope $end
$upscope $end
$enddefinitions $end
$comment Show the parameter values. $end
$dumpall
b1 f
b100 e
b1 d
b10 c
1b
b0 a
0`
b11 _
b10 ^
b1 V
b100 U
b1 T
b10 S
1R
b0 Q
b11 P
b10 O
b1 C
b100 B
b1 A
b10 @
1?
b0 >
0=
b11 <
b10 ;
b10 :
b1010000 ,
b101101 +
b1011001 *
b10 )
$end
#0
$dumpvars
bx #"
bx ""
bx !"
bx ~
bx }
bx |
bx {
bx z
xy
bx x
xw
xv
bx u
bx t
bx s
bx r
xq
bx p
bx o
xn
bx m
xl
xk
bx j
xi
bx h
bx g
bx ]
bx \
x[
bx Z
xY
bx X
bx W
b0 N
bx M
bx L
xK
bx J
xI
xH
bx G
xF
bx E
bx D
bx 9
b0 8
bx 7
bx 6
bx 5
bx 4
b0 3
12
11
x0
x/
0.
0-
x(
x'
x&
bx %
x$
bx #
x"
x!
$end
#1000
1!
0Y
b0 X
b0 W
0[
0(
b0 Z
1I
1H
0'
0"
b0 #
b0 9
b0 G
0F
b0 E
b0 D
0K
b0 J
1l
1k
0&
0$
b0 %
b0 j
0i
b0 h
b0 g
0n
b0 m
0/
00
b0 5
b0 6
02
#5000
1-
#10000
0-
#15000
1-
#20000
12
0-
#25000
1-
#30000
0-
#35000
1-
#40000
b1011001 |
b0 4
0-
#45000
1-
#50000
1.
b1011001 3
b1011001 8
b1011001 N
0-
#55000
0!
1(
b1 Z
b1011001 X
1-
#60000
b0 r
0q
0.
0-
#65000
0H
1[
1-
#70000
b1 r
0-
#75000
b10 Z
0[
0I
1-
#80000
b0 r
0-
#85000
b1 J
1[
1-
#90000
b1 r
0-
#95000
1!
b11 Z
0[
b10 J
1-
#100000
1q
b0 }
b0 r
0-
#105000
1K
1H
1[
1-
#110000
b1 r
0-
#115000
0!
b1 W
0[
1I
b11 J
0K
1-
#120000
0q
b1 }
b0 r
0-
#125000
1K
0H
1[
1-
#130000
b1 r
0-
#135000
b10 W
0[
0I
b1 D
b1 E
0K
1-
#140000
b10 }
b0 r
0-
#145000
1K
1[
1-
#150000
b1 r
0-
#155000
1!
b11 W
0[
b10 D
0K
1-
#160000
1q
b11 }
b0 r
0-
#165000
1K
1H
1[
1-
#170000
b1 r
0-
#175000
b100 W
0[
1I
b11 D
0K
1-
#180000
b100 }
b0 r
0-
#185000
1K
1[
1-
#190000
b1 r
0-
#195000
0!
b101 W
0[
b100 D
b1001 E
0K
1-
#200000
0q
b101 }
b0 r
0-
#205000
1K
0H
1[
1-
#210000
b1 r
0-
#215000
1!
b110 W
0[
0I
b101 D
b11001 E
0K
1-
#220000
1q
b110 }
b0 r
0-
#225000
1K
1H
1[
1-
#230000
b1 r
0-
#235000
b100 Z
0[
1I
b110 D
0K
1-
#240000
b111 }
b0 r
0-
#245000
1K
1[
1-
#250000
b1 r
0-
#255000
0(
b0 Z
0[
b100 J
b1011001 E
0K
1-
#260000
b0 ""
b1 #"
b10 r
0-
#265000
1K
b0 W
1-
#270000
b1 ""
0-
#275000
b0 J
1'
b1011001 #
b1011001 9
b1011001 G
1"
0K
1-
#280000
b1011001 {
b1 4
b1011001 s
b0 t
b10 ""
10
b1 6
0-
#285000
b0 D
0'
0"
1-
#290000
1.
00
0-
#295000
0!
1(
b1 Z
1-
#300000
0.
0-
#305000
0H
1[
1-
#310000
0-
#315000
b10 Z
0[
0I
1-
#320000
0-
#325000
b1 J
1[
1-
#330000
0-
#335000
1!
b11 Z
0[
b10 J
1-
#340000
1.
b101101 3
b101101 8
b101101 N
0-
#345000
1K
1H
1[
1-
#350000
b0 ""
b10 #"
0.
0-
#355000
0!
b1 W
0[
1I
b11 J
0K
1-
#360000
b1 ""
0-
#365000
1K
0H
1[
1-
#370000
b10 ""
0-
#375000
b10 W
0[
0I
b1 D
0K
1-
#380000
b11 ""
0-
#385000
1K
1[
1-
#390000
b100 ""
0-
#395000
1!
b11 W
0[
b10 D
0K
1-
#400000
b101 ""
0-
#405000
1K
1H
1[
1-
#410000
b110 ""
0-
#415000
b100 W
0[
1I
b11 D
0K
1-
#420000
b111 ""
0-
#425000
1K
1[
1-
#430000
b1000 ""
0-
#435000
0!
b101 W
0[
b100 D
0K
1-
#440000
b1001 ""
0-
#445000
1K
0H
1[
1-
#450000
b1010 ""
0-
#455000
1!
b110 W
0[
0I
b101 D
0K
1-
#460000
b1011 ""
0-
#465000
1K
1H
1[
1-
#470000
b1100 ""
0-
#475000
b100 Z
0[
1I
b110 D
0K
1-
#480000
b1101 ""
0-
#485000
1K
1[
1-
#490000
b1110 ""
0-
#495000
0(
b0 Z
0[
b100 J
0K
1-
#500000
b1111 ""
0-
#505000
1K
b0 W
1-
#510000
b10000 ""
0-
#515000
b0 J
1'
1"
0K
1-
#520000
b1 t
b10001 ""
10
b10 6
0-
#525000
b0 D
0'
0"
1-
#530000
00
0-
