DSDL9/tcam_entry.v
`timescale 1ns/1ps
`default_nettype none

// One DATA_WIDTH-bit ternary memory entry.
// A 1 in stored_x_mask makes the corresponding stored bit a X.
module tcam_entry #(
    parameter integer DATA_WIDTH = 16
) (
    input  wire                  clk,
    input  wire                  reset,
    input  wire                  write_enable,
    input  wire [DATA_WIDTH-1:0] write_data,
    input  wire [DATA_WIDTH-1:0] write_x_mask,
    input  wire [DATA_WIDTH-1:0] search_data,
    output wire                  match
);
    reg [DATA_WIDTH-1:0] stored_data;
    reg [DATA_WIDTH-1:0] stored_x_mask;
    reg                  valid;

    wire [DATA_WIDTH-1:0] mismatched_bits;

    always @(posedge clk) begin
        if (reset) begin
            valid <= 1'b0;
        end else if (write_enable) begin
            stored_data <= write_data;
            stored_x_mask <= write_x_mask;
            valid <= 1'b1;
        end
    end

    // Masked positions are removed before checking for unequal bits.
    assign mismatched_bits = (search_data ^ stored_data) & ~stored_x_mask;
    assign match = valid && (mismatched_bits == {DATA_WIDTH{1'b0}});
endmodule

`default_nettype wire

DSDL9/final/quartus/tcam_no_loop.v
`timescale 1ns/1ps
`default_nettype none

// Parallel-write TCAM with an instance array and no for loop.
// The packed data/mask buses are split across entries; search_data is shared.
module tcam_no_loop #(
    parameter integer DATA_WIDTH = 4,
    parameter integer DEPTH = 4
) (
    input  wire                         clk,
    input  wire                         reset,
    input  wire [DEPTH-1:0]             write_enable,
    input  wire [DEPTH*DATA_WIDTH-1:0]  write_data,
    input  wire [DEPTH*DATA_WIDTH-1:0]  write_x_mask,
    input  wire [DATA_WIDTH-1:0]        search_data,
    output wire [DEPTH-1:0]             match_lines
);
    generate
        if (DATA_WIDTH < 1 || DEPTH < 1) begin : invalid_parameters
            initial $fatal(1, "TCAM requires DATA_WIDTH >= 1 and DEPTH >= 1");
        end else begin : valid_parameters
            tcam_entry #(.DATA_WIDTH(DATA_WIDTH)) entries [DEPTH-1:0] (
                .clk(clk),
                .reset(reset),
                .write_enable(write_enable),
                .write_data(write_data),
                .write_x_mask(write_x_mask),
                .search_data(search_data),
                .match(match_lines)
            );
        end
    endgenerate
endmodule

`default_nettype wire

DSDL9/tcam.v
`timescale 1ns/1ps
`default_nettype none

// Each enabled row stores its own data and X mask on the same rising edge. Meaning multiple registers with defined
// Data width on a single store.
// Row i uses write_data[i*DATA_WIDTH +: DATA_WIDTH] with the same mask slice.
module tcam #(
    parameter integer DATA_WIDTH = 16,
    parameter integer DEPTH = 16
) (
    input  wire                         clk,
    input  wire                         reset,
    input  wire [DEPTH-1:0]             write_enable,
    input  wire [DEPTH*DATA_WIDTH-1:0]  write_data,     // Data of all registers
    input  wire [DEPTH*DATA_WIDTH-1:0]  write_x_mask,   // X values for all registers
    input  wire [DATA_WIDTH-1:0]        search_data,    // Data we comparing with
    output wire [DEPTH-1:0]             match_lines     // Registers matched
);
    genvar row;

    generate
        if (DATA_WIDTH < 1 || DEPTH < 1) begin : invalid_parameters
            initial $fatal(1, "TCAM requires DATA_WIDTH >= 1 and DEPTH >= 1");
        end else begin : valid_parameters
            for (row = 0; row < DEPTH; row = row + 1) begin : entries
                tcam_entry #(.DATA_WIDTH(DATA_WIDTH)) entry (
                    .clk(clk),
                    .reset(reset),
                    .write_enable(write_enable[row]),
                    .write_data(write_data[row*DATA_WIDTH +: DATA_WIDTH]),
                    .write_x_mask(write_x_mask[row*DATA_WIDTH +: DATA_WIDTH]),
                    .search_data(search_data),
                    .match(match_lines[row])
                );
            end
        end
    endgenerate
endmodule

`default_nettype wire

DSDL9/final/tb/tb_tcam_3x5.v
`timescale 1ns/1ps
`default_nettype none

// 3 x 5 non-power-of-two depth
module tb_tcam_3x5;
    localparam integer DATA_WIDTH = 5;
    localparam integer DEPTH = 3;
    reg clk = 1'b0;
    reg reset = 1'b1;
    reg [DEPTH-1:0] write_enable = 0;
    reg [DEPTH*DATA_WIDTH-1:0] write_data = 0;
    reg [DEPTH*DATA_WIDTH-1:0] write_x_mask = 0;
    reg [DATA_WIDTH-1:0] search_data = 0;
    wire [DEPTH-1:0] match_loop;
    wire [DEPTH-1:0] match_no_loop;

    tcam #(.DATA_WIDTH(DATA_WIDTH), .DEPTH(DEPTH)) loop (
        .clk(clk), .reset(reset), .write_enable(write_enable),
        .write_data(write_data), .write_x_mask(write_x_mask),
        .search_data(search_data), .match_lines(match_loop)
    );
    tcam_no_loop #(.DATA_WIDTH(DATA_WIDTH), .DEPTH(DEPTH)) no_loop (
        .clk(clk), .reset(reset), .write_enable(write_enable),
        .write_data(write_data), .write_x_mask(write_x_mask),
        .search_data(search_data), .match_lines(match_no_loop)
    );

    always #5 clk = ~clk;

    task check_search;
        input [DATA_WIDTH-1:0] data;
        input [DEPTH-1:0] expected;
        begin
            search_data = data;
            #1;
            if (match_loop !== expected || match_no_loop !== expected)
                $fatal(1, "Search %h: expected %h, loop %h, no-loop %h",
                       data, expected, match_loop, match_no_loop);
            #9; // Keep each result visible in GTKWave.
        end
    endtask

    initial begin
        $dumpfile("build/tb_tcam_3x5.vcd");
        $dumpvars(0, tb_tcam_3x5);
        @(posedge clk);
        #1 reset = 1'b0;

        @(negedge clk);
        write_data = {5'b11111, 5'b10101, 5'b00001};
        write_enable = 3'b111;
        @(posedge clk);
        #1 write_enable = 3'b000;
        check_search(5'b00001, 3'b001);
        check_search(5'b10101, 3'b010);
        check_search(5'b11111, 3'b100);
        check_search(5'b00000, 3'b000);

        $display("PASS: 3 x 5 non-power-of-two depth (both implementations)");
        $finish;
    end
endmodule

`default_nettype wire

DSDL9/build/tb_tcam_3x5.vcd
$date
	Sat Sep 12 09:50:56 2026
$end
$version
	Icarus Verilog
$end
$timescale
	1ps
$end
$scope module tb_tcam_3x5 $end
$var wire 3 ! match_no_loop [2:0] $end
$var wire 3 " match_loop [2:0] $end
$var parameter 32 # DATA_WIDTH $end
$var parameter 32 $ DEPTH $end
$var reg 1 % clk $end
$var reg 1 & reset $end
$var reg 5 ' search_data [4:0] $end
$var reg 15 ( write_data [14:0] $end
$var reg 3 ) write_enable [2:0] $end
$var reg 15 * write_x_mask [14:0] $end
$scope module loop $end
$var wire 1 % clk $end
$var wire 1 & reset $end
$var wire 5 + search_data [4:0] $end
$var wire 15 , write_data [14:0] $end
$var wire 3 - write_enable [2:0] $end
$var wire 15 . write_x_mask [14:0] $end
$var wire 3 / match_lines [2:0] $end
$var parameter 32 0 DATA_WIDTH $end
$var parameter 32 1 DEPTH $end
$scope begin valid_parameters $end
$scope begin entries[0] $end
$var parameter 2 2 row $end
$scope module entry $end
$var wire 1 % clk $end
$var wire 1 3 match $end
$var wire 5 4 mismatched_bits [4:0] $end
$var wire 1 & reset $end
$var wire 5 5 search_data [4:0] $end
$var wire 5 6 write_data [4:0] $end
$var wire 1 7 write_enable $end
$var wire 5 8 write_x_mask [4:0] $end
$var parameter 32 9 DATA_WIDTH $end
$var reg 5 : stored_data [4:0] $end
$var reg 5 ; stored_x_mask [4:0] $end
$var reg 1 < valid $end
$upscope $end
$upscope $end
$scope begin entries[1] $end
$var parameter 2 = row $end
$scope module entry $end
$var wire 1 % clk $end
$var wire 1 > match $end
$var wire 5 ? mismatched_bits [4:0] $end
$var wire 1 & reset $end
$var wire 5 @ search_data [4:0] $end
$var wire 5 A write_data [4:0] $end
$var wire 1 B write_enable $end
$var wire 5 C write_x_mask [4:0] $end
$var parameter 32 D DATA_WIDTH $end
$var reg 5 E stored_data [4:0] $end
$var reg 5 F stored_x_mask [4:0] $end
$var reg 1 G valid $end
$upscope $end
$upscope $end
$scope begin entries[2] $end
$var parameter 3 H row $end
$scope module entry $end
$var wire 1 % clk $end
$var wire 1 I match $end
$var wire 5 J mismatched_bits [4:0] $end
$var wire 1 & reset $end
$var wire 5 K search_data [4:0] $end
$var wire 5 L write_data [4:0] $end
$var wire 1 M write_enable $end
$var wire 5 N write_x_mask [4:0] $end
$var parameter 32 O DATA_WIDTH $end
$var reg 5 P stored_data [4:0] $end
$var reg 5 Q stored_x_mask [4:0] $end
$var reg 1 R valid $end
$upscope $end
$upscope $end
$upscope $end
$upscope $end
$scope module no_loop $end
$var wire 1 % clk $end
$var wire 1 & reset $end
$var wire 5 S search_data [4:0] $end
$var wire 15 T write_data [14:0] $end
$var wire 3 U write_enable [2:0] $end
$var wire 15 V write_x_mask [14:0] $end
$var wire 3 W match_lines [2:0] $end
$var parameter 32 X DATA_WIDTH $end
$var parameter 32 Y DEPTH $end
$scope begin valid_parameters $end
$scope module entries[0] $end
$var wire 1 % clk $end
$var wire 1 Z match $end
$var wire 5 [ mismatched_bits [4:0] $end
$var wire 1 & reset $end
$var wire 5 \ search_data [4:0] $end
$var wire 5 ] write_data [4:0] $end
$var wire 1 ^ write_enable $end
$var wire 5 _ write_x_mask [4:0] $end
$var parameter 32 ` DATA_WIDTH $end
$var reg 5 a stored_data [4:0] $end
$var reg 5 b stored_x_mask [4:0] $end
$var reg 1 c valid $end
$upscope $end
$scope module entries[1] $end
$var wire 1 % clk $end
$var wire 1 d match $end
$var wire 5 e mismatched_bits [4:0] $end
$var wire 1 & reset $end
$var wire 5 f search_data [4:0] $end
$var wire 5 g write_data [4:0] $end
$var wire 1 h write_enable $end
$var wire 5 i write_x_mask [4:0] $end
$var parameter 32 j DATA_WIDTH $end
$var reg 5 k stored_data [4:0] $end
$var reg 5 l stored_x_mask [4:0] $end
$var reg 1 m valid $end
$upscope $end
$scope module entries[2] $end
$var wire 1 % clk $end
$var wire 1 n match $end
$var wire 5 o mismatched_bits [4:0] $end
$var wire 1 & reset $end
$var wire 5 p search_data [4:0] $end
$var wire 5 q write_data [4:0] $end
$var wire 1 r write_enable $end
$var wire 5 s write_x_mask [4:0] $end
$var parameter 32 t DATA_WIDTH $end
$var reg 5 u stored_data [4:0] $end
$var reg 5 v stored_x_mask [4:0] $end
$var reg 1 w valid $end
$upscope $end
$upscope $end
$upscope $end
$scope task check_search $end
$var reg 5 x data [4:0] $end
$var reg 3 y expected [2:0] $end
$upscope $end
$upscope $end
$enddefinitions $end
$comment Show the parameter values. $end
$dumpall
b101 t
b101 j
b101 `
b11 Y
b101 X
b101 O
b10 H
b101 D
b1 =
b101 9
b0 2
b11 1
b101 0
b11 $
b101 #
$end
#0
$dumpvars
bx y
bx x
xw
bx v
bx u
b0 s
0r
b0 q
b0 p
bx o
xn
xm
bx l
bx k
b0 i
0h
b0 g
b0 f
bx e
xd
xc
bx b
bx a
b0 _
0^
b0 ]
b0 \
bx [
xZ
bx W
b0 V
b0 U
b0 T
b0 S
xR
bx Q
bx P
b0 N
0M
b0 L
b0 K
bx J
xI
xG
bx F
bx E
b0 C
0B
b0 A
b0 @
bx ?
x>
x<
bx ;
bx :
b0 8
07
b0 6
b0 5
bx 4
x3
bx /
b0 .
b0 -
b0 ,
b0 +
b0 *
b0 )
b0 (
b0 '
1&
0%
bx "
bx !
$end
#5000
03
0>
b0 "
b0 /
0I
0Z
0d
b0 !
b0 W
0n
0<
0G
0R
0c
0m
0w
1%
#6000
0&
#10000
17
1B
1M
1^
1h
1r
b1 6
b10101 A
b11111 L
b1 ]
b10101 g
b11111 q
b111 )
b111 -
b111 U
b111111010100001 (
b111111010100001 ,
b111111010100001 T
0%
#15000
b11111 o
b10101 e
b1 [
b11111 J
b10101 ?
b1 4
0n
0d
b0 !
b0 W
0Z
0I
0>
b0 "
b0 /
03
1w
b0 v
b11111 u
1m
b0 l
b10101 k
1c
b0 b
b1 a
1R
b0 Q
b11111 P
1G
b0 F
b10101 E
1<
b0 ;
b1 :
1%
#16000
b1 "
b1 /
13
b1 !
b1 W
1Z
b0 4
b10100 ?
b11110 J
b0 [
b10100 e
b11110 o
07
0B
0M
0^
0h
0r
b1 '
b1 +
b1 5
b1 @
b1 K
b1 S
b1 \
b1 f
b1 p
b1 y
b1 x
b0 )
b0 -
b0 U
#20000
0%
#25000
1%
#26000
03
b10 "
b10 /
1>
0Z
b10 !
b10 W
1d
b10100 4
b0 ?
b1010 J
b10100 [
b0 e
b1010 o
b10101 '
b10101 +
b10101 5
b10101 @
b10101 K
b10101 S
b10101 \
b10101 f
b10101 p
b10 y
b10101 x
#30000
0%
#35000
1%
#36000
0>
b100 "
b100 /
1I
0d
b100 !
b100 W
1n
b11110 4
b1010 ?
b0 J
b11110 [
b1010 e
b0 o
b11111 '
b11111 +
b11111 5
b11111 @
b11111 K
b11111 S
b11111 \
b11111 f
b11111 p
b100 y
b11111 x
#40000
0%
#45000
1%
#46000
b0 "
b0 /
0I
b0 !
b0 W
0n
b1 4
b10101 ?
b11111 J
b1 [
b10101 e
b11111 o
b0 '
b0 +
b0 5
b0 @
b0 K
b0 S
b0 \
b0 f
b0 p
b0 y
b0 x
