DSDL9/tcam_entry.v
`timescale 1ns/1ps
`default_nettype none

// One DATA_WIDTH-bit ternary memory entry.
// A 1 in stored_x_mask makes the corresponding stored bit a X.
module tcam_entry #(
    parameter integer DATA_WIDTH = 16
) (
    input  wire                  clk,
    input  wire                  reset,
    input  wire                  write_enable,
    input  wire [DATA_WIDTH-1:0] write_data,
    input  wire [DATA_WIDTH-1:0] write_x_mask,
    input  wire [DATA_WIDTH-1:0] search_data,
    output wire                  match
);
    reg [DATA_WIDTH-1:0] stored_data;
    reg [DATA_WIDTH-1:0] stored_x_mask;
    reg                  valid;

    wire [DATA_WIDTH-1:0] mismatched_bits;

    always @(posedge clk) begin
        if (reset) begin
            valid <= 1'b0;
        end else if (write_enable) begin
            stored_data <= write_data;
            stored_x_mask <= write_x_mask;
            valid <= 1'b1;
        end
    end

    // Masked positions are removed before checking for unequal bits.
    assign mismatched_bits = (search_data ^ stored_data) & ~stored_x_mask;
    assign match = valid && (mismatched_bits == {DATA_WIDTH{1'b0}});
endmodule

`default_nettype wire

DSDL9/tcam.v
`timescale 1ns/1ps
`default_nettype none

// Parameterized ternary content-addressable memory.
// The defaults implement the required 16 entries of 16 ternary bits each. (16 register each 16 bits)
module tcam #(
    parameter integer DATA_WIDTH = 16, // Registers width
    parameter integer DEPTH = 16, // Register count
    parameter integer ADDR_WIDTH = (DEPTH <= 1) ? 1 : $clog2(DEPTH)
) (
    input  wire                  clk,
    input  wire                  reset,
    input  wire                  write_enable,
    input  wire [ADDR_WIDTH-1:0] write_address, // Which register to write on
    input  wire [DATA_WIDTH-1:0] write_data,    // What to write on the addressed register
    input  wire [DATA_WIDTH-1:0] write_x_mask,  // X bits
    input  wire [DATA_WIDTH-1:0] search_data,   // what we matching with
    output wire [DEPTH-1:0]      match_lines    // what matched
);

    genvar entry_index;

    generate
        for (entry_index = 0; entry_index < DEPTH; entry_index = entry_index + 1) begin : entries
            localparam [ADDR_WIDTH-1:0] ENTRY_ADDRESS = entry_index;

            tcam_entry #(
                .DATA_WIDTH(DATA_WIDTH)
            ) entry (
                .clk(clk),
                .reset(reset),
                .write_enable(write_enable && (write_address == ENTRY_ADDRESS)),
                .write_data(write_data),
                .write_x_mask(write_x_mask),
                .search_data(search_data),
                .match(match_lines[entry_index])
            );
        end
    endgenerate
endmodule

`default_nettype wire

DSDL9/tb_tcam_reset.v
`timescale 1ns/1ps
`default_nettype none

// Checks that reset invalidates stored entries so empty TCAM rows never match.
module tb_tcam_reset;
    localparam integer DATA_WIDTH = 4;
    localparam integer DEPTH = 2;
    localparam integer ADDR_WIDTH = 1;

    reg clk;
    reg reset;
    reg write_enable;
    reg [ADDR_WIDTH-1:0] write_address;
    reg [DATA_WIDTH-1:0] write_data;
    reg [DATA_WIDTH-1:0] write_x_mask;
    reg [DATA_WIDTH-1:0] search_data;
    wire [DEPTH-1:0] match_lines;

    tcam #(
        .DATA_WIDTH(DATA_WIDTH),
        .DEPTH(DEPTH)
    ) dut (
        .clk(clk),
        .reset(reset),
        .write_enable(write_enable),
        .write_address(write_address),
        .write_data(write_data),
        .write_x_mask(write_x_mask),
        .search_data(search_data),
        .match_lines(match_lines)
    );

    always #5 clk = ~clk;

    initial begin
        $dumpfile("build/tb_tcam_reset.vcd");
        $dumpvars(0, tb_tcam_reset);
    end

    initial begin
        clk = 1'b0;
        reset = 1'b1;
        write_enable = 1'b0;
        write_address = {ADDR_WIDTH{1'b0}};
        write_data = {DATA_WIDTH{1'b0}};
        write_x_mask = {DATA_WIDTH{1'b0}};
        search_data = 4'b1010;

        @(posedge clk);
        #1 reset = 1'b0;

        write_data = 4'b1010;
        write_enable = 1'b1;
        @(posedge clk);
        #1 write_enable = 1'b0;

        if (match_lines !== 2'b01)
            $fatal(1, "Test setup failed to create a valid match: %b", match_lines);

        #10; // Keep the valid entry visible before reset.
        reset = 1'b1;
        @(posedge clk);
        #1 reset = 1'b0;

        if (match_lines !== 2'b00)
            $fatal(1, "Reset left a TCAM entry valid: %b", match_lines);

        #10;
        $display("PASS: reset invalidates TCAM entries");
        $finish;
    end
endmodule

`default_nettype wire

DSDL9/build/tb_tcam_reset.vcd
$date
	Thu Sep 10 15:28:40 2026
$end
$version
	Icarus Verilog
$end
$timescale
	1ps
$end
$scope module tb_tcam_reset $end
$var wire 2 ! match_lines [1:0] $end
$var parameter 32 " ADDR_WIDTH $end
$var parameter 32 # DATA_WIDTH $end
$var parameter 32 $ DEPTH $end
$var reg 1 % clk $end
$var reg 1 & reset $end
$var reg 4 ' search_data [3:0] $end
$var reg 1 ( write_address $end
$var reg 4 ) write_data [3:0] $end
$var reg 1 * write_enable $end
$var reg 4 + write_x_mask [3:0] $end
$scope module dut $end
$var wire 1 % clk $end
$var wire 1 & reset $end
$var wire 4 , search_data [3:0] $end
$var wire 1 ( write_address $end
$var wire 4 - write_data [3:0] $end
$var wire 1 * write_enable $end
$var wire 4 . write_x_mask [3:0] $end
$var wire 2 / match_lines [1:0] $end
$var parameter 32 0 ADDR_WIDTH $end
$var parameter 32 1 DATA_WIDTH $end
$var parameter 32 2 DEPTH $end
$scope begin entries[0] $end
$var parameter 1 3 ENTRY_ADDRESS $end
$var parameter 2 4 entry_index $end
$scope module entry $end
$var wire 1 % clk $end
$var wire 1 5 match $end
$var wire 4 6 mismatched_bits [3:0] $end
$var wire 1 & reset $end
$var wire 4 7 search_data [3:0] $end
$var wire 4 8 write_data [3:0] $end
$var wire 1 9 write_enable $end
$var wire 4 : write_x_mask [3:0] $end
$var parameter 32 ; DATA_WIDTH $end
$var reg 4 < stored_data [3:0] $end
$var reg 4 = stored_x_mask [3:0] $end
$var reg 1 > valid $end
$upscope $end
$upscope $end
$scope begin entries[1] $end
$var parameter 1 ? ENTRY_ADDRESS $end
$var parameter 2 @ entry_index $end
$scope module entry $end
$var wire 1 % clk $end
$var wire 1 A match $end
$var wire 4 B mismatched_bits [3:0] $end
$var wire 1 & reset $end
$var wire 4 C search_data [3:0] $end
$var wire 4 D write_data [3:0] $end
$var wire 1 E write_enable $end
$var wire 4 F write_x_mask [3:0] $end
$var parameter 32 G DATA_WIDTH $end
$var reg 4 H stored_data [3:0] $end
$var reg 4 I stored_x_mask [3:0] $end
$var reg 1 J valid $end
$upscope $end
$upscope $end
$upscope $end
$upscope $end
$enddefinitions $end
$comment Show the parameter values. $end
$dumpall
b100 G
b1 @
1?
b100 ;
b0 4
03
b10 2
b100 1
b1 0
b10 $
b100 #
b1 "
$end
#0
$dumpvars
xJ
bx I
bx H
b0 F
0E
b0 D
b1010 C
bx B
xA
x>
bx =
bx <
b0 :
09
b0 8
b1010 7
bx 6
x5
bx /
b0 .
b0 -
b1010 ,
b0 +
0*
b0 )
0(
b1010 '
1&
0%
bx !
$end
#5000
05
b0 !
b0 /
0A
0>
0J
1%
#6000
19
1*
b1010 )
b1010 -
b1010 8
b1010 D
0&
#10000
0%
#15000
b0 6
b1 !
b1 /
15
1>
b0 =
b1010 <
1%
#16000
09
0*
#20000
0%
#25000
1%
#26000
1&
#30000
0%
#35000
b0 !
b0 /
05
0>
1%
#36000
0&
